Workbook

Sheet README
A1: Uepaki — Seller Acquisition Command Center
A3: The single operating tracker for seller acquisition. It supersedes the trackers inside the First 25/100/300 lists, the Segmentation workbook KPI sheet and the Activation Checklist tracker for day-to-day use (those remain reference material).
A4: PROSPECTS is pre-filled with the red-team-corrected "Golden 300 v2" (Waves 0–2) plus blank rows for Wave −1 friendly testers, existing-seller reactivation, inbound and peer introductions. One row per professional. Never duplicate a professional.
A5: Brown headers = pre-filled from the database (read-only). Dark headers = enter data (dates as yyyy-mm-dd; dropdowns where offered). Green headers = calculated — do not type.
A6: No phone numbers, emails or WhatsApp links are stored. Resolve the verified business route from the master database by Prospect ID at outreach time and re-check it is still published.
A7: Contactable ≠ consent. 0 prospects have opted in to marketing. WhatsApp only after the professional invites it; AiSensy templates only after a recorded opt-in (column "WhatsApp opt-in").
A8: ACTIVATED = Approval date + Profile complete date + Listing live date + Payout details date + Standing OK = Y.
A9: All thresholds in SETTINGS are diagnostic TEST thresholds — not Uepaki benchmarks. Replace with observed rates after Wave 0–1.
A10: Do not start any campaign while BLOCKERS shows open Critical gates for that campaign.
A11: Sheets: PROSPECTS · CAMPAIGNS · CAMPAIGN_DASHBOARD · KPI_FUNNEL · WEEKLY_COHORTS · BLOCKERS · BUDGET · SETTINGS · LISTS

Sheet SETTINGS
A1: Diagnostic TEST thresholds — not Uepaki benchmarks
A2: Setting | B2: Value | C2: Use
A3: Days after first contact for follow-up 1 | B3: 5 | C3: Next follow-up date
A4: Days after follow-up 1 for final note | B4: 7 | C4: Next follow-up date
A5: Days of silence after sequence before any re-approach | B5: 75 | C5: Next action
A6: Minimum cell size to read a rate | B6: 20 | C6: Dashboards: below this = "Too early"
A7: Reply rate: STOP / rework below | B7: 0.1 | C7: Campaign rule (after ≥ 40 delivered)
A8: Reply rate: SCALE at or above | B8: 0.2 | C8: Campaign rule
A9: Interested → Registered: investigate below | B9: 0.3 | C9: Conversion
A10: Registered → Approved: investigate below | B10: 0.7 | C10: Conversion
A11: Approved → Activated: investigate below | B11: 0.5 | C11: Conversion
A12: Bounce rate: STOP above | B12: 0.05 | C12: Data quality
A13: Opt-out / negative rate: STOP above | B13: 0.02 | C13: Compliance guardrail
A14: Days in a stage before STUCK | B14: 3 | C14: Onboarding alert
A15: Contacts needed before a campaign rule is applied | B15: 40 | C15: Campaign rule

Sheet PROSPECTS
A1: Rank (v2) | B1: Prospect ID | C1: Prospect (name as they use it) | D1: Category | E1: Segment | F1: City | G1: Tier | H1: Priority (OS) | I1: Red-team flags | J1: Recommended channel | K1: Public route reference | L1: Campaign | M1: Channel used | N1: Owner | O1: Contact date | P1: Follow-up 1 sent | Q1: Follow-up 2 sent | R1: Response date | S1: Response type | T1: Interest date | U1: GSTIN status | V1: Registration date | W1: KYC submitted date | X1: Approval date | Y1: Profile complete date | Z1: Listing live date | AA1: Payout details date | AB1: Standing OK (Y/N) | AC1: Transaction date | AD1: Consent: named (Y/N) | AE1: WhatsApp opt-in (Y/N, date) | AF1: Manual next follow-up | AG1: Notes | AH1: Activated | AI1: Activation date | AJ1: Stage | AK1: Next follow-up | AL1: Next action | AM1: Due | AN1: Days in stage | AO1: Alert
A2: 1 | B2: UPK2-FL-172 | C2: Corpora Studio | D2: Fashion & Lifestyle | E2: FL-CONTEMPORARY | F2: Delhi NCR | G2: A | H2: P0 | I2: stockist-listed | J2: Personal 1:1 email from founder/team to published business email | K2: https://corporastudio.in/pages/contact | L2: W0 Pilot | AH2: =IF(AND(B2="",C2=""),"",IF(AND(X2<>"",Y2<>"",Z2<>"",AA2<>"",AB2="Y"),"YES","no")) | AI2: =IF(AH2="YES",MAX(X2,Y2,Z2,AA2),"") | AJ2: =IF(AND(B2="",C2=""),"",IF(OR(S2="Not interested",S2="Opt-out / do not contact"),"X Declined / suppressed",IF(S2="Bounced / undeliverable","X Bounced — research",IF(AC2<>"","13 Transacting",IF(AH2="YES","12 ACTIVATED",IF(Z2<>"","11 Listing live",IF(Y2<>"","10 Profile complete",IF(X2<>"","9 Approved",IF(W2<>"","8 KYC submitted",IF(V2<>"","7 Registered",IF(T2<>"","5 Interested",IF(R2<>"","4 Responded",IF(O2<>"","2 Contacted","1 Not yet contacted"))))))))))))) | AK2: =IF(AF2<>"",AF2,IF(OR(O2="",R2<>"",LEFT(AJ2,1)="X"),"",IF(Q2<>"","",IF(P2<>"",P2+SETTINGS!$B$4,O2+SETTINGS!$B$3)))) | AL2: =IF(AJ2="","",IF(LEFT(AJ2,1)="X","None — do not contact",IF(AJ2="1 Not yet contacted","Verify route today, then send M1",IF(AND(R2="",Q2<>""),"Sequence complete — no contact before "&TEXT(Q2+SETTINGS!$B$5,"yyyy-mm-dd"),IF(AND(R2="",P2<>""),"Send final note (M4)",IF(R2="","Send follow-up (M2)",IF(AJ2="12 ACTIVATED","7-day check-in; consent & referral soft ask",IF(AJ2="13 Transacting","Repeat-activity support","Onboarding: move to next stage (see playbook §6)")))))))) | AM2: =IF(ISNUMBER(AK2),IF(AK2<=TODAY(),"DUE",""),"") | AN2: =IF(COUNT(O2,P2,Q2,R2,T2,V2,W2,X2,Y2,Z2,AA2,AC2)=0,"",TODAY()-MAX(O2,P2,Q2,R2,T2,V2,W2,X2,Y2,Z2,AA2,AC2)) | AO2: =IF(AJ2="","",IF(AND(T2<>"",U2<>"Active (verified)"),"GST: escalate (no tax advice)",IF(AND(IFERROR(VALUE(LEFT(AJ2,2)),0)>=5,AH2<>"YES",ISNUMBER(AN2),AN2>SETTINGS!$B$14),"STUCK in onboarding","")))
A3: 2 | B3: UPK2-FL-200 | C3: Akhl | D3: Fashion & Lifestyle | E3: FL-CONTEMPORARY | F3: Delhi NCR | G3: A | H3: P0 | I3: stockist-listed | J3: Personal 1:1 email from founder/team to published business email | K3: https://www.akhlstudio.com/contact | L3: W0 Pilot | AH3: =IF(AND(B3="",C3=""),"",IF(AND(X3<>"",Y3<>"",Z3<>"",AA3<>"",AB3="Y"),"YES","no")) | AI3: =IF(AH3="YES",MAX(X3,Y3,Z3,AA3),"") | AJ3: =IF(AND(B3="",C3=""),"",IF(OR(S3="Not interested",S3="Opt-out / do not contact"),"X Declined / suppressed",IF(S3="Bounced / undeliverable","X Bounced — research",IF(AC3<>"","13 Transacting",IF(AH3="YES","12 ACTIVATED",IF(Z3<>"","11 Listing live",IF(Y3<>"","10 Profile complete",IF(X3<>"","9 Approved",IF(W3<>"","8 KYC submitted",IF(V3<>"","7 Registered",IF(T3<>"","5 Interested",IF(R3<>"","4 Responded",IF(O3<>"","2 Contacted","1 Not yet contacted"))))))))))))) | AK3: =IF(AF3<>"",AF3,IF(OR(O3="",R3<>"",LEFT(AJ3,1)="X"),"",IF(Q3<>"","",IF(P3<>"",P3+SETTINGS!$B$4,O3+SETTINGS!$B$3)))) | AL3: =IF(AJ3="","",IF(LEFT(AJ3,1)="X","None — do not contact",IF(AJ3="1 Not yet contacted","Verify route today, then send M1",IF(AND(R3="",Q3<>""),"Sequence complete — no contact before "&TEXT(Q3+SETTINGS!$B$5,"yyyy-mm-dd"),IF(AND(R3="",P3<>""),"Send final note (M4)",IF(R3="","Send follow-up (M2)",IF(AJ3="12 ACTIVATED","7-day check-in; consent & referral soft ask",IF(AJ3="13 Transacting","Repeat-activity support","Onboarding: move to next stage (see playbook §6)")))))))) | AM3: =IF(ISNUMBER(AK3),IF(AK3<=TODAY(),"DUE",""),"") | AN3: =IF(COUNT(O3,P3,Q3,R3,T3,V3,W3,X3,Y3,Z3,AA3,AC3)=0,"",TODAY()-MAX(O3,P3,Q3,R3,T3,V3,W3,X3,Y3,Z3,AA3,AC3)) | AO3: =IF(AJ3="","",IF(AND(T3<>"",U3<>"Active (verified)"),"GST: escalate (no tax advice)",IF(AND(IFERROR(VALUE(LEFT(AJ3,2)),0)>=5,AH3<>"YES",ISNUMBER(AN3),AN3>SETTINGS!$B$14),"STUCK in onboarding","")))
A4: 3 | B4: UPK2-FL-173 | C4: Kamaali Couture | D4: Fashion & Lifestyle | E4: FL-CONTEMPORARY | F4: Delhi NCR | G4: B | H4: P0 | I4: stockist-listed | J4: Personal 1:1 email from founder/team to published business email | K4: https://kamaali.in/pages/contact-us-1 | L4: W0 Pilot | AH4: =IF(AND(B4="",C4=""),"",IF(AND(X4<>"",Y4<>"",Z4<>"",AA4<>"",AB4="Y"),"YES","no")) | AI4: =IF(AH4="YES",MAX(X4,Y4,Z4,AA4),"") | AJ4: =IF(AND(B4="",C4=""),"",IF(OR(S4="Not interested",S4="Opt-out / do not contact"),"X Declined / suppressed",IF(S4="Bounced / undeliverable","X Bounced — research",IF(AC4<>"","13 Transacting",IF(AH4="YES","12 ACTIVATED",IF(Z4<>"","11 Listing live",IF(Y4<>"","10 Profile complete",IF(X4<>"","9 Approved",IF(W4<>"","8 KYC submitted",IF(V4<>"","7 Registered",IF(T4<>"","5 Interested",IF(R4<>"","4 Responded",IF(O4<>"","2 Contacted","1 Not yet contacted"))))))))))))) | AK4: =IF(AF4<>"",AF4,IF(OR(O4="",R4<>"",LEFT(AJ4,1)="X"),"",IF(Q4<>"","",IF(P4<>"",P4+SETTINGS!$B$4,O4+SETTINGS!$B$3)))) | AL4: =IF(AJ4="","",IF(LEFT(AJ4,1)="X","None — do not contact",IF(AJ4="1 Not yet contacted","Verify route today, then send M1",IF(AND(R4="",Q4<>""),"Sequence complete — no contact before "&TEXT(Q4+SETTINGS!$B$5,"yyyy-mm-dd"),IF(AND(R4="",P4<>""),"Send final note (M4)",IF(R4="","Send follow-up (M2)",IF(AJ4="12 ACTIVATED","7-day check-in; consent & referral soft ask",IF(AJ4="13 Transacting","Repeat-activity support","Onboarding: move to next stage (see playbook §6)")))))))) | AM4: =IF(ISNUMBER(AK4),IF(AK4<=TODAY(),"DUE",""),"") | AN4: =IF(COUNT(O4,P4,Q4,R4,T4,V4,W4,X4,Y4,Z4,AA4,AC4)=0,"",TODAY()-MAX(O4,P4,Q4,R4,T4,V4,W4,X4,Y4,Z4,AA4,AC4)) | AO4: =IF(AJ4="","",IF(AND(T4<>"",U4<>"Active (verified)"),"GST: escalate (no tax advice)",IF(AND(IFERROR(VALUE(LEFT(AJ4,2)),0)>=5,AH4<>"YES",ISNUMBER(AN4),AN4>SETTINGS!$B$14),"STUCK in onboarding","")))
A5: 4 | B5: UPK2-FL-180 | C5: Ituvana | D5: Fashion & Lifestyle | E5: FL-JEWELLERY | F5: Delhi NCR | G5: B | H5: P0 | I5: stockist-listed | J5: Personal 1:1 email from founder/team to published business email | K5: https://www.ituvana.com/pages/contact-us | L5: W0 Pilot | AH5: =IF(AND(B5="",C5=""),"",IF(AND(X5<>"",Y5<>"",Z5<>"",AA5<>"",AB5="Y"),"YES","no")) | AI5: =IF(AH5="YES",MAX(X5,Y5,Z5,AA5),"") | AJ5: =IF(AND(B5="",C5=""),"",IF(OR(S5="Not interested",S5="Opt-out / do not contact"),"X Declined / suppressed",IF(S5="Bounced / undeliverable","X Bounced — research",IF(AC5<>"","13 Transacting",IF(AH5="YES","12 ACTIVATED",IF(Z5<>"","11 Listing live",IF(Y5<>"","10 Profile complete",IF(X5<>"","9 Approved",IF(W5<>"","8 KYC submitted",IF(V5<>"","7 Registered",IF(T5<>"","5 Interested",IF(R5<>"","4 Responded",IF(O5<>"","2 Contacted","1 Not yet contacted"))))))))))))) | AK5: =IF(AF5<>"",AF5,IF(OR(O5="",R5<>"",LEFT(AJ5,1)="X"),"",IF(Q5<>"","",IF(P5<>"",P5+SETTINGS!$B$4,O5+SETTINGS!$B$3)))) | AL5: =IF(AJ5="","",IF(LEFT(AJ5,1)="X","None — do not contact",IF(AJ5="1 Not yet contacted","Verify route today, then send M1",IF(AND(R5="",Q5<>""),"Sequence complete — no contact before "&TEXT(Q5+SETTINGS!$B$5,"yyyy-mm-dd"),IF(AND(R5="",P5<>""),"Send final note (M4)",IF(R5="","Send follow-up (M2)",IF(AJ5="12 ACTIVATED","7-day check-in; consent & referral soft ask",IF(AJ5="13 Transacting","Repeat-activity support","Onboarding: move to next stage (see playbook §6)")))))))) | AM5: =IF(ISNUMBER(AK5),IF(AK5<=TODAY(),"DUE",""),"") | AN5: =IF(COUNT(O5,P5,Q5,R5,T5,V5,W5,X5,Y5,Z5,AA5,AC5)=0,"",TODAY()-MAX(O5,P5,Q5,R5,T5,V5,W5,X5,Y5,Z5,AA5,AC5)) | AO5: =IF(AJ5="","",IF(AND(T5<>"",U5<>"Active (verified)"),"GST: escalate (no tax advice)",IF(AND(IFERROR(VALUE(LEFT(AJ5,2)),0)>=5,AH5<>"YES",ISNUMBER(AN5),AN5>SETTINGS!$B$14),"STUCK in onboarding","")))
A6: 5 | B6: UPK2-FL-273 | C6: Jigar Mali | D6: Fashion & Lifestyle | E6: FL-OCCASION-BRIDAL | F6: Delhi NCR | G6: A | H6: P0 | I6: stockist-listed | J6: Personal 1:1 email from founder/team to published business email | K6: https://jigarmali.com/pages/contact | L6: W0 Pilot | AH6: =IF(AND(B6="",C6=""),"",IF(AND(X6<>"",Y6<>"",Z6<>"",AA6<>"",AB6="Y"),"YES","no")) | AI6: =IF(AH6="YES",MAX(X6,Y6,Z6,AA6),"") | AJ6: =IF(AND(B6="",C6=""),"",IF(OR(S6="Not interested",S6="Opt-out / do not contact"),"X Declined / suppressed",IF(S6="Bounced / undeliverable","X Bounced — research",IF(AC6<>"","13 Transacting",IF(AH6="YES","12 ACTIVATED",IF(Z6<>"","11 Listing live",IF(Y6<>"","10 Profile complete",IF(X6<>"","9 Approved",IF(W6<>"","8 KYC submitted",IF(V6<>"","7 Registered",IF(T6<>"","5 Interested",IF(R6<>"","4 Responded",IF(O6<>"","2 Contacted","1 Not yet contacted"))))))))))))) | AK6: =IF(AF6<>"",AF6,IF(OR(O6="",R6<>"",LEFT(AJ6,1)="X"),"",IF(Q6<>"","",IF(P6<>"",P6+SETTINGS!$B$4,O6+SETTINGS!$B$3)))) | AL6: =IF(AJ6="","",IF(LEFT(AJ6,1)="X","None — do not contact",IF(AJ6="1 Not yet contacted","Verify route today, then send M1",IF(AND(R6="",Q6<>""),"Sequence complete — no contact before "&TEXT(Q6+SETTINGS!$B$5,"yyyy-mm-dd"),IF(AND(R6="",P6<>""),"Send final note (M4)",IF(R6="","Send follow-up (M2)",IF(AJ6="12 ACTIVATED","7-day check-in; consent & referral soft ask",IF(AJ6="13 Transacting","Repeat-activity support","Onboarding: move to next stage (see playbook §6)")))))))) | AM6: =IF(ISNUMBER(AK6),IF(AK6<=TODAY(),"DUE",""),"") | AN6: =IF(COUNT(O6,P6,Q6,R6,T6,V6,W6,X6,Y6,Z6,AA6,AC6)=0,"",TODAY()-MAX(O6,P6,Q6,R6,T6,V6,W6,X6,Y6,Z6,AA6,AC6)) | AO6: =IF(AJ6="","",IF(AND(T6<>"",U6<>"Active (verified)"),"GST: escalate (no tax advice)",IF(AND(IFERROR(VALUE(LEFT(AJ6,2)),0)>=5,AH6<>"YES",ISNUMBER(AN6),AN6>SETTINGS!$B$14),"STUCK in onboarding","")))
A7: 6 | B7: UPK2-FL-199 | C7: Thee Modern Roots | D7: Fashion & Lifestyle | E7: FL-OCCASION-BRIDAL | F7: Delhi NCR | G7: A | H7: P0 | I7: stockist-listed | J7: Personal 1:1 email from founder/team to published business email | K7: https://theemodernroots.com/pages/contact | L7: W0 Pilot | AH7: =IF(AND(B7="",C7=""),"",IF(AND(X7<>"",Y7<>"",Z7<>"",AA7<>"",AB7="Y"),"YES","no")) | AI7: =IF(AH7="YES",MAX(X7,Y7,Z7,AA7),"") | AJ7: =IF(AND(B7="",C7=""),"",IF(OR(S7="Not interested",S7="Opt-out / do not contact"),"X Declined / suppressed",IF(S7="Bounced / undeliverable","X Bounced — research",IF(AC7<>"","13 Transacting",IF(AH7="YES","12 ACTIVATED",IF(Z7<>"","11 Listing live",IF(Y7<>"","10 Profile complete",IF(X7<>"","9 Approved",IF(W7<>"","8 KYC submitted",IF(V7<>"","7 Registered",IF(T7<>"","5 Interested",IF(R7<>"","4 Responded",IF(O7<>"","2 Contacted","1 Not yet contacted"))))))))))))) | AK7: =IF(AF7<>"",AF7,IF(OR(O7="",R7<>"",LEFT(AJ7,1)="X"),"",IF(Q7<>"","",IF(P7<>"",P7+SETTINGS!$B$4,O7+SETTINGS!$B$3)))) | AL7: =IF(AJ7="","",IF(LEFT(AJ7,1)="X","None — do not contact",IF(AJ7="1 Not yet contacted","Verify route today, then send M1",IF(AND(R7="",Q7<>""),"Sequence complete — no contact before "&TEXT(Q7+SETTINGS!$B$5,"yyyy-mm-dd"),IF(AND(R7="",P7<>""),"Send final note (M4)",IF(R7="","Send follow-up (M2)",IF(AJ7="12 ACTIVATED","7-day check-in; consent & referral soft ask",IF(AJ7="13 Transacting","Repeat-activity support","Onboarding: move to next stage (see playbook §6)")))))))) | AM7: =IF(ISNUMBER(AK7),IF(AK7<=TODAY(),"DUE",""),"") | AN7: =IF(COUNT(O7,P7,Q7,R7,T7,V7,W7,X7,Y7,Z7,AA7,AC7)=0,"",TODAY()-MAX(O7,P7,Q7,R7,T7,V7,W7,X7,Y7,Z7,AA7,AC7)) | AO7: =IF(AJ7="","",IF(AND(T7<>"",U7<>"Active (verified)"),"GST: escalate (no tax advice)",IF(AND(IFERROR(VALUE(LEFT(AJ7,2)),0)>=5,AH7<>"YES",ISNUMBER(AN7),AN7>SETTINGS!$B$14),"STUCK in onboarding","")))
A8: 7 | B8: UPK2-SD-290 | C8: Parman Designs | D8: Space & Design | E8: SD-PRODUCT-MAKER | F8: Delhi NCR | G8: A | H8: P0 | I8: under-discovered | J8: Personal 1:1 email from founder/team to published business email | K8: https://www.parmandesigns.com/ | L8: W0 Pilot | AH8: =IF(AND(B8="",C8=""),"",IF(AND(X8<>"",Y8<>"",Z8<>"",AA8<>"",AB8="Y"),"YES","no")) | AI8: =IF(AH8="YES",MAX(X8,Y8,Z8,AA8),"") | AJ8: =IF(AND(B8="",C8=""),"",IF(OR(S8="Not interested",S8="Opt-out / do not contact"),"X Declined / suppressed",IF(S8="Bounced / undeliverable","X Bounced — research",IF(AC8<>"","13 Transacting",IF(AH8="YES","12 ACTIVATED",IF(Z8<>"","11 Listing live",IF(Y8<>"","10 Profile complete",IF(X8<>"","9 Approved",IF(W8<>"","8 KYC submitted",IF(V8<>"","7 Registered",IF(T8<>"","5 Interested",IF(R8<>"","4 Responded",IF(O8<>"","2 Contacted","1 Not yet contacted"))))))))))))) | AK8: =IF(AF8<>"",AF8,IF(OR(O8="",R8<>"",LEFT(AJ8,1)="X"),"",IF(Q8<>"","",IF(P8<>"",P8+SETTINGS!$B$4,O8+SETTINGS!$B$3)))) | AL8: =IF(AJ8="","",IF(LEFT(AJ8,1)="X","None — do not contact",IF(AJ8="1 Not yet contacted","Verify route today, then send M1",IF(AND(R8="",Q8<>""),"Sequence complete — no contact before "&TEXT(Q8+SETTINGS!$B$5,"yyyy-mm-dd"),IF(AND(R8="",P8<>""),"Send final note (M4)",IF(R8="","Send follow-up (M2)",IF(AJ8="12 ACTIVATED","7-day check-in; consent & referral soft ask",IF(AJ8="13 Transacting","Repeat-activity support","Onboarding: move to next stage (see playbook §6)")))))))) | AM8: =IF(ISNUMBER(AK8),IF(AK8<=TODAY(),"DUE",""),"") | AN8: =IF(COUNT(O8,P8,Q8,R8,T8,V8,W8,X8,Y8,Z8,AA8,AC8)=0,"",TODAY()-MAX(O8,P8,Q8,R8,T8,V8,W8,X8,Y8,Z8,AA8,AC8)) | AO8: =IF(AJ8="","",IF(AND(T8<>"",U8<>"Active (verified)"),"GST: escalate (no tax advice)",IF(AND(IFERROR(VALUE(LEFT(AJ8,2)),0)>=5,AH8<>"YES",ISNUMBER(AN8),AN8>SETTINGS!$B$14),"STUCK in onboarding","")))
A9: 8 | B9: UPK2-SD-292 | C9: Harshita Jhamtani Designs LLP | D9: Space & Design | E9: SD-PRODUCT-MAKER | F9: Mumbai | G9: A | H9: P0 | I9: under-discovered | J9: Personal 1:1 email from founder/team to published business email | K9: https://www.harshitajhamtani.com/ | L9: W0 Pilot | AH9: =IF(AND(B9="",C9=""),"",IF(AND(X9<>"",Y9<>"",Z9<>"",AA9<>"",AB9="Y"),"YES","no")) | AI9: =IF(AH9="YES",MAX(X9,Y9,Z9,AA9),"") | AJ9: =IF(AND(B9="",C9=""),"",IF(OR(S9="Not interested",S9="Opt-out / do not contact"),"X Declined / suppressed",IF(S9="Bounced / undeliverable","X Bounced — research",IF(AC9<>"","13 Transacting",IF(AH9="YES","12 ACTIVATED",IF(Z9<>"","11 Listing live",IF(Y9<>"","10 Profile complete",IF(X9<>"","9 Approved",IF(W9<>"","8 KYC submitted",IF(V9<>"","7 Registered",IF(T9<>"","5 Interested",IF(R9<>"","4 Responded",IF(O9<>"","2 Contacted","1 Not yet contacted"))))))))))))) | AK9: =IF(AF9<>"",AF9,IF(OR(O9="",R9<>"",LEFT(AJ9,1)="X"),"",IF(Q9<>"","",IF(P9<>"",P9+SETTINGS!$B$4,O9+SETTINGS!$B$3)))) | AL9: =IF(AJ9="","",IF(LEFT(AJ9,1)="X","None — do not contact",IF(AJ9="1 Not yet contacted","Verify route today, then send M1",IF(AND(R9="",Q9<>""),"Sequence complete — no contact before "&TEXT(Q9+SETTINGS!$B$5,"yyyy-mm-dd"),IF(AND(R9="",P9<>""),"Send final note (M4)",IF(R9="","Send follow-up (M2)",IF(AJ9="12 ACTIVATED","7-day check-in; consent & referral soft ask",IF(AJ9="13 Transacting","Repeat-activity support","Onboarding: move to next stage (see playbook §6)")))))))) | AM9: =IF(ISNUMBER(AK9),IF(AK9<=TODAY(),"DUE",""),"") | AN9: =IF(COUNT(O9,P9,Q9,R9,T9,V9,W9,X9,Y9,Z9,AA9,AC9)=0,"",TODAY()-MAX(O9,P9,Q9,R9,T9,V9,W9,X9,Y9,Z9,AA9,AC9)) | AO9: =IF(AJ9="","",IF(AND(T9<>"",U9<>"Active (verified)"),"GST: escalate (no tax advice)",IF(AND(IFERROR(VALUE(LEFT(AJ9,2)),0)>=5,AH9<>"YES",ISNUMBER(AN9),AN9>SETTINGS!$B$14),"STUCK in onboarding","")))
A10: 9 | B10: UPK2-SD-291 | C10: LumeHaus | D10: Space & Design | E10: SD-PRODUCT-MAKER | F10: Delhi NCR | G10: A | H10: P0 | I10: under-discovered | J10: Personal 1:1 email from founder/team to published business email | K10: https://lumehaus.in/ | L10: W0 Pilot | AH10: =IF(AND(B10="",C10=""),"",IF(AND(X10<>"",Y10<>"",Z10<>"",AA10<>"",AB10="Y"),"YES","no")) | AI10: =IF(AH10="YES",MAX(X10,Y10,Z10,AA10),"") | AJ10: =IF(AND(B10="",C10=""),"",IF(OR(S10="Not interested",S10="Opt-out / do not contact"),"X Declined / suppressed",IF(S10="Bounced / undeliverable","X Bounced — research",IF(AC10<>"","13 Transacting",IF(AH10="YES","12 ACTIVATED",IF(Z10<>"","11 Listing live",IF(Y10<>"","10 Profile complete",IF(X10<>"","9 Approved",IF(W10<>"","8 KYC submitted",IF(V10<>"","7 Registered",IF(T10<>"","5 Interested",IF(R10<>"","4 Responded",IF(O10<>"","2 Contacted","1 Not yet contacted"))))))))))))) | AK10: =IF(AF10<>"",AF10,IF(OR(O10="",R10<>"",LEFT(AJ10,1)="X"),"",IF(Q10<>"","",IF(P10<>"",P10+SETTINGS!$B$4,O10+SETTINGS!$B$3)))) | AL10: =IF(AJ10="","",IF(LEFT(AJ10,1)="X","None — do not contact",IF(AJ10="1 Not yet contacted","Verify route today, then send M1",IF(AND(R10="",Q10<>""),"Sequence complete — no contact before "&TEXT(Q10+SETTINGS!$B$5,"yyyy-mm-dd"),IF(AND(R10="",P10<>""),"Send final note (M4)",IF(R10="","Send follow-up (M2)",IF(AJ10="12 ACTIVATED","7-day check-in; consent & referral soft ask",IF(AJ10="13 Transacting","Repeat-activity support","Onboarding: move to next stage (see playbook §6)")))))))) | AM10: =IF(ISNUMBER(AK10),IF(AK10<=TODAY(),"DUE",""),"") | AN10: =IF(COUNT(O10,P10,Q10,R10,T10,V10,W10,X10,Y10,Z10,AA10,AC10)=0,"",TODAY()-MAX(O10,P10,Q10,R10,T10,V10,W10,X10,Y10,Z10,AA10,AC10)) | AO10: =IF(AJ10="","",IF(AND(T10<>"",U10<>"Active (verified)"),"GST: escalate (no tax advice)",IF(AND(IFERROR(VALUE(LEFT(AJ10,2)),0)>=5,AH10<>"YES",ISNUMBER(AN10),AN10>SETTINGS!$B$14),"STUCK in onboarding","")))
A11: 10 | B11: UPK2-SD-018 | C11: Saaz Design Studio | D11: Space & Design | E11: SD-ARCHITECTURE | F11: Delhi NCR | G11: A | H11: P0 | I11: under-discovered | J11: Personal 1:1 email from founder/team to published business email | K11: https://www.saazdesignstudio.com/ | L11: W0 Pilot | AH11: =IF(AND(B11="",C11=""),"",IF(AND(X11<>"",Y11<>"",Z11<>"",AA11<>"",AB11="Y"),"YES","no")) | AI11: =IF(AH11="YES",MAX(X11,Y11,Z11,AA11),"") | AJ11: =IF(AND(B11="",C11=""),"",IF(OR(S11="Not interested",S11="Opt-out / do not contact"),"X Declined / suppressed",IF(S11="Bounced / undeliverable","X Bounced — research",IF(AC11<>"","13 Transacting",IF(AH11="YES","12 ACTIVATED",IF(Z11<>"","11 Listing live",IF(Y11<>"","10 Profile complete",IF(X11<>"","9 Approved",IF(W11<>"","8 KYC submitted",IF(V11<>"","7 Registered",IF(T11<>"","5 Interested",IF(R11<>"","4 Responded",IF(O11<>"","2 Contacted","1 Not yet contacted"))))))))))))) | AK11: =IF(AF11<>"",AF11,IF(OR(O11="",R11<>"",LEFT(AJ11,1)="X"),"",IF(Q11<>"","",IF(P11<>"",P11+SETTINGS!$B$4,O11+SETTINGS!$B$3)))) | AL11: =IF(AJ11="","",IF(LEFT(AJ11,1)="X","None — do not contact",IF(AJ11="1 Not yet contacted","Verify route today, then send M1",IF(AND(R11="",Q11<>""),"Sequence complete — no contact before "&TEXT(Q11+SETTINGS!$B$5,"yyyy-mm-dd"),IF(AND(R11="",P11<>""),"Send final note (M4)",IF(R11="","Send follow-up (M2)",IF(AJ11="12 ACTIVATED","7-day check-in; consent & referral soft ask",IF(AJ11="13 Transacting","Repeat-activity support","Onboarding: move to next stage (see playbook §6)")))))))) | AM11: =IF(ISNUMBER(AK11),IF(AK11<=TODAY(),"DUE",""),"") | AN11: =IF(COUNT(O11,P11,Q11,R11,T11,V11,W11,X11,Y11,Z11,AA11,AC11)=0,"",TODAY()-MAX(O11,P11,Q11,R11,T11,V11,W11,X11,Y11,Z11,AA11,AC11)) | AO11: =IF(AJ11="","",IF(AND(T11<>"",U11<>"Active (verified)"),"GST: escalate (no tax advice)",IF(AND(IFERROR(VALUE(LEFT(AJ11,2)),0)>=5,AH11<>"YES",ISNUMBER(AN11),AN11>SETTINGS!$B$14),"STUCK in onboarding","")))
A12: 11 | B12: UPK2-SD-009 | C12: Studio Dot | D12: Space & Design | E12: SD-INTERIOR | F12: Delhi NCR | G12: A | H12: P0 | I12: under-discovered | J12: Personal 1:1 email from founder/team to published business email | K12: https://www.studiodot.co.in/contact | L12: W0 Pilot | AH12: =IF(AND(B12="",C12=""),"",IF(AND(X12<>"",Y12<>"",Z12<>"",AA12<>"",AB12="Y"),"YES","no")) | AI12: =IF(AH12="YES",MAX(X12,Y12,Z12,AA12),"") | AJ12: =IF(AND(B12="",C12=""),"",IF(OR(S12="Not interested",S12="Opt-out / do not contact"),"X Declined / suppressed",IF(S12="Bounced / undeliverable","X Bounced — research",IF(AC12<>"","13 Transacting",IF(AH12="YES","12 ACTIVATED",IF(Z12<>"","11 Listing live",IF(Y12<>"","10 Profile complete",IF(X12<>"","9 Approved",IF(W12<>"","8 KYC submitted",IF(V12<>"","7 Registered",IF(T12<>"","5 Interested",IF(R12<>"","4 Responded",IF(O12<>"","2 Contacted","1 Not yet contacted"))))))))))))) | AK12: =IF(AF12<>"",AF12,IF(OR(O12="",R12<>"",LEFT(AJ12,1)="X"),"",IF(Q12<>"","",IF(P12<>"",P12+SETTINGS!$B$4,O12+SETTINGS!$B$3)))) | AL12: =IF(AJ12="","",IF(LEFT(AJ12,1)="X","None — do not contact",IF(AJ12="1 Not yet contacted","Verify route today, then send M1",IF(AND(R12="",Q12<>""),"Sequence complete — no contact before "&TEXT(Q12+SETTINGS!$B$5,"yyyy-mm-dd"),IF(AND(R12="",P12<>""),"Send final note (M4)",IF(R12="","Send follow-up (M2)",IF(AJ12="12 ACTIVATED","7-day check-in; consent & referral soft ask",IF(AJ12="13 Transacting","Repeat-activity support","Onboarding: move to next stage (see playbook §6)")))))))) | AM12: =IF(ISNUMBER(AK12),IF(AK12<=TODAY(),"DUE",""),"") | AN12: =IF(COUNT(O12,P12,Q12,R12,T12,V12,W12,X12,Y12,Z12,AA12,AC12)=0,"",TODAY()-MAX(O12,P12,Q12,R12,T12,V12,W12,X12,Y12,Z12,AA12,AC12)) | AO12: =IF(AJ12="","",IF(AND(T12<>"",U12<>"Active (verified)"),"GST: escalate (no tax advice)",IF(AND(IFERROR(VALUE(LEFT(AJ12,2)),0)>=5,AH12<>"YES",ISNUMBER(AN12),AN12>SETTINGS!$B$14),"STUCK in onboarding","")))
A13: 12 | B13: UPK2-SD-003 | C13: Navrasa | D13: Space & Design | E13: SD-INTERIOR | F13: Delhi NCR | G13: B | H13: P0 | J13: Personal 1:1 email from founder/team to published business email | K13: https://nav-rasa.com/ | L13: W0 Pilot | AH13: =IF(AND(B13="",C13=""),"",IF(AND(X13<>"",Y13<>"",Z13<>"",AA13<>"",AB13="Y"),"YES","no")) | AI13: =IF(AH13="YES",MAX(X13,Y13,Z13,AA13),"") | AJ13: =IF(AND(B13="",C13=""),"",IF(OR(S13="Not interested",S13="Opt-out / do not contact"),"X Declined / suppressed",IF(S13="Bounced / undeliverable","X Bounced — research",IF(AC13<>"","13 Transacting",IF(AH13="YES","12 ACTIVATED",IF(Z13<>"","11 Listing live",IF(Y13<>"","10 Profile complete",IF(X13<>"","9 Approved",IF(W13<>"","8 KYC submitted",IF(V13<>"","7 Registered",IF(T13<>"","5 Interested",IF(R13<>"","4 Responded",IF(O13<>"","2 Contacted","1 Not yet contacted"))))))))))))) | AK13: =IF(AF13<>"",AF13,IF(OR(O13="",R13<>"",LEFT(AJ13,1)="X"),"",IF(Q13<>"","",IF(P13<>"",P13+SETTINGS!$B$4,O13+SETTINGS!$B$3)))) | AL13: =IF(AJ13="","",IF(LEFT(AJ13,1)="X","None — do not contact",IF(AJ13="1 Not yet contacted","Verify route today, then send M1",IF(AND(R13="",Q13<>""),"Sequence complete — no contact before "&TEXT(Q13+SETTINGS!$B$5,"yyyy-mm-dd"),IF(AND(R13="",P13<>""),"Send final note (M4)",IF(R13="","Send follow-up (M2)",IF(AJ13="12 ACTIVATED","7-day check-in; consent & referral soft ask",IF(AJ13="13 Transacting","Repeat-activity support","Onboarding: move to next stage (see playbook §6)")))))))) | AM13: =IF(ISNUMBER(AK13),IF(AK13<=TODAY(),"DUE",""),"") | AN13: =IF(COUNT(O13,P13,Q13,R13,T13,V13,W13,X13,Y13,Z13,AA13,AC13)=0,"",TODAY()-MAX(O13,P13,Q13,R13,T13,V13,W13,X13,Y13,Z13,AA13,AC13)) | AO13: =IF(AJ13="","",IF(AND(T13<>"",U13<>"Active (verified)"),"GST: escalate (no tax advice)",IF(AND(IFERROR(VALUE(LEFT(AJ13,2)),0)>=5,AH13<>"YES",ISNUMBER(AN13),AN13>SETTINGS!$B$14),"STUCK in onboarding","")))
A14: 13 | B14: UPK2-DV-006 | C14: Inkyhand | D14: Digital & Visual Arts | E14: DV-CALLIGRAPHY-STATIONERY | F14: Delhi NCR | G14: A | H14: P0 | I14: under-discovered | J14: Personal 1:1 email from founder/team to published business email | K14: https://www.inkyhand.com/ | L14: W0 Pilot | AH14: =IF(AND(B14="",C14=""),"",IF(AND(X14<>"",Y14<>"",Z14<>"",AA14<>"",AB14="Y"),"YES","no")) | AI14: =IF(AH14="YES",MAX(X14,Y14,Z14,AA14),"") | AJ14: =IF(AND(B14="",C14=""),"",IF(OR(S14="Not interested",S14="Opt-out / do not contact"),"X Declined / suppressed",IF(S14="Bounced / undeliverable","X Bounced — research",IF(AC14<>"","13 Transacting",IF(AH14="YES","12 ACTIVATED",IF(Z14<>"","11 Listing live",IF(Y14<>"","10 Profile complete",IF(X14<>"","9 Approved",IF(W14<>"","8 KYC submitted",IF(V14<>"","7 Registered",IF(T14<>"","5 Interested",IF(R14<>"","4 Responded",IF(O14<>"","2 Contacted","1 Not yet contacted"))))))))))))) | AK14: =IF(AF14<>"",AF14,IF(OR(O14="",R14<>"",LEFT(AJ14,1)="X"),"",IF(Q14<>"","",IF(P14<>"",P14+SETTINGS!$B$4,O14+SETTINGS!$B$3)))) | AL14: =IF(AJ14="","",IF(LEFT(AJ14,1)="X","None — do not contact",IF(AJ14="1 Not yet contacted","Verify route today, then send M1",IF(AND(R14="",Q14<>""),"Sequence complete — no contact before "&TEXT(Q14+SETTINGS!$B$5,"yyyy-mm-dd"),IF(AND(R14="",P14<>""),"Send final note (M4)",IF(R14="","Send follow-up (M2)",IF(AJ14="12 ACTIVATED","7-day check-in; consent & referral soft ask",IF(AJ14="13 Transacting","Repeat-activity support","Onboarding: move to next stage (see playbook §6)")))))))) | AM14: =IF(ISNUMBER(AK14),IF(AK14<=TODAY(),"DUE",""),"") | AN14: =IF(COUNT(O14,P14,Q14,R14,T14,V14,W14,X14,Y14,Z14,AA14,AC14)=0,"",TODAY()-MAX(O14,P14,Q14,R14,T14,V14,W14,X14,Y14,Z14,AA14,AC14)) | AO14: =IF(AJ14="","",IF(AND(T14<>"",U14<>"Active (verified)"),"GST: escalate (no tax advice)",IF(AND(IFERROR(VALUE(LEFT(AJ14,2)),0)>=5,AH14<>"YES",ISNUMBER(AN14),AN14>SETTINGS!$B$14),"STUCK in onboarding","")))
A15: 14 | B15: UPK2-DV-034 | C15: Presentable | D15: Digital & Visual Arts | E15: DV-DESIGN-STUDIO | F15: Delhi NCR | G15: B | H15: P0 | J15: Personal 1:1 email from founder/team to published business email | K15: https://www.makepresentable.com/contact | L15: W0 Pilot | AH15: =IF(AND(B15="",C15=""),"",IF(AND(X15<>"",Y15<>"",Z15<>"",AA15<>"",AB15="Y"),"YES","no")) | AI15: =IF(AH15="YES",MAX(X15,Y15,Z15,AA15),"") | AJ15: =IF(AND(B15="",C15=""),"",IF(OR(S15="Not interested",S15="Opt-out / do not contact"),"X Declined / suppressed",IF(S15="Bounced / undeliverable","X Bounced — research",IF(AC15<>"","13 Transacting",IF(AH15="YES","12 ACTIVATED",IF(Z15<>"","11 Listing live",IF(Y15<>"","10 Profile complete",IF(X15<>"","9 Approved",IF(W15<>"","8 KYC submitted",IF(V15<>"","7 Registered",IF(T15<>"","5 Interested",IF(R15<>"","4 Responded",IF(O15<>"","2 Contacted","1 Not yet contacted"))))))))))))) | AK15: =IF(AF15<>"",AF15,IF(OR(O15="",R15<>"",LEFT(AJ15,1)="X"),"",IF(Q15<>"","",IF(P15<>"",P15+SETTINGS!$B$4,O15+SETTINGS!$B$3)))) | AL15: =IF(AJ15="","",IF(LEFT(AJ15,1)="X","None — do not contact",IF(AJ15="1 Not yet contacted","Verify route today, then send M1",IF(AND(R15="",Q15<>""),"Sequence complete — no contact before "&TEXT(Q15+SETTINGS!$B$5,"yyyy-mm-dd"),IF(AND(R15="",P15<>""),"Send final note (M4)",IF(R15="","Send follow-up (M2)",IF(AJ15="12 ACTIVATED","7-day check-in; consent & referral soft ask",IF(AJ15="13 Transacting","Repeat-activity support","Onboarding: move to next stage (see playbook §6)")))))))) | AM15: =IF(ISNUMBER(AK15),IF(AK15<=TODAY(),"DUE",""),"") | AN15: =IF(COUNT(O15,P15,Q15,R15,T15,V15,W15,X15,Y15,Z15,AA15,AC15)=0,"",TODAY()-MAX(O15,P15,Q15,R15,T15,V15,W15,X15,Y15,Z15,AA15,AC15)) | AO15: =IF(AJ15="","",IF(AND(T15<>"",U15<>"Active (verified)"),"GST: escalate (no tax advice)",IF(AND(IFERROR(VALUE(LEFT(AJ15,2)),0)>=5,AH15<>"YES",ISNUMBER(AN15),AN15>SETTINGS!$B$14),"STUCK in onboarding","")))
A16: 15 | B16: UPK2-DV-003 | C16: Ink n Bliss | D16: Digital & Visual Arts | E16: DV-CALLIGRAPHY-STATIONERY | F16: Mumbai | G16: B | H16: P0 | J16: Personal 1:1 email from founder/team to published business email | K16: https://www.inknbliss.com/contact | L16: W0 Pilot | AH16: =IF(AND(B16="",C16=""),"",IF(AND(X16<>"",Y16<>"",Z16<>"",AA16<>"",AB16="Y"),"YES","no")) | AI16: =IF(AH16="YES",MAX(X16,Y16,Z16,AA16),"") | AJ16: =IF(AND(B16="",C16=""),"",IF(OR(S16="Not interested",S16="Opt-out / do not contact"),"X Declined / suppressed",IF(S16="Bounced / undeliverable","X Bounced — research",IF(AC16<>"","13 Transacting",IF(AH16="YES","12 ACTIVATED",IF(Z16<>"","11 Listing live",IF(Y16<>"","10 Profile complete",IF(X16<>"","9 Approved",IF(W16<>"","8 KYC submitted",IF(V16<>"","7 Registered",IF(T16<>"","5 Interested",IF(R16<>"","4 Responded",IF(O16<>"","2 Contacted","1 Not yet contacted"))))))))))))) | AK16: =IF(AF16<>"",AF16,IF(OR(O16="",R16<>"",LEFT(AJ16,1)="X"),"",IF(Q16<>"","",IF(P16<>"",P16+SETTINGS!$B$4,O16+SETTINGS!$B$3)))) | AL16: =IF(AJ16="","",IF(LEFT(AJ16,1)="X","None — do not contact",IF(AJ16="1 Not yet contacted","Verify route today, then send M1",IF(AND(R16="",Q16<>""),"Sequence complete — no contact before "&TEXT(Q16+SETTINGS!$B$5,"yyyy-mm-dd"),IF(AND(R16="",P16<>""),"Send final note (M4)",IF(R16="","Send follow-up (M2)",IF(AJ16="12 ACTIVATED","7-day check-in; consent & referral soft ask",IF(AJ16="13 Transacting","Repeat-activity support","Onboarding: move to next stage (see playbook §6)")))))))) | AM16: =IF(ISNUMBER(AK16),IF(AK16<=TODAY(),"DUE",""),"") | AN16: =IF(COUNT(O16,P16,Q16,R16,T16,V16,W16,X16,Y16,Z16,AA16,AC16)=0,"",TODAY()-MAX(O16,P16,Q16,R16,T16,V16,W16,X16,Y16,Z16,AA16,AC16)) | AO16: =IF(AJ16="","",IF(AND(T16<>"",U16<>"Active (verified)"),"GST: escalate (no tax advice)",IF(AND(IFERROR(VALUE(LEFT(AJ16,2)),0)>=5,AH16<>"YES",ISNUMBER(AN16),AN16>SETTINGS!$B$14),"STUCK in onboarding","")))
A17: 16 | B17: UPK2-BM-277 | C17: Ram Kumar Mehandi | D17: Beauty & Makeup | E17: BM-MEHENDI | F17: Delhi NCR | G17: A | H17: P0 | J17: Personal 1:1 email from founder/team to published business email | K17: https://ramkumarmehandi.com/landing/ | L17: W0 Pilot | AH17: =IF(AND(B17="",C17=""),"",IF(AND(X17<>"",Y17<>"",Z17<>"",AA17<>"",AB17="Y"),"YES","no")) | AI17: =IF(AH17="YES",MAX(X17,Y17,Z17,AA17),"") | AJ17: =IF(AND(B17="",C17=""),"",IF(OR(S17="Not interested",S17="Opt-out / do not contact"),"X Declined / suppressed",IF(S17="Bounced / undeliverable","X Bounced — research",IF(AC17<>"","13 Transacting",IF(AH17="YES","12 ACTIVATED",IF(Z17<>"","11 Listing live",IF(Y17<>"","10 Profile complete",IF(X17<>"","9 Approved",IF(W17<>"","8 KYC submitted",IF(V17<>"","7 Registered",IF(T17<>"","5 Interested",IF(R17<>"","4 Responded",IF(O17<>"","2 Contacted","1 Not yet contacted"))))))))))))) | AK17: =IF(AF17<>"",AF17,IF(OR(O17="",R17<>"",LEFT(AJ17,1)="X"),"",IF(Q17<>"","",IF(P17<>"",P17+SETTINGS!$B$4,O17+SETTINGS!$B$3)))) | AL17: =IF(AJ17="","",IF(LEFT(AJ17,1)="X","None — do not contact",IF(AJ17="1 Not yet contacted","Verify route today, then send M1",IF(AND(R17="",Q17<>""),"Sequence complete — no contact before "&TEXT(Q17+SETTINGS!$B$5,"yyyy-mm-dd"),IF(AND(R17="",P17<>""),"Send final note (M4)",IF(R17="","Send follow-up (M2)",IF(AJ17="12 ACTIVATED","7-day check-in; consent & referral soft ask",IF(AJ17="13 Transacting","Repeat-activity support","Onboarding: move to next stage (see playbook §6)")))))))) | AM17: =IF(ISNUMBER(AK17),IF(AK17<=TODAY(),"DUE",""),"") | AN17: =IF(COUNT(O17,P17,Q17,R17,T17,V17,W17,X17,Y17,Z17,AA17,AC17)=0,"",TODAY()-MAX(O17,P17,Q17,R17,T17,V17,W17,X17,Y17,Z17,AA17,AC17)) | AO17: =IF(AJ17="","",IF(AND(T17<>"",U17<>"Active (verified)"),"GST: escalate (no tax advice)",IF(AND(IFERROR(VALUE(LEFT(AJ17,2)),0)>=5,AH17<>"YES",ISNUMBER(AN17),AN17>SETTINGS!$B$14),"STUCK in onboarding","")))
A18: 17 | B18: UPK2-BM-163 | C18: Arun Mehandi | D18: Beauty & Makeup | E18: BM-MEHENDI | F18: Mumbai | G18: C | H18: P0 | J18: Personal 1:1 email from founder/team to published business email | K18: https://arunmehandi.com/ | L18: W0 Pilot | AH18: =IF(AND(B18="",C18=""),"",IF(AND(X18<>"",Y18<>"",Z18<>"",AA18<>"",AB18="Y"),"YES","no")) | AI18: =IF(AH18="YES",MAX(X18,Y18,Z18,AA18),"") | AJ18: =IF(AND(B18="",C18=""),"",IF(OR(S18="Not interested",S18="Opt-out / do not contact"),"X Declined / suppressed",IF(S18="Bounced / undeliverable","X Bounced — research",IF(AC18<>"","13 Transacting",IF(AH18="YES","12 ACTIVATED",IF(Z18<>"","11 Listing live",IF(Y18<>"","10 Profile complete",IF(X18<>"","9 Approved",IF(W18<>"","8 KYC submitted",IF(V18<>"","7 Registered",IF(T18<>"","5 Interested",IF(R18<>"","4 Responded",IF(O18<>"","2 Contacted","1 Not yet contacted"))))))))))))) | AK18: =IF(AF18<>"",AF18,IF(OR(O18="",R18<>"",LEFT(AJ18,1)="X"),"",IF(Q18<>"","",IF(P18<>"",P18+SETTINGS!$B$4,O18+SETTINGS!$B$3)))) | AL18: =IF(AJ18="","",IF(LEFT(AJ18,1)="X","None — do not contact",IF(AJ18="1 Not yet contacted","Verify route today, then send M1",IF(AND(R18="",Q18<>""),"Sequence complete — no contact before "&TEXT(Q18+SETTINGS!$B$5,"yyyy-mm-dd"),IF(AND(R18="",P18<>""),"Send final note (M4)",IF(R18="","Send follow-up (M2)",IF(AJ18="12 ACTIVATED","7-day check-in; consent & referral soft ask",IF(AJ18="13 Transacting","Repeat-activity support","Onboarding: move to next stage (see playbook §6)")))))))) | AM18: =IF(ISNUMBER(AK18),IF(AK18<=TODAY(),"DUE",""),"") | AN18: =IF(COUNT(O18,P18,Q18,R18,T18,V18,W18,X18,Y18,Z18,AA18,AC18)=0,"",TODAY()-MAX(O18,P18,Q18,R18,T18,V18,W18,X18,Y18,Z18,AA18,AC18)) | AO18: =IF(AJ18="","",IF(AND(T18<>"",U18<>"Active (verified)"),"GST: escalate (no tax advice)",IF(AND(IFERROR(VALUE(LEFT(AJ18,2)),0)>=5,AH18<>"YES",ISNUMBER(AN18),AN18>SETTINGS!$B$14),"STUCK in onboarding","")))
A19: 18 | B19: UPK2-BM-178 | C19: Himani Bhandula Makeup Artist | D19: Beauty & Makeup | E19: BM-INDEPENDENT-MUA | F19: Delhi NCR | G19: B | H19: P0 | J19: 1:1 message via own-website contact form | K19: https://himanibhandula.com/contact/ | L19: W0 Pilot | AH19: =IF(AND(B19="",C19=""),"",IF(AND(X19<>"",Y19<>"",Z19<>"",AA19<>"",AB19="Y"),"YES","no")) | AI19: =IF(AH19="YES",MAX(X19,Y19,Z19,AA19),"") | AJ19: =IF(AND(B19="",C19=""),"",IF(OR(S19="Not interested",S19="Opt-out / do not contact"),"X Declined / suppressed",IF(S19="Bounced / undeliverable","X Bounced — research",IF(AC19<>"","13 Transacting",IF(AH19="YES","12 ACTIVATED",IF(Z19<>"","11 Listing live",IF(Y19<>"","10 Profile complete",IF(X19<>"","9 Approved",IF(W19<>"","8 KYC submitted",IF(V19<>"","7 Registered",IF(T19<>"","5 Interested",IF(R19<>"","4 Responded",IF(O19<>"","2 Contacted","1 Not yet contacted"))))))))))))) | AK19: =IF(AF19<>"",AF19,IF(OR(O19="",R19<>"",LEFT(AJ19,1)="X"),"",IF(Q19<>"","",IF(P19<>"",P19+SETTINGS!$B$4,O19+SETTINGS!$B$3)))) | AL19: =IF(AJ19="","",IF(LEFT(AJ19,1)="X","None — do not contact",IF(AJ19="1 Not yet contacted","Verify route today, then send M1",IF(AND(R19="",Q19<>""),"Sequence complete — no contact before "&TEXT(Q19+SETTINGS!$B$5,"yyyy-mm-dd"),IF(AND(R19="",P19<>""),"Send final note (M4)",IF(R19="","Send follow-up (M2)",IF(AJ19="12 ACTIVATED","7-day check-in; consent & referral soft ask",IF(AJ19="13 Transacting","Repeat-activity support","Onboarding: move to next stage (see playbook §6)")))))))) | AM19: =IF(ISNUMBER(AK19),IF(AK19<=TODAY(),"DUE",""),"") | AN19: =IF(COUNT(O19,P19,Q19,R19,T19,V19,W19,X19,Y19,Z19,AA19,AC19)=0,"",TODAY()-MAX(O19,P19,Q19,R19,T19,V19,W19,X19,Y19,Z19,AA19,AC19)) | AO19: =IF(AJ19="","",IF(AND(T19<>"",U19<>"Active (verified)"),"GST: escalate (no tax advice)",IF(AND(IFERROR(VALUE(LEFT(AJ19,2)),0)>=5,AH19<>"YES",ISNUMBER(AN19),AN19>SETTINGS!$B$14),"STUCK in onboarding","")))
A20: 19 | B20: UPK2-BM-208 | C20: Roopali Talwar Makeup Artist | D20: Beauty & Makeup | E20: BM-INDEPENDENT-MUA | F20: Delhi NCR | G20: B | H20: P0 | J20: 1:1 message via own-website contact form | K20: https://roopalitalwar.com/ | L20: W0 Pilot | AH20: =IF(AND(B20="",C20=""),"",IF(AND(X20<>"",Y20<>"",Z20<>"",AA20<>"",AB20="Y"),"YES","no")) | AI20: =IF(AH20="YES",MAX(X20,Y20,Z20,AA20),"") | AJ20: =IF(AND(B20="",C20=""),"",IF(OR(S20="Not interested",S20="Opt-out / do not contact"),"X Declined / suppressed",IF(S20="Bounced / undeliverable","X Bounced — research",IF(AC20<>"","13 Transacting",IF(AH20="YES","12 ACTIVATED",IF(Z20<>"","11 Listing live",IF(Y20<>"","10 Profile complete",IF(X20<>"","9 Approved",IF(W20<>"","8 KYC submitted",IF(V20<>"","7 Registered",IF(T20<>"","5 Interested",IF(R20<>"","4 Responded",IF(O20<>"","2 Contacted","1 Not yet contacted"))))))))))))) | AK20: =IF(AF20<>"",AF20,IF(OR(O20="",R20<>"",LEFT(AJ20,1)="X"),"",IF(Q20<>"","",IF(P20<>"",P20+SETTINGS!$B$4,O20+SETTINGS!$B$3)))) | AL20: =IF(AJ20="","",IF(LEFT(AJ20,1)="X","None — do not contact",IF(AJ20="1 Not yet contacted","Verify route today, then send M1",IF(AND(R20="",Q20<>""),"Sequence complete — no contact before "&TEXT(Q20+SETTINGS!$B$5,"yyyy-mm-dd"),IF(AND(R20="",P20<>""),"Send final note (M4)",IF(R20="","Send follow-up (M2)",IF(AJ20="12 ACTIVATED","7-day check-in; consent & referral soft ask",IF(AJ20="13 Transacting","Repeat-activity support","Onboarding: move to next stage (see playbook §6)")))))))) | AM20: =IF(ISNUMBER(AK20),IF(AK20<=TODAY(),"DUE",""),"") | AN20: =IF(COUNT(O20,P20,Q20,R20,T20,V20,W20,X20,Y20,Z20,AA20,AC20)=0,"",TODAY()-MAX(O20,P20,Q20,R20,T20,V20,W20,X20,Y20,Z20,AA20,AC20)) | AO20: =IF(AJ20="","",IF(AND(T20<>"",U20<>"Active (verified)"),"GST: escalate (no tax advice)",IF(AND(IFERROR(VALUE(LEFT(AJ20,2)),0)>=5,AH20<>"YES",ISNUMBER(AN20),AN20>SETTINGS!$B$14),"STUCK in onboarding","")))
A21: 20 | B21: UPK2-LM-219 | C21: 7 Vows Stories | D21: Lens & Motion | E21: LM-WEDDING | F21: Delhi NCR | G21: A | H21: P0 | J21: Personal 1:1 email from founder/team to published business email | K21: https://www.7vowsstories.com/ | L21: W0 Pilot | AH21: =IF(AND(B21="",C21=""),"",IF(AND(X21<>"",Y21<>"",Z21<>"",AA21<>"",AB21="Y"),"YES","no")) | AI21: =IF(AH21="YES",MAX(X21,Y21,Z21,AA21),"") | AJ21: =IF(AND(B21="",C21=""),"",IF(OR(S21="Not interested",S21="Opt-out / do not contact"),"X Declined / suppressed",IF(S21="Bounced / undeliverable","X Bounced — research",IF(AC21<>"","13 Transacting",IF(AH21="YES","12 ACTIVATED",IF(Z21<>"","11 Listing live",IF(Y21<>"","10 Profile complete",IF(X21<>"","9 Approved",IF(W21<>"","8 KYC submitted",IF(V21<>"","7 Registered",IF(T21<>"","5 Interested",IF(R21<>"","4 Responded",IF(O21<>"","2 Contacted","1 Not yet contacted"))))))))))))) | AK21: =IF(AF21<>"",AF21,IF(OR(O21="",R21<>"",LEFT(AJ21,1)="X"),"",IF(Q21<>"","",IF(P21<>"",P21+SETTINGS!$B$4,O21+SETTINGS!$B$3)))) | AL21: =IF(AJ21="","",IF(LEFT(AJ21,1)="X","None — do not contact",IF(AJ21="1 Not yet contacted","Verify route today, then send M1",IF(AND(R21="",Q21<>""),"Sequence complete — no contact before "&TEXT(Q21+SETTINGS!$B$5,"yyyy-mm-dd"),IF(AND(R21="",P21<>""),"Send final note (M4)",IF(R21="","Send follow-up (M2)",IF(AJ21="12 ACTIVATED","7-day check-in; consent & referral soft ask",IF(AJ21="13 Transacting","Repeat-activity support","Onboarding: move to next stage (see playbook §6)")))))))) | AM21: =IF(ISNUMBER(AK21),IF(AK21<=TODAY(),"DUE",""),"") | AN21: =IF(COUNT(O21,P21,Q21,R21,T21,V21,W21,X21,Y21,Z21,AA21,AC21)=0,"",TODAY()-MAX(O21,P21,Q21,R21,T21,V21,W21,X21,Y21,Z21,AA21,AC21)) | AO21: =IF(AJ21="","",IF(AND(T21<>"",U21<>"Active (verified)"),"GST: escalate (no tax advice)",IF(AND(IFERROR(VALUE(LEFT(AJ21,2)),0)>=5,AH21<>"YES",ISNUMBER(AN21),AN21>SETTINGS!$B$14),"STUCK in onboarding","")))
A22: 21 | B22: UPK2-LM-208 | C22: Photomist | D22: Lens & Motion | E22: LM-WEDDING | F22: Mumbai | G22: B | H22: P0 | J22: Personal 1:1 email from founder/team to published business email | K22: https://www.photomist.in/ | L22: W0 Pilot | AH22: =IF(AND(B22="",C22=""),"",IF(AND(X22<>"",Y22<>"",Z22<>"",AA22<>"",AB22="Y"),"YES","no")) | AI22: =IF(AH22="YES",MAX(X22,Y22,Z22,AA22),"") | AJ22: =IF(AND(B22="",C22=""),"",IF(OR(S22="Not interested",S22="Opt-out / do not contact"),"X Declined / suppressed",IF(S22="Bounced / undeliverable","X Bounced — research",IF(AC22<>"","13 Transacting",IF(AH22="YES","12 ACTIVATED",IF(Z22<>"","11 Listing live",IF(Y22<>"","10 Profile complete",IF(X22<>"","9 Approved",IF(W22<>"","8 KYC submitted",IF(V22<>"","7 Registered",IF(T22<>"","5 Interested",IF(R22<>"","4 Responded",IF(O22<>"","2 Contacted","1 Not yet contacted"))))))))))))) | AK22: =IF(AF22<>"",AF22,IF(OR(O22="",R22<>"",LEFT(AJ22,1)="X"),"",IF(Q22<>"","",IF(P22<>"",P22+SETTINGS!$B$4,O22+SETTINGS!$B$3)))) | AL22: =IF(AJ22="","",IF(LEFT(AJ22,1)="X","None — do not contact",IF(AJ22="1 Not yet contacted","Verify route today, then send M1",IF(AND(R22="",Q22<>""),"Sequence complete — no contact before "&TEXT(Q22+SETTINGS!$B$5,"yyyy-mm-dd"),IF(AND(R22="",P22<>""),"Send final note (M4)",IF(R22="","Send follow-up (M2)",IF(AJ22="12 ACTIVATED","7-day check-in; consent & referral soft ask",IF(AJ22="13 Transacting","Repeat-activity support","Onboarding: move to next stage (see playbook §6)")))))))) | AM22: =IF(ISNUMBER(AK22),IF(AK22<=TODAY(),"DUE",""),"") | AN22: =IF(COUNT(O22,P22,Q22,R22,T22,V22,W22,X22,Y22,Z22,AA22,AC22)=0,"",TODAY()-MAX(O22,P22,Q22,R22,T22,V22,W22,X22,Y22,Z22,AA22,AC22)) | AO22: =IF(AJ22="","",IF(AND(T22<>"",U22<>"Active (verified)"),"GST: escalate (no tax advice)",IF(AND(IFERROR(VALUE(LEFT(AJ22,2)),0)>=5,AH22<>"YES",ISNUMBER(AN22),AN22>SETTINGS!$B$14),"STUCK in onboarding","")))
A23: 22 | B23: UPK2-LM-225 | C23: A.Rrajani Photography | D23: Lens & Motion | E23: LM-COMMERCIAL-FASHION | F23: Mumbai | G23: C | H23: P0 | I23: under-discovered | J23: Personal 1:1 email from founder/team to published business email | K23: https://www.a-rrajani.com/contact-andheri-mumbai/ | L23: W0 Pilot | AH23: =IF(AND(B23="",C23=""),"",IF(AND(X23<>"",Y23<>"",Z23<>"",AA23<>"",AB23="Y"),"YES","no")) | AI23: =IF(AH23="YES",MAX(X23,Y23,Z23,AA23),"") | AJ23: =IF(AND(B23="",C23=""),"",IF(OR(S23="Not interested",S23="Opt-out / do not contact"),"X Declined / suppressed",IF(S23="Bounced / undeliverable","X Bounced — research",IF(AC23<>"","13 Transacting",IF(AH23="YES","12 ACTIVATED",IF(Z23<>"","11 Listing live",IF(Y23<>"","10 Profile complete",IF(X23<>"","9 Approved",IF(W23<>"","8 KYC submitted",IF(V23<>"","7 Registered",IF(T23<>"","5 Interested",IF(R23<>"","4 Responded",IF(O23<>"","2 Contacted","1 Not yet contacted"))))))))))))) | AK23: =IF(AF23<>"",AF23,IF(OR(O23="",R23<>"",LEFT(AJ23,1)="X"),"",IF(Q23<>"","",IF(P23<>"",P23+SETTINGS!$B$4,O23+SETTINGS!$B$3)))) | AL23: =IF(AJ23="","",IF(LEFT(AJ23,1)="X","None — do not contact",IF(AJ23="1 Not yet contacted","Verify route today, then send M1",IF(AND(R23="",Q23<>""),"Sequence complete — no contact before "&TEXT(Q23+SETTINGS!$B$5,"yyyy-mm-dd"),IF(AND(R23="",P23<>""),"Send final note (M4)",IF(R23="","Send follow-up (M2)",IF(AJ23="12 ACTIVATED","7-day check-in; consent & referral soft ask",IF(AJ23="13 Transacting","Repeat-activity support","Onboarding: move to next stage (see playbook §6)")))))))) | AM23: =IF(ISNUMBER(AK23),IF(AK23<=TODAY(),"DUE",""),"") | AN23: =IF(COUNT(O23,P23,Q23,R23,T23,V23,W23,X23,Y23,Z23,AA23,AC23)=0,"",TODAY()-MAX(O23,P23,Q23,R23,T23,V23,W23,X23,Y23,Z23,AA23,AC23)) | AO23: =IF(AJ23="","",IF(AND(T23<>"",U23<>"Active (verified)"),"GST: escalate (no tax advice)",IF(AND(IFERROR(VALUE(LEFT(AJ23,2)),0)>=5,AH23<>"YES",ISNUMBER(AN23),AN23>SETTINGS!$B$14),"STUCK in onboarding","")))
A24: 23 | B24: UPK2-LM-279 | C24: Jignesh Jhaveri | D24: Lens & Motion | E24: LM-COMMERCIAL-FASHION | F24: Mumbai | G24: C | H24: P0 | I24: under-discovered | J24: Personal 1:1 email from founder/team to published business email | K24: https://www.jigneshjhaveri.com/contact | L24: W0 Pilot | AH24: =IF(AND(B24="",C24=""),"",IF(AND(X24<>"",Y24<>"",Z24<>"",AA24<>"",AB24="Y"),"YES","no")) | AI24: =IF(AH24="YES",MAX(X24,Y24,Z24,AA24),"") | AJ24: =IF(AND(B24="",C24=""),"",IF(OR(S24="Not interested",S24="Opt-out / do not contact"),"X Declined / suppressed",IF(S24="Bounced / undeliverable","X Bounced — research",IF(AC24<>"","13 Transacting",IF(AH24="YES","12 ACTIVATED",IF(Z24<>"","11 Listing live",IF(Y24<>"","10 Profile complete",IF(X24<>"","9 Approved",IF(W24<>"","8 KYC submitted",IF(V24<>"","7 Registered",IF(T24<>"","5 Interested",IF(R24<>"","4 Responded",IF(O24<>"","2 Contacted","1 Not yet contacted"))))))))))))) | AK24: =IF(AF24<>"",AF24,IF(OR(O24="",R24<>"",LEFT(AJ24,1)="X"),"",IF(Q24<>"","",IF(P24<>"",P24+SETTINGS!$B$4,O24+SETTINGS!$B$3)))) | AL24: =IF(AJ24="","",IF(LEFT(AJ24,1)="X","None — do not contact",IF(AJ24="1 Not yet contacted","Verify route today, then send M1",IF(AND(R24="",Q24<>""),"Sequence complete — no contact before "&TEXT(Q24+SETTINGS!$B$5,"yyyy-mm-dd"),IF(AND(R24="",P24<>""),"Send final note (M4)",IF(R24="","Send follow-up (M2)",IF(AJ24="12 ACTIVATED","7-day check-in; consent & referral soft ask",IF(AJ24="13 Transacting","Repeat-activity support","Onboarding: move to next stage (see playbook §6)")))))))) | AM24: =IF(ISNUMBER(AK24),IF(AK24<=TODAY(),"DUE",""),"") | AN24: =IF(COUNT(O24,P24,Q24,R24,T24,V24,W24,X24,Y24,Z24,AA24,AC24)=0,"",TODAY()-MAX(O24,P24,Q24,R24,T24,V24,W24,X24,Y24,Z24,AA24,AC24)) | AO24: =IF(AJ24="","",IF(AND(T24<>"",U24<>"Active (verified)"),"GST: escalate (no tax advice)",IF(AND(IFERROR(VALUE(LEFT(AJ24,2)),0)>=5,AH24<>"YES",ISNUMBER(AN24),AN24>SETTINGS!$B$14),"STUCK in onboarding","")))
A25: 24 | B25: UPK2-CM-046 | C25: Amol Soni | D25: Content & Media | E25: CM-EMCEE-HOST | F25: Mumbai | G25: A | H25: P0 | J25: Personal 1:1 email from founder/team to published business email | K25: https://www.entertaineramolsoni.com/ | L25: W0 Pilot | AH25: =IF(AND(B25="",C25=""),"",IF(AND(X25<>"",Y25<>"",Z25<>"",AA25<>"",AB25="Y"),"YES","no")) | AI25: =IF(AH25="YES",MAX(X25,Y25,Z25,AA25),"") | AJ25: =IF(AND(B25="",C25=""),"",IF(OR(S25="Not interested",S25="Opt-out / do not contact"),"X Declined / suppressed",IF(S25="Bounced / undeliverable","X Bounced — research",IF(AC25<>"","13 Transacting",IF(AH25="YES","12 ACTIVATED",IF(Z25<>"","11 Listing live",IF(Y25<>"","10 Profile complete",IF(X25<>"","9 Approved",IF(W25<>"","8 KYC submitted",IF(V25<>"","7 Registered",IF(T25<>"","5 Interested",IF(R25<>"","4 Responded",IF(O25<>"","2 Contacted","1 Not yet contacted"))))))))))))) | AK25: =IF(AF25<>"",AF25,IF(OR(O25="",R25<>"",LEFT(AJ25,1)="X"),"",IF(Q25<>"","",IF(P25<>"",P25+SETTINGS!$B$4,O25+SETTINGS!$B$3)))) | AL25: =IF(AJ25="","",IF(LEFT(AJ25,1)="X","None — do not contact",IF(AJ25="1 Not yet contacted","Verify route today, then send M1",IF(AND(R25="",Q25<>""),"Sequence complete — no contact before "&TEXT(Q25+SETTINGS!$B$5,"yyyy-mm-dd"),IF(AND(R25="",P25<>""),"Send final note (M4)",IF(R25="","Send follow-up (M2)",IF(AJ25="12 ACTIVATED","7-day check-in; consent & referral soft ask",IF(AJ25="13 Transacting","Repeat-activity support","Onboarding: move to next stage (see playbook §6)")))))))) | AM25: =IF(ISNUMBER(AK25),IF(AK25<=TODAY(),"DUE",""),"") | AN25: =IF(COUNT(O25,P25,Q25,R25,T25,V25,W25,X25,Y25,Z25,AA25,AC25)=0,"",TODAY()-MAX(O25,P25,Q25,R25,T25,V25,W25,X25,Y25,Z25,AA25,AC25)) | AO25: =IF(AJ25="","",IF(AND(T25<>"",U25<>"Active (verified)"),"GST: escalate (no tax advice)",IF(AND(IFERROR(VALUE(LEFT(AJ25,2)),0)>=5,AH25<>"YES",ISNUMBER(AN25),AN25>SETTINGS!$B$14),"STUCK in onboarding","")))
A26: 25 | B26: UPK2-CM-044 | C26: Sagar Duggal | D26: Content & Media | E26: CM-EMCEE-HOST | F26: Delhi NCR | G26: C | H26: P0 | J26: Personal 1:1 email from founder/team to published business email | K26: https://talkativesagar.com/ | L26: W0 Pilot | AH26: =IF(AND(B26="",C26=""),"",IF(AND(X26<>"",Y26<>"",Z26<>"",AA26<>"",AB26="Y"),"YES","no")) | AI26: =IF(AH26="YES",MAX(X26,Y26,Z26,AA26),"") | AJ26: =IF(AND(B26="",C26=""),"",IF(OR(S26="Not interested",S26="Opt-out / do not contact"),"X Declined / suppressed",IF(S26="Bounced / undeliverable","X Bounced — research",IF(AC26<>"","13 Transacting",IF(AH26="YES","12 ACTIVATED",IF(Z26<>"","11 Listing live",IF(Y26<>"","10 Profile complete",IF(X26<>"","9 Approved",IF(W26<>"","8 KYC submitted",IF(V26<>"","7 Registered",IF(T26<>"","5 Interested",IF(R26<>"","4 Responded",IF(O26<>"","2 Contacted","1 Not yet contacted"))))))))))))) | AK26: =IF(AF26<>"",AF26,IF(OR(O26="",R26<>"",LEFT(AJ26,1)="X"),"",IF(Q26<>"","",IF(P26<>"",P26+SETTINGS!$B$4,O26+SETTINGS!$B$3)))) | AL26: =IF(AJ26="","",IF(LEFT(AJ26,1)="X","None — do not contact",IF(AJ26="1 Not yet contacted","Verify route today, then send M1",IF(AND(R26="",Q26<>""),"Sequence complete — no contact before "&TEXT(Q26+SETTINGS!$B$5,"yyyy-mm-dd"),IF(AND(R26="",P26<>""),"Send final note (M4)",IF(R26="","Send follow-up (M2)",IF(AJ26="12 ACTIVATED","7-day check-in; consent & referral soft ask",IF(AJ26="13 Transacting","Repeat-activity support","Onboarding: move to next stage (see playbook §6)")))))))) | AM26: =IF(ISNUMBER(AK26),IF(AK26<=TODAY(),"DUE",""),"") | AN26: =IF(COUNT(O26,P26,Q26,R26,T26,V26,W26,X26,Y26,Z26,AA26,AC26)=0,"",TODAY()-MAX(O26,P26,Q26,R26,T26,V26,W26,X26,Y26,Z26,AA26,AC26)) | AO26: =IF(AJ26="","",IF(AND(T26<>"",U26<>"Active (verified)"),"GST: escalate (no tax advice)",IF(AND(IFERROR(VALUE(LEFT(AJ26,2)),0)>=5,AH26<>"YES",ISNUMBER(AN26),AN26>SETTINGS!$B$14),"STUCK in onboarding","")))
A27: 26 | B27: UPK2-FL-171 | C27: Aseem Kapoor | D27: Fashion & Lifestyle | E27: FL-OCCASION-BRIDAL | F27: Delhi NCR | G27: A | H27: P0 | I27: stockist-listed|large catalogue | J27: Personal 1:1 email from founder/team to published business email | K27: https://aseemkapoor.com/pages/contact | L27: W1 Founding cohort | AH27: =IF(AND(B27="",C27=""),"",IF(AND(X27<>"",Y27<>"",Z27<>"",AA27<>"",AB27="Y"),"YES","no")) | AI27: =IF(AH27="YES",MAX(X27,Y27,Z27,AA27),"") | AJ27: =IF(AND(B27="",C27=""),"",IF(OR(S27="Not interested",S27="Opt-out / do not contact"),"X Declined / suppressed",IF(S27="Bounced / undeliverable","X Bounced — research",IF(AC27<>"","13 Transacting",IF(AH27="YES","12 ACTIVATED",IF(Z27<>"","11 Listing live",IF(Y27<>"","10 Profile complete",IF(X27<>"","9 Approved",IF(W27<>"","8 KYC submitted",IF(V27<>"","7 Registered",IF(T27<>"","5 Interested",IF(R27<>"","4 Responded",IF(O27<>"","2 Contacted","1 Not yet contacted"))))))))))))) | AK27: =IF(AF27<>"",AF27,IF(OR(O27="",R27<>"",LEFT(AJ27,1)="X"),"",IF(Q27<>"","",IF(P27<>"",P27+SETTINGS!$B$4,O27+SETTINGS!$B$3)))) | AL27: =IF(AJ27="","",IF(LEFT(AJ27,1)="X","None — do not contact",IF(AJ27="1 Not yet contacted","Verify route today, then send M1",IF(AND(R27="",Q27<>""),"Sequence complete — no contact before "&TEXT(Q27+SETTINGS!$B$5,"yyyy-mm-dd"),IF(AND(R27="",P27<>""),"Send final note (M4)",IF(R27="","Send follow-up (M2)",IF(AJ27="12 ACTIVATED","7-day check-in; consent & referral soft ask",IF(AJ27="13 Transacting","Repeat-activity support","Onboarding: move to next stage (see playbook §6)")))))))) | AM27: =IF(ISNUMBER(AK27),IF(AK27<=TODAY(),"DUE",""),"") | AN27: =IF(COUNT(O27,P27,Q27,R27,T27,V27,W27,X27,Y27,Z27,AA27,AC27)=0,"",TODAY()-MAX(O27,P27,Q27,R27,T27,V27,W27,X27,Y27,Z27,AA27,AC27)) | AO27: =IF(AJ27="","",IF(AND(T27<>"",U27<>"Active (verified)"),"GST: escalate (no tax advice)",IF(AND(IFERROR(VALUE(LEFT(AJ27,2)),0)>=5,AH27<>"YES",ISNUMBER(AN27),AN27>SETTINGS!$B$14),"STUCK in onboarding","")))
A28: 27 | B28: UPK2-FL-256 | C28: Atbw | D28: Fashion & Lifestyle | E28: FL-CONTEMPORARY | F28: Delhi NCR | G28: A | H28: P0 | I28: stockist-listed | J28: Personal 1:1 email from founder/team to published business email | K28: https://atbw.shop/collections/the-artists-notebook | L28: W1 Founding cohort | AH28: =IF(AND(B28="",C28=""),"",IF(AND(X28<>"",Y28<>"",Z28<>"",AA28<>"",AB28="Y"),"YES","no")) | AI28: =IF(AH28="YES",MAX(X28,Y28,Z28,AA28),"") | AJ28: =IF(AND(B28="",C28=""),"",IF(OR(S28="Not interested",S28="Opt-out / do not contact"),"X Declined / suppressed",IF(S28="Bounced / undeliverable","X Bounced — research",IF(AC28<>"","13 Transacting",IF(AH28="YES","12 ACTIVATED",IF(Z28<>"","11 Listing live",IF(Y28<>"","10 Profile complete",IF(X28<>"","9 Approved",IF(W28<>"","8 KYC submitted",IF(V28<>"","7 Registered",IF(T28<>"","5 Interested",IF(R28<>"","4 Responded",IF(O28<>"","2 Contacted","1 Not yet contacted"))))))))))))) | AK28: =IF(AF28<>"",AF28,IF(OR(O28="",R28<>"",LEFT(AJ28,1)="X"),"",IF(Q28<>"","",IF(P28<>"",P28+SETTINGS!$B$4,O28+SETTINGS!$B$3)))) | AL28: =IF(AJ28="","",IF(LEFT(AJ28,1)="X","None — do not contact",IF(AJ28="1 Not yet contacted","Verify route today, then send M1",IF(AND(R28="",Q28<>""),"Sequence complete — no contact before "&TEXT(Q28+SETTINGS!$B$5,"yyyy-mm-dd"),IF(AND(R28="",P28<>""),"Send final note (M4)",IF(R28="","Send follow-up (M2)",IF(AJ28="12 ACTIVATED","7-day check-in; consent & referral soft ask",IF(AJ28="13 Transacting","Repeat-activity support","Onboarding: move to next stage (see playbook §6)")))))))) | AM28: =IF(ISNUMBER(AK28),IF(AK28<=TODAY(),"DUE",""),"") | AN28: =IF(COUNT(O28,P28,Q28,R28,T28,V28,W28,X28,Y28,Z28,AA28,AC28)=0,"",TODAY()-MAX(O28,P28,Q28,R28,T28,V28,W28,X28,Y28,Z28,AA28,AC28)) | AO28: =IF(AJ28="","",IF(AND(T28<>"",U28<>"Active (verified)"),"GST: escalate (no tax advice)",IF(AND(IFERROR(VALUE(LEFT(AJ28,2)),0)>=5,AH28<>"YES",ISNUMBER(AN28),AN28>SETTINGS!$B$14),"STUCK in onboarding","")))
A29: 28 | B29: UPK2-FL-261 | C29: Jodi | D29: Fashion & Lifestyle | E29: FL-OCCASION-BRIDAL | F29: Bengaluru | G29: B | H29: P0 | I29: stockist-listed | J29: Personal 1:1 email from founder/team to published business email | K29: https://jodistudio.com/contact | L29: W1 Founding cohort | AH29: =IF(AND(B29="",C29=""),"",IF(AND(X29<>"",Y29<>"",Z29<>"",AA29<>"",AB29="Y"),"YES","no")) | AI29: =IF(AH29="YES",MAX(X29,Y29,Z29,AA29),"") | AJ29: =IF(AND(B29="",C29=""),"",IF(OR(S29="Not interested",S29="Opt-out / do not contact"),"X Declined / suppressed",IF(S29="Bounced / undeliverable","X Bounced — research",IF(AC29<>"","13 Transacting",IF(AH29="YES","12 ACTIVATED",IF(Z29<>"","11 Listing live",IF(Y29<>"","10 Profile complete",IF(X29<>"","9 Approved",IF(W29<>"","8 KYC submitted",IF(V29<>"","7 Registered",IF(T29<>"","5 Interested",IF(R29<>"","4 Responded",IF(O29<>"","2 Contacted","1 Not yet contacted"))))))))))))) | AK29: =IF(AF29<>"",AF29,IF(OR(O29="",R29<>"",LEFT(AJ29,1)="X"),"",IF(Q29<>"","",IF(P29<>"",P29+SETTINGS!$B$4,O29+SETTINGS!$B$3)))) | AL29: =IF(AJ29="","",IF(LEFT(AJ29,1)="X","None — do not contact",IF(AJ29="1 Not yet contacted","Verify route today, then send M1",IF(AND(R29="",Q29<>""),"Sequence complete — no contact before "&TEXT(Q29+SETTINGS!$B$5,"yyyy-mm-dd"),IF(AND(R29="",P29<>""),"Send final note (M4)",IF(R29="","Send follow-up (M2)",IF(AJ29="12 ACTIVATED","7-day check-in; consent & referral soft ask",IF(AJ29="13 Transacting","Repeat-activity support","Onboarding: move to next stage (see playbook §6)")))))))) | AM29: =IF(ISNUMBER(AK29),IF(AK29<=TODAY(),"DUE",""),"") | AN29: =IF(COUNT(O29,P29,Q29,R29,T29,V29,W29,X29,Y29,Z29,AA29,AC29)=0,"",TODAY()-MAX(O29,P29,Q29,R29,T29,V29,W29,X29,Y29,Z29,AA29,AC29)) | AO29: =IF(AJ29="","",IF(AND(T29<>"",U29<>"Active (verified)"),"GST: escalate (no tax advice)",IF(AND(IFERROR(VALUE(LEFT(AJ29,2)),0)>=5,AH29<>"YES",ISNUMBER(AN29),AN29>SETTINGS!$B$14),"STUCK in onboarding","")))
A30: 29 | B30: UPK2-FL-267 | C30: Amisha Kothari | D30: Fashion & Lifestyle | E30: FL-CONTEMPORARY | F30: Mumbai | G30: B | H30: P0 | I30: stockist-listed | J30: Personal 1:1 email from founder/team to published business email | K30: https://amishakotharilabel.com/contact/ | L30: W1 Founding cohort | AH30: =IF(AND(B30="",C30=""),"",IF(AND(X30<>"",Y30<>"",Z30<>"",AA30<>"",AB30="Y"),"YES","no")) | AI30: =IF(AH30="YES",MAX(X30,Y30,Z30,AA30),"") | AJ30: =IF(AND(B30="",C30=""),"",IF(OR(S30="Not interested",S30="Opt-out / do not contact"),"X Declined / suppressed",IF(S30="Bounced / undeliverable","X Bounced — research",IF(AC30<>"","13 Transacting",IF(AH30="YES","12 ACTIVATED",IF(Z30<>"","11 Listing live",IF(Y30<>"","10 Profile complete",IF(X30<>"","9 Approved",IF(W30<>"","8 KYC submitted",IF(V30<>"","7 Registered",IF(T30<>"","5 Interested",IF(R30<>"","4 Responded",IF(O30<>"","2 Contacted","1 Not yet contacted"))))))))))))) | AK30: =IF(AF30<>"",AF30,IF(OR(O30="",R30<>"",LEFT(AJ30,1)="X"),"",IF(Q30<>"","",IF(P30<>"",P30+SETTINGS!$B$4,O30+SETTINGS!$B$3)))) | AL30: =IF(AJ30="","",IF(LEFT(AJ30,1)="X","None — do not contact",IF(AJ30="1 Not yet contacted","Verify route today, then send M1",IF(AND(R30="",Q30<>""),"Sequence complete — no contact before "&TEXT(Q30+SETTINGS!$B$5,"yyyy-mm-dd"),IF(AND(R30="",P30<>""),"Send final note (M4)",IF(R30="","Send follow-up (M2)",IF(AJ30="12 ACTIVATED","7-day check-in; consent & referral soft ask",IF(AJ30="13 Transacting","Repeat-activity support","Onboarding: move to next stage (see playbook §6)")))))))) | AM30: =IF(ISNUMBER(AK30),IF(AK30<=TODAY(),"DUE",""),"") | AN30: =IF(COUNT(O30,P30,Q30,R30,T30,V30,W30,X30,Y30,Z30,AA30,AC30)=0,"",TODAY()-MAX(O30,P30,Q30,R30,T30,V30,W30,X30,Y30,Z30,AA30,AC30)) | AO30: =IF(AJ30="","",IF(AND(T30<>"",U30<>"Active (verified)"),"GST: escalate (no tax advice)",IF(AND(IFERROR(VALUE(LEFT(AJ30,2)),0)>=5,AH30<>"YES",ISNUMBER(AN30),AN30>SETTINGS!$B$14),"STUCK in onboarding","")))
A31: 30 | B31: UPK2-FL-164 | C31: Devnaagri | D31: Fashion & Lifestyle | E31: FL-OCCASION-BRIDAL | F31: Delhi NCR | G31: B | H31: P0 | I31: stockist-listed|large catalogue | J31: Personal 1:1 email from founder/team to published business email | K31: https://www.devnaagri.com/pages/contact-us | L31: W1 Founding cohort | AH31: =IF(AND(B31="",C31=""),"",IF(AND(X31<>"",Y31<>"",Z31<>"",AA31<>"",AB31="Y"),"YES","no")) | AI31: =IF(AH31="YES",MAX(X31,Y31,Z31,AA31),"") | AJ31: =IF(AND(B31="",C31=""),"",IF(OR(S31="Not interested",S31="Opt-out / do not contact"),"X Declined / suppressed",IF(S31="Bounced / undeliverable","X Bounced — research",IF(AC31<>"","13 Transacting",IF(AH31="YES","12 ACTIVATED",IF(Z31<>"","11 Listing live",IF(Y31<>"","10 Profile complete",IF(X31<>"","9 Approved",IF(W31<>"","8 KYC submitted",IF(V31<>"","7 Registered",IF(T31<>"","5 Interested",IF(R31<>"","4 Responded",IF(O31<>"","2 Contacted","1 Not yet contacted"))))))))))))) | AK31: =IF(AF31<>"",AF31,IF(OR(O31="",R31<>"",LEFT(AJ31,1)="X"),"",IF(Q31<>"","",IF(P31<>"",P31+SETTINGS!$B$4,O31+SETTINGS!$B$3)))) | AL31: =IF(AJ31="","",IF(LEFT(AJ31,1)="X","None — do not contact",IF(AJ31="1 Not yet contacted","Verify route today, then send M1",IF(AND(R31="",Q31<>""),"Sequence complete — no contact before "&TEXT(Q31+SETTINGS!$B$5,"yyyy-mm-dd"),IF(AND(R31="",P31<>""),"Send final note (M4)",IF(R31="","Send follow-up (M2)",IF(AJ31="12 ACTIVATED","7-day check-in; consent & referral soft ask",IF(AJ31="13 Transacting","Repeat-activity support","Onboarding: move to next stage (see playbook §6)")))))))) | AM31: =IF(ISNUMBER(AK31),IF(AK31<=TODAY(),"DUE",""),"") | AN31: =IF(COUNT(O31,P31,Q31,R31,T31,V31,W31,X31,Y31,Z31,AA31,AC31)=0,"",TODAY()-MAX(O31,P31,Q31,R31,T31,V31,W31,X31,Y31,Z31,AA31,AC31)) | AO31: =IF(AJ31="","",IF(AND(T31<>"",U31<>"Active (verified)"),"GST: escalate (no tax advice)",IF(AND(IFERROR(VALUE(LEFT(AJ31,2)),0)>=5,AH31<>"YES",ISNUMBER(AN31),AN31>SETTINGS!$B$14),"STUCK in onboarding","")))
A32: 31 | B32: UPK2-FL-165 | C32: Miss Jo | D32: Fashion & Lifestyle | E32: FL-JEWELLERY | F32: Delhi NCR | G32: B | H32: P0 | I32: stockist-listed|large catalogue | J32: Personal 1:1 email from founder/team to published business email | K32: https://missjo.com/pages/contact | L32: W1 Founding cohort | AH32: =IF(AND(B32="",C32=""),"",IF(AND(X32<>"",Y32<>"",Z32<>"",AA32<>"",AB32="Y"),"YES","no")) | AI32: =IF(AH32="YES",MAX(X32,Y32,Z32,AA32),"") | AJ32: =IF(AND(B32="",C32=""),"",IF(OR(S32="Not interested",S32="Opt-out / do not contact"),"X Declined / suppressed",IF(S32="Bounced / undeliverable","X Bounced — research",IF(AC32<>"","13 Transacting",IF(AH32="YES","12 ACTIVATED",IF(Z32<>"","11 Listing live",IF(Y32<>"","10 Profile complete",IF(X32<>"","9 Approved",IF(W32<>"","8 KYC submitted",IF(V32<>"","7 Registered",IF(T32<>"","5 Interested",IF(R32<>"","4 Responded",IF(O32<>"","2 Contacted","1 Not yet contacted"))))))))))))) | AK32: =IF(AF32<>"",AF32,IF(OR(O32="",R32<>"",LEFT(AJ32,1)="X"),"",IF(Q32<>"","",IF(P32<>"",P32+SETTINGS!$B$4,O32+SETTINGS!$B$3)))) | AL32: =IF(AJ32="","",IF(LEFT(AJ32,1)="X","None — do not contact",IF(AJ32="1 Not yet contacted","Verify route today, then send M1",IF(AND(R32="",Q32<>""),"Sequence complete — no contact before "&TEXT(Q32+SETTINGS!$B$5,"yyyy-mm-dd"),IF(AND(R32="",P32<>""),"Send final note (M4)",IF(R32="","Send follow-up (M2)",IF(AJ32="12 ACTIVATED","7-day check-in; consent & referral soft ask",IF(AJ32="13 Transacting","Repeat-activity support","Onboarding: move to next stage (see playbook §6)")))))))) | AM32: =IF(ISNUMBER(AK32),IF(AK32<=TODAY(),"DUE",""),"") | AN32: =IF(COUNT(O32,P32,Q32,R32,T32,V32,W32,X32,Y32,Z32,AA32,AC32)=0,"",TODAY()-MAX(O32,P32,Q32,R32,T32,V32,W32,X32,Y32,Z32,AA32,AC32)) | AO32: =IF(AJ32="","",IF(AND(T32<>"",U32<>"Active (verified)"),"GST: escalate (no tax advice)",IF(AND(IFERROR(VALUE(LEFT(AJ32,2)),0)>=5,AH32<>"YES",ISNUMBER(AN32),AN32>SETTINGS!$B$14),"STUCK in onboarding","")))
A33: 32 | B33: UPK2-FL-166 | C33: Preeti Mohan | D33: Fashion & Lifestyle | E33: FL-JEWELLERY | F33: Delhi NCR | G33: B | H33: P0 | I33: stockist-listed|large catalogue | J33: Personal 1:1 email from founder/team to published business email | K33: https://preetimohan.com/pages/contact | L33: W1 Founding cohort | AH33: =IF(AND(B33="",C33=""),"",IF(AND(X33<>"",Y33<>"",Z33<>"",AA33<>"",AB33="Y"),"YES","no")) | AI33: =IF(AH33="YES",MAX(X33,Y33,Z33,AA33),"") | AJ33: =IF(AND(B33="",C33=""),"",IF(OR(S33="Not interested",S33="Opt-out / do not contact"),"X Declined / suppressed",IF(S33="Bounced / undeliverable","X Bounced — research",IF(AC33<>"","13 Transacting",IF(AH33="YES","12 ACTIVATED",IF(Z33<>"","11 Listing live",IF(Y33<>"","10 Profile complete",IF(X33<>"","9 Approved",IF(W33<>"","8 KYC submitted",IF(V33<>"","7 Registered",IF(T33<>"","5 Interested",IF(R33<>"","4 Responded",IF(O33<>"","2 Contacted","1 Not yet contacted"))))))))))))) | AK33: =IF(AF33<>"",AF33,IF(OR(O33="",R33<>"",LEFT(AJ33,1)="X"),"",IF(Q33<>"","",IF(P33<>"",P33+SETTINGS!$B$4,O33+SETTINGS!$B$3)))) | AL33: =IF(AJ33="","",IF(LEFT(AJ33,1)="X","None — do not contact",IF(AJ33="1 Not yet contacted","Verify route today, then send M1",IF(AND(R33="",Q33<>""),"Sequence complete — no contact before "&TEXT(Q33+SETTINGS!$B$5,"yyyy-mm-dd"),IF(AND(R33="",P33<>""),"Send final note (M4)",IF(R33="","Send follow-up (M2)",IF(AJ33="12 ACTIVATED","7-day check-in; consent & referral soft ask",IF(AJ33="13 Transacting","Repeat-activity support","Onboarding: move to next stage (see playbook §6)")))))))) | AM33: =IF(ISNUMBER(AK33),IF(AK33<=TODAY(),"DUE",""),"") | AN33: =IF(COUNT(O33,P33,Q33,R33,T33,V33,W33,X33,Y33,Z33,AA33,AC33)=0,"",TODAY()-MAX(O33,P33,Q33,R33,T33,V33,W33,X33,Y33,Z33,AA33,AC33)) | AO33: =IF(AJ33="","",IF(AND(T33<>"",U33<>"Active (verified)"),"GST: escalate (no tax advice)",IF(AND(IFERROR(VALUE(LEFT(AJ33,2)),0)>=5,AH33<>"YES",ISNUMBER(AN33),AN33>SETTINGS!$B$14),"STUCK in onboarding","")))
A34: 33 | B34: UPK2-FL-162 | C34: Azga | D34: Fashion & Lifestyle | E34: FL-CONTEMPORARY | F34: Jaipur | G34: B | H34: P0 | I34: stockist-listed|large catalogue | J34: Personal 1:1 email from founder/team to published business email | K34: https://www.azga.in/pages/reach-us | L34: W1 Founding cohort | AH34: =IF(AND(B34="",C34=""),"",IF(AND(X34<>"",Y34<>"",Z34<>"",AA34<>"",AB34="Y"),"YES","no")) | AI34: =IF(AH34="YES",MAX(X34,Y34,Z34,AA34),"") | AJ34: =IF(AND(B34="",C34=""),"",IF(OR(S34="Not interested",S34="Opt-out / do not contact"),"X Declined / suppressed",IF(S34="Bounced / undeliverable","X Bounced — research",IF(AC34<>"","13 Transacting",IF(AH34="YES","12 ACTIVATED",IF(Z34<>"","11 Listing live",IF(Y34<>"","10 Profile complete",IF(X34<>"","9 Approved",IF(W34<>"","8 KYC submitted",IF(V34<>"","7 Registered",IF(T34<>"","5 Interested",IF(R34<>"","4 Responded",IF(O34<>"","2 Contacted","1 Not yet contacted"))))))))))))) | AK34: =IF(AF34<>"",AF34,IF(OR(O34="",R34<>"",LEFT(AJ34,1)="X"),"",IF(Q34<>"","",IF(P34<>"",P34+SETTINGS!$B$4,O34+SETTINGS!$B$3)))) | AL34: =IF(AJ34="","",IF(LEFT(AJ34,1)="X","None — do not contact",IF(AJ34="1 Not yet contacted","Verify route today, then send M1",IF(AND(R34="",Q34<>""),"Sequence complete — no contact before "&TEXT(Q34+SETTINGS!$B$5,"yyyy-mm-dd"),IF(AND(R34="",P34<>""),"Send final note (M4)",IF(R34="","Send follow-up (M2)",IF(AJ34="12 ACTIVATED","7-day check-in; consent & referral soft ask",IF(AJ34="13 Transacting","Repeat-activity support","Onboarding: move to next stage (see playbook §6)")))))))) | AM34: =IF(ISNUMBER(AK34),IF(AK34<=TODAY(),"DUE",""),"") | AN34: =IF(COUNT(O34,P34,Q34,R34,T34,V34,W34,X34,Y34,Z34,AA34,AC34)=0,"",TODAY()-MAX(O34,P34,Q34,R34,T34,V34,W34,X34,Y34,Z34,AA34,AC34)) | AO34: =IF(AJ34="","",IF(AND(T34<>"",U34<>"Active (verified)"),"GST: escalate (no tax advice)",IF(AND(IFERROR(VALUE(LEFT(AJ34,2)),0)>=5,AH34<>"YES",ISNUMBER(AN34),AN34>SETTINGS!$B$14),"STUCK in onboarding","")))
A35: 34 | B35: UPK2-FL-163 | C35: Bhumika Sharma | D35: Fashion & Lifestyle | E35: FL-OCCASION-BRIDAL | F35: Delhi NCR | G35: B | H35: P0 | I35: stockist-listed|large catalogue | J35: Personal 1:1 email from founder/team to published business email | K35: https://www.bhumikasharma.in/pages/contact | L35: W1 Founding cohort | AH35: =IF(AND(B35="",C35=""),"",IF(AND(X35<>"",Y35<>"",Z35<>"",AA35<>"",AB35="Y"),"YES","no")) | AI35: =IF(AH35="YES",MAX(X35,Y35,Z35,AA35),"") | AJ35: =IF(AND(B35="",C35=""),"",IF(OR(S35="Not interested",S35="Opt-out / do not contact"),"X Declined / suppressed",IF(S35="Bounced / undeliverable","X Bounced — research",IF(AC35<>"","13 Transacting",IF(AH35="YES","12 ACTIVATED",IF(Z35<>"","11 Listing live",IF(Y35<>"","10 Profile complete",IF(X35<>"","9 Approved",IF(W35<>"","8 KYC submitted",IF(V35<>"","7 Registered",IF(T35<>"","5 Interested",IF(R35<>"","4 Responded",IF(O35<>"","2 Contacted","1 Not yet contacted"))))))))))))) | AK35: =IF(AF35<>"",AF35,IF(OR(O35="",R35<>"",LEFT(AJ35,1)="X"),"",IF(Q35<>"","",IF(P35<>"",P35+SETTINGS!$B$4,O35+SETTINGS!$B$3)))) | AL35: =IF(AJ35="","",IF(LEFT(AJ35,1)="X","None — do not contact",IF(AJ35="1 Not yet contacted","Verify route today, then send M1",IF(AND(R35="",Q35<>""),"Sequence complete — no contact before "&TEXT(Q35+SETTINGS!$B$5,"yyyy-mm-dd"),IF(AND(R35="",P35<>""),"Send final note (M4)",IF(R35="","Send follow-up (M2)",IF(AJ35="12 ACTIVATED","7-day check-in; consent & referral soft ask",IF(AJ35="13 Transacting","Repeat-activity support","Onboarding: move to next stage (see playbook §6)")))))))) | AM35: =IF(ISNUMBER(AK35),IF(AK35<=TODAY(),"DUE",""),"") | AN35: =IF(COUNT(O35,P35,Q35,R35,T35,V35,W35,X35,Y35,Z35,AA35,AC35)=0,"",TODAY()-MAX(O35,P35,Q35,R35,T35,V35,W35,X35,Y35,Z35,AA35,AC35)) | AO35: =IF(AJ35="","",IF(AND(T35<>"",U35<>"Active (verified)"),"GST: escalate (no tax advice)",IF(AND(IFERROR(VALUE(LEFT(AJ35,2)),0)>=5,AH35<>"YES",ISNUMBER(AN35),AN35>SETTINGS!$B$14),"STUCK in onboarding","")))
A36: 35 | B36: UPK2-FL-167 | C36: The Leather Garden | D36: Fashion & Lifestyle | E36: FL-ACCESSORIES | F36: Delhi NCR | G36: B | H36: P0 | I36: stockist-listed|large catalogue | J36: Personal 1:1 email from founder/team to published business email | K36: https://theleathergarden.com/collections/notebook | L36: W1 Founding cohort | AH36: =IF(AND(B36="",C36=""),"",IF(AND(X36<>"",Y36<>"",Z36<>"",AA36<>"",AB36="Y"),"YES","no")) | AI36: =IF(AH36="YES",MAX(X36,Y36,Z36,AA36),"") | AJ36: =IF(AND(B36="",C36=""),"",IF(OR(S36="Not interested",S36="Opt-out / do not contact"),"X Declined / suppressed",IF(S36="Bounced / undeliverable","X Bounced — research",IF(AC36<>"","13 Transacting",IF(AH36="YES","12 ACTIVATED",IF(Z36<>"","11 Listing live",IF(Y36<>"","10 Profile complete",IF(X36<>"","9 Approved",IF(W36<>"","8 KYC submitted",IF(V36<>"","7 Registered",IF(T36<>"","5 Interested",IF(R36<>"","4 Responded",IF(O36<>"","2 Contacted","1 Not yet contacted"))))))))))))) | AK36: =IF(AF36<>"",AF36,IF(OR(O36="",R36<>"",LEFT(AJ36,1)="X"),"",IF(Q36<>"","",IF(P36<>"",P36+SETTINGS!$B$4,O36+SETTINGS!$B$3)))) | AL36: =IF(AJ36="","",IF(LEFT(AJ36,1)="X","None — do not contact",IF(AJ36="1 Not yet contacted","Verify route today, then send M1",IF(AND(R36="",Q36<>""),"Sequence complete — no contact before "&TEXT(Q36+SETTINGS!$B$5,"yyyy-mm-dd"),IF(AND(R36="",P36<>""),"Send final note (M4)",IF(R36="","Send follow-up (M2)",IF(AJ36="12 ACTIVATED","7-day check-in; consent & referral soft ask",IF(AJ36="13 Transacting","Repeat-activity support","Onboarding: move to next stage (see playbook §6)")))))))) | AM36: =IF(ISNUMBER(AK36),IF(AK36<=TODAY(),"DUE",""),"") | AN36: =IF(COUNT(O36,P36,Q36,R36,T36,V36,W36,X36,Y36,Z36,AA36,AC36)=0,"",TODAY()-MAX(O36,P36,Q36,R36,T36,V36,W36,X36,Y36,Z36,AA36,AC36)) | AO36: =IF(AJ36="","",IF(AND(T36<>"",U36<>"Active (verified)"),"GST: escalate (no tax advice)",IF(AND(IFERROR(VALUE(LEFT(AJ36,2)),0)>=5,AH36<>"YES",ISNUMBER(AN36),AN36>SETTINGS!$B$14),"STUCK in onboarding","")))
A37: 36 | B37: UPK2-FL-264 | C37: Partykles | D37: Fashion & Lifestyle | E37: FL-OCCASION-BRIDAL | F37: Delhi NCR | G37: A | H37: P0 | I37: stockist-listed | J37: Personal 1:1 email from founder/team to published business email | K37: https://partykles.in/pages/contact | L37: W1 Founding cohort | AH37: =IF(AND(B37="",C37=""),"",IF(AND(X37<>"",Y37<>"",Z37<>"",AA37<>"",AB37="Y"),"YES","no")) | AI37: =IF(AH37="YES",MAX(X37,Y37,Z37,AA37),"") | AJ37: =IF(AND(B37="",C37=""),"",IF(OR(S37="Not interested",S37="Opt-out / do not contact"),"X Declined / suppressed",IF(S37="Bounced / undeliverable","X Bounced — research",IF(AC37<>"","13 Transacting",IF(AH37="YES","12 ACTIVATED",IF(Z37<>"","11 Listing live",IF(Y37<>"","10 Profile complete",IF(X37<>"","9 Approved",IF(W37<>"","8 KYC submitted",IF(V37<>"","7 Registered",IF(T37<>"","5 Interested",IF(R37<>"","4 Responded",IF(O37<>"","2 Contacted","1 Not yet contacted"))))))))))))) | AK37: =IF(AF37<>"",AF37,IF(OR(O37="",R37<>"",LEFT(AJ37,1)="X"),"",IF(Q37<>"","",IF(P37<>"",P37+SETTINGS!$B$4,O37+SETTINGS!$B$3)))) | AL37: =IF(AJ37="","",IF(LEFT(AJ37,1)="X","None — do not contact",IF(AJ37="1 Not yet contacted","Verify route today, then send M1",IF(AND(R37="",Q37<>""),"Sequence complete — no contact before "&TEXT(Q37+SETTINGS!$B$5,"yyyy-mm-dd"),IF(AND(R37="",P37<>""),"Send final note (M4)",IF(R37="","Send follow-up (M2)",IF(AJ37="12 ACTIVATED","7-day check-in; consent & referral soft ask",IF(AJ37="13 Transacting","Repeat-activity support","Onboarding: move to next stage (see playbook §6)")))))))) | AM37: =IF(ISNUMBER(AK37),IF(AK37<=TODAY(),"DUE",""),"") | AN37: =IF(COUNT(O37,P37,Q37,R37,T37,V37,W37,X37,Y37,Z37,AA37,AC37)=0,"",TODAY()-MAX(O37,P37,Q37,R37,T37,V37,W37,X37,Y37,Z37,AA37,AC37)) | AO37: =IF(AJ37="","",IF(AND(T37<>"",U37<>"Active (verified)"),"GST: escalate (no tax advice)",IF(AND(IFERROR(VALUE(LEFT(AJ37,2)),0)>=5,AH37<>"YES",ISNUMBER(AN37),AN37>SETTINGS!$B$14),"STUCK in onboarding","")))
A38: 37 | B38: UPK2-FL-169 | C38: Lajjoo C | D38: Fashion & Lifestyle | E38: FL-OCCASION-BRIDAL | F38: Mumbai | G38: B | H38: P0 | I38: stockist-listed|large catalogue | J38: Personal 1:1 email from founder/team to published business email | K38: https://lajjooc.com/ | L38: W1 Founding cohort | AH38: =IF(AND(B38="",C38=""),"",IF(AND(X38<>"",Y38<>"",Z38<>"",AA38<>"",AB38="Y"),"YES","no")) | AI38: =IF(AH38="YES",MAX(X38,Y38,Z38,AA38),"") | AJ38: =IF(AND(B38="",C38=""),"",IF(OR(S38="Not interested",S38="Opt-out / do not contact"),"X Declined / suppressed",IF(S38="Bounced / undeliverable","X Bounced — research",IF(AC38<>"","13 Transacting",IF(AH38="YES","12 ACTIVATED",IF(Z38<>"","11 Listing live",IF(Y38<>"","10 Profile complete",IF(X38<>"","9 Approved",IF(W38<>"","8 KYC submitted",IF(V38<>"","7 Registered",IF(T38<>"","5 Interested",IF(R38<>"","4 Responded",IF(O38<>"","2 Contacted","1 Not yet contacted"))))))))))))) | AK38: =IF(AF38<>"",AF38,IF(OR(O38="",R38<>"",LEFT(AJ38,1)="X"),"",IF(Q38<>"","",IF(P38<>"",P38+SETTINGS!$B$4,O38+SETTINGS!$B$3)))) | AL38: =IF(AJ38="","",IF(LEFT(AJ38,1)="X","None — do not contact",IF(AJ38="1 Not yet contacted","Verify route today, then send M1",IF(AND(R38="",Q38<>""),"Sequence complete — no contact before "&TEXT(Q38+SETTINGS!$B$5,"yyyy-mm-dd"),IF(AND(R38="",P38<>""),"Send final note (M4)",IF(R38="","Send follow-up (M2)",IF(AJ38="12 ACTIVATED","7-day check-in; consent & referral soft ask",IF(AJ38="13 Transacting","Repeat-activity support","Onboarding: move to next stage (see playbook §6)")))))))) | AM38: =IF(ISNUMBER(AK38),IF(AK38<=TODAY(),"DUE",""),"") | AN38: =IF(COUNT(O38,P38,Q38,R38,T38,V38,W38,X38,Y38,Z38,AA38,AC38)=0,"",TODAY()-MAX(O38,P38,Q38,R38,T38,V38,W38,X38,Y38,Z38,AA38,AC38)) | AO38: =IF(AJ38="","",IF(AND(T38<>"",U38<>"Active (verified)"),"GST: escalate (no tax advice)",IF(AND(IFERROR(VALUE(LEFT(AJ38,2)),0)>=5,AH38<>"YES",ISNUMBER(AN38),AN38>SETTINGS!$B$14),"STUCK in onboarding","")))
... A53: 52 | B53: UPK2-SD-428 | C53: Objects In Space | D53: Space & Design | E53: SD-PRODUCT-MAKER | F53: Delhi NCR | G53: A | H53: P0 | I53: under-discovered | J53: 1:1 message via own-website contact form | K53: https://objectsinspace.in/ | L53: W1 Founding cohort | AH53: =IF(AND(B53="",C53=""),"",IF(AND(X53<>"",Y53<>"",Z53<>"",AA53<>"",AB53="Y"),"YES","no")) | AI53: =IF(AH53="YES",MAX(X53,Y53,Z53,AA53),"") | AJ53: =IF(AND(B53="",C53=""),"",IF(OR(S53="Not interested",S53="Opt-out / do not contact"),"X Declined / suppressed",IF(S53="Bounced / undeliverable","X Bounced — research",IF(AC53<>"","13 Transacting",IF(AH53="YES","12 ACTIVATED",IF(Z53<>"","11 Listing live",IF(Y53<>"","10 Profile complete",IF(X53<>"","9 Approved",IF(W53<>"","8 KYC submitted",IF(V53<>"","7 Registered",IF(T53<>"","5 Interested",IF(R53<>"","4 Responded",IF(O53<>"","2 Contacted","1 Not yet contacted"))))))))))))) | AK53: =IF(AF53<>"",AF53,IF(OR(O53="",R53<>"",LEFT(AJ53,1)="X"),"",IF(Q53<>"","",IF(P53<>"",P53+SETTINGS!$B$4,O53+SETTINGS!$B$3)))) | AL53: =IF(AJ53="","",IF(LEFT(AJ53,1)="X","None — do not contact",IF(AJ53="1 Not yet contacted","Verify route today, then send M1",IF(AND(R53="",Q53<>""),"Sequence complete — no contact before "&TEXT(Q53+SETTINGS!$B$5,"yyyy-mm-dd"),IF(AND(R53="",P53<>""),"Send final note (M4)",IF(R53="","Send follow-up (M2)",IF(AJ53="12 ACTIVATED","7-day check-in; consent & referral soft ask",IF(AJ53="13 Transacting","Repeat-activity support","Onboarding: move to next stage (see playbook §6)")))))))) | AM53: =IF(ISNUMBER(AK53),IF(AK53<=TODAY(),"DUE",""),"") | AN53: =IF(COUNT(O53,P53,Q53,R53,T53,V53,W53,X53,Y53,Z53,AA53,AC53)=0,"",TODAY()-MAX(O53,P53,Q53,R53,T53,V53,W53,X53,Y53,Z53,AA53,AC53)) | AO53: =IF(AJ53="","",IF(AND(T53<>"",U53<>"Active (verified)"),"GST: escalate (no tax advice)",IF(AND(IFERROR(VALUE(LEFT(AJ53,2)),0)>=5,AH53<>"YES",ISNUMBER(AN53),AN53>SETTINGS!$B$14),"STUCK in onboarding","")))
A54: 53 | B54: UPK2-SD-279 | C54: Pasana | D54: Space & Design | E54: SD-PRODUCT-MAKER | F54: Jaipur | G54: B | H54: P0 | J54: Personal 1:1 email from founder/team to published business email | K54: https://pasana.co.in/contact-us/ | L54: W1 Founding cohort | AH54: =IF(AND(B54="",C54=""),"",IF(AND(X54<>"",Y54<>"",Z54<>"",AA54<>"",AB54="Y"),"YES","no")) | AI54: =IF(AH54="YES",MAX(X54,Y54,Z54,AA54),"") | AJ54: =IF(AND(B54="",C54=""),"",IF(OR(S54="Not interested",S54="Opt-out / do not contact"),"X Declined / suppressed",IF(S54="Bounced / undeliverable","X Bounced — research",IF(AC54<>"","13 Transacting",IF(AH54="YES","12 ACTIVATED",IF(Z54<>"","11 Listing live",IF(Y54<>"","10 Profile complete",IF(X54<>"","9 Approved",IF(W54<>"","8 KYC submitted",IF(V54<>"","7 Registered",IF(T54<>"","5 Interested",IF(R54<>"","4 Responded",IF(O54<>"","2 Contacted","1 Not yet contacted"))))))))))))) | AK54: =IF(AF54<>"",AF54,IF(OR(O54="",R54<>"",LEFT(AJ54,1)="X"),"",IF(Q54<>"","",IF(P54<>"",P54+SETTINGS!$B$4,O54+SETTINGS!$B$3)))) | AL54: =IF(AJ54="","",IF(LEFT(AJ54,1)="X","None — do not contact",IF(AJ54="1 Not yet contacted","Verify route today, then send M1",IF(AND(R54="",Q54<>""),"Sequence complete — no contact before "&TEXT(Q54+SETTINGS!$B$5,"yyyy-mm-dd"),IF(AND(R54="",P54<>""),"Send final note (M4)",IF(R54="","Send follow-up (M2)",IF(AJ54="12 ACTIVATED","7-day check-in; consent & referral soft ask",IF(AJ54="13 Transacting","Repeat-activity support","Onboarding: move to next stage (see playbook §6)")))))))) | AM54: =IF(ISNUMBER(AK54),IF(AK54<=TODAY(),"DUE",""),"") | AN54: =IF(COUNT(O54,P54,Q54,R54,T54,V54,W54,X54,Y54,Z54,AA54,AC54)=0,"",TODAY()-MAX(O54,P54,Q54,R54,T54,V54,W54,X54,Y54,Z54,AA54,AC54)) | AO54: =IF(AJ54="","",IF(AND(T54<>"",U54<>"Active (verified)"),"GST: escalate (no tax advice)",IF(AND(IFERROR(VALUE(LEFT(AJ54,2)),0)>=5,AH54<>"YES",ISNUMBER(AN54),AN54>SETTINGS!$B$14),"STUCK in onboarding","")))
A55: 54 | B55: UPK2-SD-281 | C55: Mohh | D55: Space & Design | E55: SD-PRODUCT-MAKER | F55: Delhi NCR | G55: B | H55: P0 | J55: Personal 1:1 email from founder/team to published business email | K55: https://mohh.com/pages/contact | L55: W1 Founding cohort | AH55: =IF(AND(B55="",C55=""),"",IF(AND(X55<>"",Y55<>"",Z55<>"",AA55<>"",AB55="Y"),"YES","no")) | AI55: =IF(AH55="YES",MAX(X55,Y55,Z55,AA55),"") | AJ55: =IF(AND(B55="",C55=""),"",IF(OR(S55="Not interested",S55="Opt-out / do not contact"),"X Declined / suppressed",IF(S55="Bounced / undeliverable","X Bounced — research",IF(AC55<>"","13 Transacting",IF(AH55="YES","12 ACTIVATED",IF(Z55<>"","11 Listing live",IF(Y55<>"","10 Profile complete",IF(X55<>"","9 Approved",IF(W55<>"","8 KYC submitted",IF(V55<>"","7 Registered",IF(T55<>"","5 Interested",IF(R55<>"","4 Responded",IF(O55<>"","2 Contacted","1 Not yet contacted"))))))))))))) | AK55: =IF(AF55<>"",AF55,IF(OR(O55="",R55<>"",LEFT(AJ55,1)="X"),"",IF(Q55<>"","",IF(P55<>"",P55+SETTINGS!$B$4,O55+SETTINGS!$B$3)))) | AL55: =IF(AJ55="","",IF(LEFT(AJ55,1)="X","None — do not contact",IF(AJ55="1 Not yet contacted","Verify route today, then send M1",IF(AND(R55="",Q55<>""),"Sequence complete — no contact before "&TEXT(Q55+SETTINGS!$B$5,"yyyy-mm-dd"),IF(AND(R55="",P55<>""),"Send final note (M4)",IF(R55="","Send follow-up (M2)",IF(AJ55="12 ACTIVATED","7-day check-in; consent & referral soft ask",IF(AJ55="13 Transacting","Repeat-activity support","Onboarding: move to next stage (see playbook §6)")))))))) | AM55: =IF(ISNUMBER(AK55),IF(AK55<=TODAY(),"DUE",""),"") | AN55: =IF(COUNT(O55,P55,Q55,R55,T55,V55,W55,X55,Y55,Z55,AA55,AC55)=0,"",TODAY()-MAX(O55,P55,Q55,R55,T55,V55,W55,X55,Y55,Z55,AA55,AC55)) | AO55: =IF(AJ55="","",IF(AND(T55<>"",U55<>"Active (verified)"),"GST: escalate (no tax advice)",IF(AND(IFERROR(VALUE(LEFT(AJ55,2)),0)>=5,AH55<>"YES",ISNUMBER(AN55),AN55>SETTINGS!$B$14),"STUCK in onboarding","")))
A56: 55 | B56: UPK2-SD-005 | C56: The Concreate Story | D56: Space & Design | E56: SD-ARCHITECTURE | F56: Delhi NCR | G56: B | H56: P0 | J56: Personal 1:1 email from founder/team to published business email | K56: https://theconcreatestory.in/contact | L56: W1 Founding cohort | AH56: =IF(AND(B56="",C56=""),"",IF(AND(X56<>"",Y56<>"",Z56<>"",AA56<>"",AB56="Y"),"YES","no")) | AI56: =IF(AH56="YES",MAX(X56,Y56,Z56,AA56),"") | AJ56: =IF(AND(B56="",C56=""),"",IF(OR(S56="Not interested",S56="Opt-out / do not contact"),"X Declined / suppressed",IF(S56="Bounced / undeliverable","X Bounced — research",IF(AC56<>"","13 Transacting",IF(AH56="YES","12 ACTIVATED",IF(Z56<>"","11 Listing live",IF(Y56<>"","10 Profile complete",IF(X56<>"","9 Approved",IF(W56<>"","8 KYC submitted",IF(V56<>"","7 Registered",IF(T56<>"","5 Interested",IF(R56<>"","4 Responded",IF(O56<>"","2 Contacted","1 Not yet contacted"))))))))))))) | AK56: =IF(AF56<>"",AF56,IF(OR(O56="",R56<>"",LEFT(AJ56,1)="X"),"",IF(Q56<>"","",IF(P56<>"",P56+SETTINGS!$B$4,O56+SETTINGS!$B$3)))) | AL56: =IF(AJ56="","",IF(LEFT(AJ56,1)="X","None — do not contact",IF(AJ56="1 Not yet contacted","Verify route today, then send M1",IF(AND(R56="",Q56<>""),"Sequence complete — no contact before "&TEXT(Q56+SETTINGS!$B$5,"yyyy-mm-dd"),IF(AND(R56="",P56<>""),"Send final note (M4)",IF(R56="","Send follow-up (M2)",IF(AJ56="12 ACTIVATED","7-day check-in; consent & referral soft ask",IF(AJ56="13 Transacting","Repeat-activity support","Onboarding: move to next stage (see playbook §6)")))))))) | AM56: =IF(ISNUMBER(AK56),IF(AK56<=TODAY(),"DUE",""),"") | AN56: =IF(COUNT(O56,P56,Q56,R56,T56,V56,W56,X56,Y56,Z56,AA56,AC56)=0,"",TODAY()-MAX(O56,P56,Q56,R56,T56,V56,W56,X56,Y56,Z56,AA56,AC56)) | AO56: =IF(AJ56="","",IF(AND(T56<>"",U56<>"Active (verified)"),"GST: escalate (no tax advice)",IF(AND(IFERROR(VALUE(LEFT(AJ56,2)),0)>=5,AH56<>"YES",ISNUMBER(AN56),AN56>SETTINGS!$B$14),"STUCK in onboarding","")))
A57: 56 | B57: UPK2-SD-030 | C57: Studio Windows To Vernacular | D57: Space & Design | E57: SD-ARCHITECTURE | F57: Delhi NCR | G57: B | H57: P0 | J57: Personal 1:1 email from founder/team to published business email | K57: https://www.windowstovernacular.com/ | L57: W1 Founding cohort | AH57: =IF(AND(B57="",C57=""),"",IF(AND(X57<>"",Y57<>"",Z57<>"",AA57<>"",AB57="Y"),"YES","no")) | AI57: =IF(AH57="YES",MAX(X57,Y57,Z57,AA57),"") | AJ57: =IF(AND(B57="",C57=""),"",IF(OR(S57="Not interested",S57="Opt-out / do not contact"),"X Declined / suppressed",IF(S57="Bounced / undeliverable","X Bounced — research",IF(AC57<>"","13 Transacting",IF(AH57="YES","12 ACTIVATED",IF(Z57<>"","11 Listing live",IF(Y57<>"","10 Profile complete",IF(X57<>"","9 Approved",IF(W57<>"","8 KYC submitted",IF(V57<>"","7 Registered",IF(T57<>"","5 Interested",IF(R57<>"","4 Responded",IF(O57<>"","2 Contacted","1 Not yet contacted"))))))))))))) | AK57: =IF(AF57<>"",AF57,IF(OR(O57="",R57<>"",LEFT(AJ57,1)="X"),"",IF(Q57<>"","",IF(P57<>"",P57+SETTINGS!$B$4,O57+SETTINGS!$B$3)))) | AL57: =IF(AJ57="","",IF(LEFT(AJ57,1)="X","None — do not contact",IF(AJ57="1 Not yet contacted","Verify route today, then send M1",IF(AND(R57="",Q57<>""),"Sequence complete — no contact before "&TEXT(Q57+SETTINGS!$B$5,"yyyy-mm-dd"),IF(AND(R57="",P57<>""),"Send final note (M4)",IF(R57="","Send follow-up (M2)",IF(AJ57="12 ACTIVATED","7-day check-in; consent & referral soft ask",IF(AJ57="13 Transacting","Repeat-activity support","Onboarding: move to next stage (see playbook §6)")))))))) | AM57: =IF(ISNUMBER(AK57),IF(AK57<=TODAY(),"DUE",""),"") | AN57: =IF(COUNT(O57,P57,Q57,R57,T57,V57,W57,X57,Y57,Z57,AA57,AC57)=0,"",TODAY()-MAX(O57,P57,Q57,R57,T57,V57,W57,X57,Y57,Z57,AA57,AC57)) | AO57: =IF(AJ57="","",IF(AND(T57<>"",U57<>"Active (verified)"),"GST: escalate (no tax advice)",IF(AND(IFERROR(VALUE(LEFT(AJ57,2)),0)>=5,AH57<>"YES",ISNUMBER(AN57),AN57>SETTINGS!$B$14),"STUCK in onboarding","")))
A58: 57 | B58: UPK2-SD-050 | C58: Studio Navya (Navya & a Quarter) | D58: Space & Design | E58: SD-INTERIOR | F58: Delhi NCR | G58: A | H58: P0 | I58: under-discovered | J58: Personal 1:1 email from founder/team to published business email | K58: https://www.navya.studio/ | L58: W1 Founding cohort | AH58: =IF(AND(B58="",C58=""),"",IF(AND(X58<>"",Y58<>"",Z58<>"",AA58<>"",AB58="Y"),"YES","no")) | AI58: =IF(AH58="YES",MAX(X58,Y58,Z58,AA58),"") | AJ58: =IF(AND(B58="",C58=""),"",IF(OR(S58="Not interested",S58="Opt-out / do not contact"),"X Declined / suppressed",IF(S58="Bounced / undeliverable","X Bounced — research",IF(AC58<>"","13 Transacting",IF(AH58="YES","12 ACTIVATED",IF(Z58<>"","11 Listing live",IF(Y58<>"","10 Profile complete",IF(X58<>"","9 Approved",IF(W58<>"","8 KYC submitted",IF(V58<>"","7 Registered",IF(T58<>"","5 Interested",IF(R58<>"","4 Responded",IF(O58<>"","2 Contacted","1 Not yet contacted"))))))))))))) | AK58: =IF(AF58<>"",AF58,IF(OR(O58="",R58<>"",LEFT(AJ58,1)="X"),"",IF(Q58<>"","",IF(P58<>"",P58+SETTINGS!$B$4,O58+SETTINGS!$B$3)))) | AL58: =IF(AJ58="","",IF(LEFT(AJ58,1)="X","None — do not contact",IF(AJ58="1 Not yet contacted","Verify route today, then send M1",IF(AND(R58="",Q58<>""),"Sequence complete — no contact before "&TEXT(Q58+SETTINGS!$B$5,"yyyy-mm-dd"),IF(AND(R58="",P58<>""),"Send final note (M4)",IF(R58="","Send follow-up (M2)",IF(AJ58="12 ACTIVATED","7-day check-in; consent & referral soft ask",IF(AJ58="13 Transacting","Repeat-activity support","Onboarding: move to next stage (see playbook §6)")))))))) | AM58: =IF(ISNUMBER(AK58),IF(AK58<=TODAY(),"DUE",""),"") | AN58: =IF(COUNT(O58,P58,Q58,R58,T58,V58,W58,X58,Y58,Z58,AA58,AC58)=0,"",TODAY()-MAX(O58,P58,Q58,R58,T58,V58,W58,X58,Y58,Z58,AA58,AC58)) | AO58: =IF(AJ58="","",IF(AND(T58<>"",U58<>"Active (verified)"),"GST: escalate (no tax advice)",IF(AND(IFERROR(VALUE(LEFT(AJ58,2)),0)>=5,AH58<>"YES",ISNUMBER(AN58),AN58>SETTINGS!$B$14),"STUCK in onboarding","")))
A59: 58 | B59: UPK2-SD-064 | C59: Saachi Rana Design Studio | D59: Space & Design | E59: SD-INTERIOR | F59: Delhi NCR | G59: A | H59: P0 | I59: under-discovered | J59: Personal 1:1 email from founder/team to published business email | K59: https://www.saachirana.com/contact | L59: W1 Founding cohort | AH59: =IF(AND(B59="",C59=""),"",IF(AND(X59<>"",Y59<>"",Z59<>"",AA59<>"",AB59="Y"),"YES","no")) | AI59: =IF(AH59="YES",MAX(X59,Y59,Z59,AA59),"") | AJ59: =IF(AND(B59="",C59=""),"",IF(OR(S59="Not interested",S59="Opt-out / do not contact"),"X Declined / suppressed",IF(S59="Bounced / undeliverable","X Bounced — research",IF(AC59<>"","13 Transacting",IF(AH59="YES","12 ACTIVATED",IF(Z59<>"","11 Listing live",IF(Y59<>"","10 Profile complete",IF(X59<>"","9 Approved",IF(W59<>"","8 KYC submitted",IF(V59<>"","7 Registered",IF(T59<>"","5 Interested",IF(R59<>"","4 Responded",IF(O59<>"","2 Contacted","1 Not yet contacted"))))))))))))) | AK59: =IF(AF59<>"",AF59,IF(OR(O59="",R59<>"",LEFT(AJ59,1)="X"),"",IF(Q59<>"","",IF(P59<>"",P59+SETTINGS!$B$4,O59+SETTINGS!$B$3)))) | AL59: =IF(AJ59="","",IF(LEFT(AJ59,1)="X","None — do not contact",IF(AJ59="1 Not yet contacted","Verify route today, then send M1",IF(AND(R59="",Q59<>""),"Sequence complete — no contact before "&TEXT(Q59+SETTINGS!$B$5,"yyyy-mm-dd"),IF(AND(R59="",P59<>""),"Send final note (M4)",IF(R59="","Send follow-up (M2)",IF(AJ59="12 ACTIVATED","7-day check-in; consent & referral soft ask",IF(AJ59="13 Transacting","Repeat-activity support","Onboarding: move to next stage (see playbook §6)")))))))) | AM59: =IF(ISNUMBER(AK59),IF(AK59<=TODAY(),"DUE",""),"") | AN59: =IF(COUNT(O59,P59,Q59,R59,T59,V59,W59,X59,Y59,Z59,AA59,AC59)=0,"",TODAY()-MAX(O59,P59,Q59,R59,T59,V59,W59,X59,Y59,Z59,AA59,AC59)) | AO59: =IF(AJ59="","",IF(AND(T59<>"",U59<>"Active (verified)"),"GST: escalate (no tax advice)",IF(AND(IFERROR(VALUE(LEFT(AJ59,2)),0)>=5,AH59<>"YES",ISNUMBER(AN59),AN59>SETTINGS!$B$14),"STUCK in onboarding","")))
A60: 59 | B60: UPK2-SD-002 | C60: Logic Design + Build | D60: Space & Design | E60: SD-ARCHITECTURE | F60: Delhi NCR | G60: C | H60: P0 | J60: Personal 1:1 email from founder/team to published business email | K60: https://www.logic.co.in/ | L60: W1 Founding cohort | AH60: =IF(AND(B60="",C60=""),"",IF(AND(X60<>"",Y60<>"",Z60<>"",AA60<>"",AB60="Y"),"YES","no")) | AI60: =IF(AH60="YES",MAX(X60,Y60,Z60,AA60),"") | AJ60: =IF(AND(B60="",C60=""),"",IF(OR(S60="Not interested",S60="Opt-out / do not contact"),"X Declined / suppressed",IF(S60="Bounced / undeliverable","X Bounced — research",IF(AC60<>"","13 Transacting",IF(AH60="YES","12 ACTIVATED",IF(Z60<>"","11 Listing live",IF(Y60<>"","10 Profile complete",IF(X60<>"","9 Approved",IF(W60<>"","8 KYC submitted",IF(V60<>"","7 Registered",IF(T60<>"","5 Interested",IF(R60<>"","4 Responded",IF(O60<>"","2 Contacted","1 Not yet contacted"))))))))))))) | AK60: =IF(AF60<>"",AF60,IF(OR(O60="",R60<>"",LEFT(AJ60,1)="X"),"",IF(Q60<>"","",IF(P60<>"",P60+SETTINGS!$B$4,O60+SETTINGS!$B$3)))) | AL60: =IF(AJ60="","",IF(LEFT(AJ60,1)="X","None — do not contact",IF(AJ60="1 Not yet contacted","Verify route today, then send M1",IF(AND(R60="",Q60<>""),"Sequence complete — no contact before "&TEXT(Q60+SETTINGS!$B$5,"yyyy-mm-dd"),IF(AND(R60="",P60<>""),"Send final note (M4)",IF(R60="","Send follow-up (M2)",IF(AJ60="12 ACTIVATED","7-day check-in; consent & referral soft ask",IF(AJ60="13 Transacting","Repeat-activity support","Onboarding: move to next stage (see playbook §6)")))))))) | AM60: =IF(ISNUMBER(AK60),IF(AK60<=TODAY(),"DUE",""),"") | AN60: =IF(COUNT(O60,P60,Q60,R60,T60,V60,W60,X60,Y60,Z60,AA60,AC60)=0,"",TODAY()-MAX(O60,P60,Q60,R60,T60,V60,W60,X60,Y60,Z60,AA60,AC60)) | AO60: =IF(AJ60="","",IF(AND(T60<>"",U60<>"Active (verified)"),"GST: escalate (no tax advice)",IF(AND(IFERROR(VALUE(LEFT(AJ60,2)),0)>=5,AH60<>"YES",ISNUMBER(AN60),AN60>SETTINGS!$B$14),"STUCK in onboarding","")))
A61: 60 | B61: UPK2-SD-001 | C61: DesigNiche Architecture | D61: Space & Design | E61: SD-ARCHITECTURE | F61: Delhi NCR | G61: B | H61: P0 | J61: Personal 1:1 email from founder/team to published business email | K61: https://designiche.co/contact-us.php | L61: W1 Founding cohort | AH61: =IF(AND(B61="",C61=""),"",IF(AND(X61<>"",Y61<>"",Z61<>"",AA61<>"",AB61="Y"),"YES","no")) | AI61: =IF(AH61="YES",MAX(X61,Y61,Z61,AA61),"") | AJ61: =IF(AND(B61="",C61=""),"",IF(OR(S61="Not interested",S61="Opt-out / do not contact"),"X Declined / suppressed",IF(S61="Bounced / undeliverable","X Bounced — research",IF(AC61<>"","13 Transacting",IF(AH61="YES","12 ACTIVATED",IF(Z61<>"","11 Listing live",IF(Y61<>"","10 Profile complete",IF(X61<>"","9 Approved",IF(W61<>"","8 KYC submitted",IF(V61<>"","7 Registered",IF(T61<>"","5 Interested",IF(R61<>"","4 Responded",IF(O61<>"","2 Contacted","1 Not yet contacted"))))))))))))) | AK61: =IF(AF61<>"",AF61,IF(OR(O61="",R61<>"",LEFT(AJ61,1)="X"),"",IF(Q61<>"","",IF(P61<>"",P61+SETTINGS!$B$4,O61+SETTINGS!$B$3)))) | AL61: =IF(AJ61="","",IF(LEFT(AJ61,1)="X","None — do not contact",IF(AJ61="1 Not yet contacted","Verify route today, then send M1",IF(AND(R61="",Q61<>""),"Sequence complete — no contact before "&TEXT(Q61+SETTINGS!$B$5,"yyyy-mm-dd"),IF(AND(R61="",P61<>""),"Send final note (M4)",IF(R61="","Send follow-up (M2)",IF(AJ61="12 ACTIVATED","7-day check-in; consent & referral soft ask",IF(AJ61="13 Transacting","Repeat-activity support","Onboarding: move to next stage (see playbook §6)")))))))) | AM61: =IF(ISNUMBER(AK61),IF(AK61<=TODAY(),"DUE",""),"") | AN61: =IF(COUNT(O61,P61,Q61,R61,T61,V61,W61,X61,Y61,Z61,AA61,AC61)=0,"",TODAY()-MAX(O61,P61,Q61,R61,T61,V61,W61,X61,Y61,Z61,AA61,AC61)) | AO61: =IF(AJ61="","",IF(AND(T61<>"",U61<>"Active (verified)"),"GST: escalate (no tax advice)",IF(AND(IFERROR(VALUE(LEFT(AJ61,2)),0)>=5,AH61<>"YES",ISNUMBER(AN61),AN61>SETTINGS!$B$14),"STUCK in onboarding","")))
A62: 61 | B62: UPK2-SD-031 | C62: The Goodwood | D62: Space & Design | E62: SD-INTERIOR | F62: Delhi NCR | G62: A | H62: P0 | I62: under-discovered | J62: Personal 1:1 email from founder/team to published business email | K62: https://thegoodwood.in/ | L62: W1 Founding cohort | AH62: =IF(AND(B62="",C62=""),"",IF(AND(X62<>"",Y62<>"",Z62<>"",AA62<>"",AB62="Y"),"YES","no")) | AI62: =IF(AH62="YES",MAX(X62,Y62,Z62,AA62),"") | AJ62: =IF(AND(B62="",C62=""),"",IF(OR(S62="Not interested",S62="Opt-out / do not contact"),"X Declined / suppressed",IF(S62="Bounced / undeliverable","X Bounced — research",IF(AC62<>"","13 Transacting",IF(AH62="YES","12 ACTIVATED",IF(Z62<>"","11 Listing live",IF(Y62<>"","10 Profile complete",IF(X62<>"","9 Approved",IF(W62<>"","8 KYC submitted",IF(V62<>"","7 Registered",IF(T62<>"","5 Interested",IF(R62<>"","4 Responded",IF(O62<>"","2 Contacted","1 Not yet contacted"))))))))))))) | AK62: =IF(AF62<>"",AF62,IF(OR(O62="",R62<>"",LEFT(AJ62,1)="X"),"",IF(Q62<>"","",IF(P62<>"",P62+SETTINGS!$B$4,O62+SETTINGS!$B$3)))) | AL62: =IF(AJ62="","",IF(LEFT(AJ62,1)="X","None — do not contact",IF(AJ62="1 Not yet contacted","Verify route today, then send M1",IF(AND(R62="",Q62<>""),"Sequence complete — no contact before "&TEXT(Q62+SETTINGS!$B$5,"yyyy-mm-dd"),IF(AND(R62="",P62<>""),"Send final note (M4)",IF(R62="","Send follow-up (M2)",IF(AJ62="12 ACTIVATED","7-day check-in; consent & referral soft ask",IF(AJ62="13 Transacting","Repeat-activity support","Onboarding: move to next stage (see playbook §6)")))))))) | AM62: =IF(ISNUMBER(AK62),IF(AK62<=TODAY(),"DUE",""),"") | AN62: =IF(COUNT(O62,P62,Q62,R62,T62,V62,W62,X62,Y62,Z62,AA62,AC62)=0,"",TODAY()-MAX(O62,P62,Q62,R62,T62,V62,W62,X62,Y62,Z62,AA62,AC62)) | AO62: =IF(AJ62="","",IF(AND(T62<>"",U62<>"Active (verified)"),"GST: escalate (no tax advice)",IF(AND(IFERROR(VALUE(LEFT(AJ62,2)),0)>=5,AH62<>"YES",ISNUMBER(AN62),AN62>SETTINGS!$B$14),"STUCK in onboarding","")))
A63: 62 | B63: UPK2-SD-027 | C63: Moi Den Interiors | D63: Space & Design | E63: SD-INTERIOR | F63: Delhi NCR | G63: B | H63: P0 | J63: 1:1 message via own-website contact form | K63: https://www.moiden.in/contact-us/ | L63: W1 Founding cohort | AH63: =IF(AND(B63="",C63=""),"",IF(AND(X63<>"",Y63<>"",Z63<>"",AA63<>"",AB63="Y"),"YES","no")) | AI63: =IF(AH63="YES",MAX(X63,Y63,Z63,AA63),"") | AJ63: =IF(AND(B63="",C63=""),"",IF(OR(S63="Not interested",S63="Opt-out / do not contact"),"X Declined / suppressed",IF(S63="Bounced / undeliverable","X Bounced — research",IF(AC63<>"","13 Transacting",IF(AH63="YES","12 ACTIVATED",IF(Z63<>"","11 Listing live",IF(Y63<>"","10 Profile complete",IF(X63<>"","9 Approved",IF(W63<>"","8 KYC submitted",IF(V63<>"","7 Registered",IF(T63<>"","5 Interested",IF(R63<>"","4 Responded",IF(O63<>"","2 Contacted","1 Not yet contacted"))))))))))))) | AK63: =IF(AF63<>"",AF63,IF(OR(O63="",R63<>"",LEFT(AJ63,1)="X"),"",IF(Q63<>"","",IF(P63<>"",P63+SETTINGS!$B$4,O63+SETTINGS!$B$3)))) | AL63: =IF(AJ63="","",IF(LEFT(AJ63,1)="X","None — do not contact",IF(AJ63="1 Not yet contacted","Verify route today, then send M1",IF(AND(R63="",Q63<>""),"Sequence complete — no contact before "&TEXT(Q63+SETTINGS!$B$5,"yyyy-mm-dd"),IF(AND(R63="",P63<>""),"Send final note (M4)",IF(R63="","Send follow-up (M2)",IF(AJ63="12 ACTIVATED","7-day check-in; consent & referral soft ask",IF(AJ63="13 Transacting","Repeat-activity support","Onboarding: move to next stage (see playbook §6)")))))))) | AM63: =IF(ISNUMBER(AK63),IF(AK63<=TODAY(),"DUE",""),"") | AN63: =IF(COUNT(O63,P63,Q63,R63,T63,V63,W63,X63,Y63,Z63,AA63,AC63)=0,"",TODAY()-MAX(O63,P63,Q63,R63,T63,V63,W63,X63,Y63,Z63,AA63,AC63)) | AO63: =IF(AJ63="","",IF(AND(T63<>"",U63<>"Active (verified)"),"GST: escalate (no tax advice)",IF(AND(IFERROR(VALUE(LEFT(AJ63,2)),0)>=5,AH63<>"YES",ISNUMBER(AN63),AN63>SETTINGS!$B$14),"STUCK in onboarding","")))
A64: 63 | B64: UPK2-SD-011 | C64: Shefali Design Studio | D64: Space & Design | E64: SD-ARCHITECTURE | F64: Delhi NCR | G64: B | H64: P0 | J64: Personal 1:1 email from founder/team to published business email | K64: https://shefalidesignstudio.com/ | L64: W1 Founding cohort | AH64: =IF(AND(B64="",C64=""),"",IF(AND(X64<>"",Y64<>"",Z64<>"",AA64<>"",AB64="Y"),"YES","no")) | AI64: =IF(AH64="YES",MAX(X64,Y64,Z64,AA64),"") | AJ64: =IF(AND(B64="",C64=""),"",IF(OR(S64="Not interested",S64="Opt-out / do not contact"),"X Declined / suppressed",IF(S64="Bounced / undeliverable","X Bounced — research",IF(AC64<>"","13 Transacting",IF(AH64="YES","12 ACTIVATED",IF(Z64<>"","11 Listing live",IF(Y64<>"","10 Profile complete",IF(X64<>"","9 Approved",IF(W64<>"","8 KYC submitted",IF(V64<>"","7 Registered",IF(T64<>"","5 Interested",IF(R64<>"","4 Responded",IF(O64<>"","2 Contacted","1 Not yet contacted"))))))))))))) | AK64: =IF(AF64<>"",AF64,IF(OR(O64="",R64<>"",LEFT(AJ64,1)="X"),"",IF(Q64<>"","",IF(P64<>"",P64+SETTINGS!$B$4,O64+SETTINGS!$B$3)))) | AL64: =IF(AJ64="","",IF(LEFT(AJ64,1)="X","None — do not contact",IF(AJ64="1 Not yet contacted","Verify route today, then send M1",IF(AND(R64="",Q64<>""),"Sequence complete — no contact before "&TEXT(Q64+SETTINGS!$B$5,"yyyy-mm-dd"),IF(AND(R64="",P64<>""),"Send final note (M4)",IF(R64="","Send follow-up (M2)",IF(AJ64="12 ACTIVATED","7-day check-in; consent & referral soft ask",IF(AJ64="13 Transacting","Repeat-activity support","Onboarding: move to next stage (see playbook §6)")))))))) | AM64: =IF(ISNUMBER(AK64),IF(AK64<=TODAY(),"DUE",""),"") | AN64: =IF(COUNT(O64,P64,Q64,R64,T64,V64,W64,X64,Y64,Z64,AA64,AC64)=0,"",TODAY()-MAX(O64,P64,Q64,R64,T64,V64,W64,X64,Y64,Z64,AA64,AC64)) | AO64: =IF(AJ64="","",IF(AND(T64<>"",U64<>"Active (verified)"),"GST: escalate (no tax advice)",IF(AND(IFERROR(VALUE(LEFT(AJ64,2)),0)>=5,AH64<>"YES",ISNUMBER(AN64),AN64>SETTINGS!$B$14),"STUCK in onboarding","")))
A65: 64 | B65: UPK2-DV-002 | C65: Dream Pen Calligraphy | D65: Digital & Visual Arts | E65: DV-CALLIGRAPHY-STATIONERY | F65: Bengaluru | G65: A | H65: P0 | I65: under-discovered | J65: Personal 1:1 email from founder/team to published business email | K65: https://www.dreampencalligraphy.com/contact | L65: W1 Founding cohort | AH65: =IF(AND(B65="",C65=""),"",IF(AND(X65<>"",Y65<>"",Z65<>"",AA65<>"",AB65="Y"),"YES","no")) | AI65: =IF(AH65="YES",MAX(X65,Y65,Z65,AA65),"") | AJ65: =IF(AND(B65="",C65=""),"",IF(OR(S65="Not interested",S65="Opt-out / do not contact"),"X Declined / suppressed",IF(S65="Bounced / undeliverable","X Bounced — research",IF(AC65<>"","13 Transacting",IF(AH65="YES","12 ACTIVATED",IF(Z65<>"","11 Listing live",IF(Y65<>"","10 Profile complete",IF(X65<>"","9 Approved",IF(W65<>"","8 KYC submitted",IF(V65<>"","7 Registered",IF(T65<>"","5 Interested",IF(R65<>"","4 Responded",IF(O65<>"","2 Contacted","1 Not yet contacted"))))))))))))) | AK65: =IF(AF65<>"",AF65,IF(OR(O65="",R65<>"",LEFT(AJ65,1)="X"),"",IF(Q65<>"","",IF(P65<>"",P65+SETTINGS!$B$4,O65+SETTINGS!$B$3)))) | AL65: =IF(AJ65="","",IF(LEFT(AJ65,1)="X","None — do not contact",IF(AJ65="1 Not yet contacted","Verify route today, then send M1",IF(AND(R65="",Q65<>""),"Sequence complete — no contact before "&TEXT(Q65+SETTINGS!$B$5,"yyyy-mm-dd"),IF(AND(R65="",P65<>""),"Send final note (M4)",IF(R65="","Send follow-up (M2)",IF(AJ65="12 ACTIVATED","7-day check-in; consent & referral soft ask",IF(AJ65="13 Transacting","Repeat-activity support","Onboarding: move to next stage (see playbook §6)")))))))) | AM65: =IF(ISNUMBER(AK65),IF(AK65<=TODAY(),"DUE",""),"") | AN65: =IF(COUNT(O65,P65,Q65,R65,T65,V65,W65,X65,Y65,Z65,AA65,AC65)=0,"",TODAY()-MAX(O65,P65,Q65,R65,T65,V65,W65,X65,Y65,Z65,AA65,AC65)) | AO65: =IF(AJ65="","",IF(AND(T65<>"",U65<>"Active (verified)"),"GST: escalate (no tax advice)",IF(AND(IFERROR(VALUE(LEFT(AJ65,2)),0)>=5,AH65<>"YES",ISNUMBER(AN65),AN65>SETTINGS!$B$14),"STUCK in onboarding","")))
A66: 65 | B66: UPK2-DV-030 | C66: Deep Ink Letters | D66: Digital & Visual Arts | E66: DV-CALLIGRAPHY-STATIONERY | F66: Mumbai | G66: A | H66: P1 | J66: Personal 1:1 email from founder/team to published business email | K66: https://deepinkletters.com/contact | L66: W1 Founding cohort | AH66: =IF(AND(B66="",C66=""),"",IF(AND(X66<>"",Y66<>"",Z66<>"",AA66<>"",AB66="Y"),"YES","no")) | AI66: =IF(AH66="YES",MAX(X66,Y66,Z66,AA66),"") | AJ66: =IF(AND(B66="",C66=""),"",IF(OR(S66="Not interested",S66="Opt-out / do not contact"),"X Declined / suppressed",IF(S66="Bounced / undeliverable","X Bounced — research",IF(AC66<>"","13 Transacting",IF(AH66="YES","12 ACTIVATED",IF(Z66<>"","11 Listing live",IF(Y66<>"","10 Profile complete",IF(X66<>"","9 Approved",IF(W66<>"","8 KYC submitted",IF(V66<>"","7 Registered",IF(T66<>"","5 Interested",IF(R66<>"","4 Responded",IF(O66<>"","2 Contacted","1 Not yet contacted"))))))))))))) | AK66: =IF(AF66<>"",AF66,IF(OR(O66="",R66<>"",LEFT(AJ66,1)="X"),"",IF(Q66<>"","",IF(P66<>"",P66+SETTINGS!$B$4,O66+SETTINGS!$B$3)))) | AL66: =IF(AJ66="","",IF(LEFT(AJ66,1)="X","None — do not contact",IF(AJ66="1 Not yet contacted","Verify route today, then send M1",IF(AND(R66="",Q66<>""),"Sequence complete — no contact before "&TEXT(Q66+SETTINGS!$B$5,"yyyy-mm-dd"),IF(AND(R66="",P66<>""),"Send final note (M4)",IF(R66="","Send follow-up (M2)",IF(AJ66="12 ACTIVATED","7-day check-in; consent & referral soft ask",IF(AJ66="13 Transacting","Repeat-activity support","Onboarding: move to next stage (see playbook §6)")))))))) | AM66: =IF(ISNUMBER(AK66),IF(AK66<=TODAY(),"DUE",""),"") | AN66: =IF(COUNT(O66,P66,Q66,R66,T66,V66,W66,X66,Y66,Z66,AA66,AC66)=0,"",TODAY()-MAX(O66,P66,Q66,R66,T66,V66,W66,X66,Y66,Z66,AA66,AC66)) | AO66: =IF(AJ66="","",IF(AND(T66<>"",U66<>"Active (verified)"),"GST: escalate (no tax advice)",IF(AND(IFERROR(VALUE(LEFT(AJ66,2)),0)>=5,AH66<>"YES",ISNUMBER(AN66),AN66>SETTINGS!$B$14),"STUCK in onboarding","")))
A67: 66 | B67: UPK2-DV-032 | C67: Osprey Invites | D67: Digital & Visual Arts | E67: DV-CALLIGRAPHY-STATIONERY | F67: Mumbai | G67: A | H67: P0 | J67: Personal 1:1 email from founder/team to published business email | K67: https://ospreyinvites.com/pages/contact | L67: W1 Founding cohort | AH67: =IF(AND(B67="",C67=""),"",IF(AND(X67<>"",Y67<>"",Z67<>"",AA67<>"",AB67="Y"),"YES","no")) | AI67: =IF(AH67="YES",MAX(X67,Y67,Z67,AA67),"") | AJ67: =IF(AND(B67="",C67=""),"",IF(OR(S67="Not interested",S67="Opt-out / do not contact"),"X Declined / suppressed",IF(S67="Bounced / undeliverable","X Bounced — research",IF(AC67<>"","13 Transacting",IF(AH67="YES","12 ACTIVATED",IF(Z67<>"","11 Listing live",IF(Y67<>"","10 Profile complete",IF(X67<>"","9 Approved",IF(W67<>"","8 KYC submitted",IF(V67<>"","7 Registered",IF(T67<>"","5 Interested",IF(R67<>"","4 Responded",IF(O67<>"","2 Contacted","1 Not yet contacted"))))))))))))) | AK67: =IF(AF67<>"",AF67,IF(OR(O67="",R67<>"",LEFT(AJ67,1)="X"),"",IF(Q67<>"","",IF(P67<>"",P67+SETTINGS!$B$4,O67+SETTINGS!$B$3)))) | AL67: =IF(AJ67="","",IF(LEFT(AJ67,1)="X","None — do not contact",IF(AJ67="1 Not yet contacted","Verify route today, then send M1",IF(AND(R67="",Q67<>""),"Sequence complete — no contact before "&TEXT(Q67+SETTINGS!$B$5,"yyyy-mm-dd"),IF(AND(R67="",P67<>""),"Send final note (M4)",IF(R67="","Send follow-up (M2)",IF(AJ67="12 ACTIVATED","7-day check-in; consent & referral soft ask",IF(AJ67="13 Transacting","Repeat-activity support","Onboarding: move to next stage (see playbook §6)")))))))) | AM67: =IF(ISNUMBER(AK67),IF(AK67<=TODAY(),"DUE",""),"") | AN67: =IF(COUNT(O67,P67,Q67,R67,T67,V67,W67,X67,Y67,Z67,AA67,AC67)=0,"",TODAY()-MAX(O67,P67,Q67,R67,T67,V67,W67,X67,Y67,Z67,AA67,AC67)) | AO67: =IF(AJ67="","",IF(AND(T67<>"",U67<>"Active (verified)"),"GST: escalate (no tax advice)",IF(AND(IFERROR(VALUE(LEFT(AJ67,2)),0)>=5,AH67<>"YES",ISNUMBER(AN67),AN67>SETTINGS!$B$14),"STUCK in onboarding","")))
A68: 67 | B68: UPK2-DV-008 | C68: Alicia Souza | D68: Digital & Visual Arts | E68: DV-ARTIST-ILLUSTRATOR | F68: Bengaluru | G68: C | H68: P0 | J68: Personal 1:1 email from founder/team to published business email | K68: https://aliciasouza.com/pages/contact | L68: W1 Founding cohort | AH68: =IF(AND(B68="",C68=""),"",IF(AND(X68<>"",Y68<>"",Z68<>"",AA68<>"",AB68="Y"),"YES","no")) | AI68: =IF(AH68="YES",MAX(X68,Y68,Z68,AA68),"") | AJ68: =IF(AND(B68="",C68=""),"",IF(OR(S68="Not interested",S68="Opt-out / do not contact"),"X Declined / suppressed",IF(S68="Bounced / undeliverable","X Bounced — research",IF(AC68<>"","13 Transacting",IF(AH68="YES","12 ACTIVATED",IF(Z68<>"","11 Listing live",IF(Y68<>"","10 Profile complete",IF(X68<>"","9 Approved",IF(W68<>"","8 KYC submitted",IF(V68<>"","7 Registered",IF(T68<>"","5 Interested",IF(R68<>"","4 Responded",IF(O68<>"","2 Contacted","1 Not yet contacted"))))))))))))) | AK68: =IF(AF68<>"",AF68,IF(OR(O68="",R68<>"",LEFT(AJ68,1)="X"),"",IF(Q68<>"","",IF(P68<>"",P68+SETTINGS!$B$4,O68+SETTINGS!$B$3)))) | AL68: =IF(AJ68="","",IF(LEFT(AJ68,1)="X","None — do not contact",IF(AJ68="1 Not yet contacted","Verify route today, then send M1",IF(AND(R68="",Q68<>""),"Sequence complete — no contact before "&TEXT(Q68+SETTINGS!$B$5,"yyyy-mm-dd"),IF(AND(R68="",P68<>""),"Send final note (M4)",IF(R68="","Send follow-up (M2)",IF(AJ68="12 ACTIVATED","7-day check-in; consent & referral soft ask",IF(AJ68="13 Transacting","Repeat-activity support","Onboarding: move to next stage (see playbook §6)")))))))) | AM68: =IF(ISNUMBER(AK68),IF(AK68<=TODAY(),"DUE",""),"") | AN68: =IF(COUNT(O68,P68,Q68,R68,T68,V68,W68,X68,Y68,Z68,AA68,AC68)=0,"",TODAY()-MAX(O68,P68,Q68,R68,T68,V68,W68,X68,Y68,Z68,AA68,AC68)) | AO68: =IF(AJ68="","",IF(AND(T68<>"",U68<>"Active (verified)"),"GST: escalate (no tax advice)",IF(AND(IFERROR(VALUE(LEFT(AJ68,2)),0)>=5,AH68<>"YES",ISNUMBER(AN68),AN68>SETTINGS!$B$14),"STUCK in onboarding","")))
A69: 68 | B69: UPK2-DV-036 | C69: Customizing Creativity | D69: Digital & Visual Arts | E69: DV-CALLIGRAPHY-STATIONERY | F69: Mumbai | G69: B | H69: P1 | J69: Personal 1:1 email from founder/team to published business email | K69: https://www.customizingcreativity.in/ | L69: W1 Founding cohort | AH69: =IF(AND(B69="",C69=""),"",IF(AND(X69<>"",Y69<>"",Z69<>"",AA69<>"",AB69="Y"),"YES","no")) | AI69: =IF(AH69="YES",MAX(X69,Y69,Z69,AA69),"") | AJ69: =IF(AND(B69="",C69=""),"",IF(OR(S69="Not interested",S69="Opt-out / do not contact"),"X Declined / suppressed",IF(S69="Bounced / undeliverable","X Bounced — research",IF(AC69<>"","13 Transacting",IF(AH69="YES","12 ACTIVATED",IF(Z69<>"","11 Listing live",IF(Y69<>"","10 Profile complete",IF(X69<>"","9 Approved",IF(W69<>"","8 KYC submitted",IF(V69<>"","7 Registered",IF(T69<>"","5 Interested",IF(R69<>"","4 Responded",IF(O69<>"","2 Contacted","1 Not yet contacted"))))))))))))) | AK69: =IF(AF69<>"",AF69,IF(OR(O69="",R69<>"",LEFT(AJ69,1)="X"),"",IF(Q69<>"","",IF(P69<>"",P69+SETTINGS!$B$4,O69+SETTINGS!$B$3)))) | AL69: =IF(AJ69="","",IF(LEFT(AJ69,1)="X","None — do not contact",IF(AJ69="1 Not yet contacted","Verify route today, then send M1",IF(AND(R69="",Q69<>""),"Sequence complete — no contact before "&TEXT(Q69+SETTINGS!$B$5,"yyyy-mm-dd"),IF(AND(R69="",P69<>""),"Send final note (M4)",IF(R69="","Send follow-up (M2)",IF(AJ69="12 ACTIVATED","7-day check-in; consent & referral soft ask",IF(AJ69="13 Transacting","Repeat-activity support","Onboarding: move to next stage (see playbook §6)")))))))) | AM69: =IF(ISNUMBER(AK69),IF(AK69<=TODAY(),"DUE",""),"") | AN69: =IF(COUNT(O69,P69,Q69,R69,T69,V69,W69,X69,Y69,Z69,AA69,AC69)=0,"",TODAY()-MAX(O69,P69,Q69,R69,T69,V69,W69,X69,Y69,Z69,AA69,AC69)) | AO69: =IF(AJ69="","",IF(AND(T69<>"",U69<>"Active (verified)"),"GST: escalate (no tax advice)",IF(AND(IFERROR(VALUE(LEFT(AJ69,2)),0)>=5,AH69<>"YES",ISNUMBER(AN69),AN69>SETTINGS!$B$14),"STUCK in onboarding","")))
A70: 69 | B70: UPK2-DV-035 | C70: Girjesh Jaiswar | D70: Digital & Visual Arts | E70: DV-ARTIST-ILLUSTRATOR | F70: Mumbai | G70: A | H70: P1 | J70: Personal 1:1 email from founder/team to published business email | K70: https://girjeshjaiswar.com/contact | L70: W1 Founding cohort | AH70: =IF(AND(B70="",C70=""),"",IF(AND(X70<>"",Y70<>"",Z70<>"",AA70<>"",AB70="Y"),"YES","no")) | AI70: =IF(AH70="YES",MAX(X70,Y70,Z70,AA70),"") | AJ70: =IF(AND(B70="",C70=""),"",IF(OR(S70="Not interested",S70="Opt-out / do not contact"),"X Declined / suppressed",IF(S70="Bounced / undeliverable","X Bounced — research",IF(AC70<>"","13 Transacting",IF(AH70="YES","12 ACTIVATED",IF(Z70<>"","11 Listing live",IF(Y70<>"","10 Profile complete",IF(X70<>"","9 Approved",IF(W70<>"","8 KYC submitted",IF(V70<>"","7 Registered",IF(T70<>"","5 Interested",IF(R70<>"","4 Responded",IF(O70<>"","2 Contacted","1 Not yet contacted"))))))))))))) | AK70: =IF(AF70<>"",AF70,IF(OR(O70="",R70<>"",LEFT(AJ70,1)="X"),"",IF(Q70<>"","",IF(P70<>"",P70+SETTINGS!$B$4,O70+SETTINGS!$B$3)))) | AL70: =IF(AJ70="","",IF(LEFT(AJ70,1)="X","None — do not contact",IF(AJ70="1 Not yet contacted","Verify route today, then send M1",IF(AND(R70="",Q70<>""),"Sequence complete — no contact before "&TEXT(Q70+SETTINGS!$B$5,"yyyy-mm-dd"),IF(AND(R70="",P70<>""),"Send final note (M4)",IF(R70="","Send follow-up (M2)",IF(AJ70="12 ACTIVATED","7-day check-in; consent & referral soft ask",IF(AJ70="13 Transacting","Repeat-activity support","Onboarding: move to next stage (see playbook §6)")))))))) | AM70: =IF(ISNUMBER(AK70),IF(AK70<=TODAY(),"DUE",""),"") | AN70: =IF(COUNT(O70,P70,Q70,R70,T70,V70,W70,X70,Y70,Z70,AA70,AC70)=0,"",TODAY()-MAX(O70,P70,Q70,R70,T70,V70,W70,X70,Y70,Z70,AA70,AC70)) | AO70: =IF(AJ70="","",IF(AND(T70<>"",U70<>"Active (verified)"),"GST: escalate (no tax advice)",IF(AND(IFERROR(VALUE(LEFT(AJ70,2)),0)>=5,AH70<>"YES",ISNUMBER(AN70),AN70>SETTINGS!$B$14),"STUCK in onboarding","")))
A71: 70 | B71: UPK2-DV-037 | C71: CRAFX Studio | D71: Digital & Visual Arts | E71: DV-DESIGN-STUDIO | F71: Mumbai | G71: B | H71: P0 | J71: Personal 1:1 email from founder/team to published business email | K71: https://www.crafxstudio.com/ | L71: W1 Founding cohort | AH71: =IF(AND(B71="",C71=""),"",IF(AND(X71<>"",Y71<>"",Z71<>"",AA71<>"",AB71="Y"),"YES","no")) | AI71: =IF(AH71="YES",MAX(X71,Y71,Z71,AA71),"") | AJ71: =IF(AND(B71="",C71=""),"",IF(OR(S71="Not interested",S71="Opt-out / do not contact"),"X Declined / suppressed",IF(S71="Bounced / undeliverable","X Bounced — research",IF(AC71<>"","13 Transacting",IF(AH71="YES","12 ACTIVATED",IF(Z71<>"","11 Listing live",IF(Y71<>"","10 Profile complete",IF(X71<>"","9 Approved",IF(W71<>"","8 KYC submitted",IF(V71<>"","7 Registered",IF(T71<>"","5 Interested",IF(R71<>"","4 Responded",IF(O71<>"","2 Contacted","1 Not yet contacted"))))))))))))) | AK71: =IF(AF71<>"",AF71,IF(OR(O71="",R71<>"",LEFT(AJ71,1)="X"),"",IF(Q71<>"","",IF(P71<>"",P71+SETTINGS!$B$4,O71+SETTINGS!$B$3)))) | AL71: =IF(AJ71="","",IF(LEFT(AJ71,1)="X","None — do not contact",IF(AJ71="1 Not yet contacted","Verify route today, then send M1",IF(AND(R71="",Q71<>""),"Sequence complete — no contact before "&TEXT(Q71+SETTINGS!$B$5,"yyyy-mm-dd"),IF(AND(R71="",P71<>""),"Send final note (M4)",IF(R71="","Send follow-up (M2)",IF(AJ71="12 ACTIVATED","7-day check-in; consent & referral soft ask",IF(AJ71="13 Transacting","Repeat-activity support","Onboarding: move to next stage (see playbook §6)")))))))) | AM71: =IF(ISNUMBER(AK71),IF(AK71<=TODAY(),"DUE",""),"") | AN71: =IF(COUNT(O71,P71,Q71,R71,T71,V71,W71,X71,Y71,Z71,AA71,AC71)=0,"",TODAY()-MAX(O71,P71,Q71,R71,T71,V71,W71,X71,Y71,Z71,AA71,AC71)) | AO71: =IF(AJ71="","",IF(AND(T71<>"",U71<>"Active (verified)"),"GST: escalate (no tax advice)",IF(AND(IFERROR(VALUE(LEFT(AJ71,2)),0)>=5,AH71<>"YES",ISNUMBER(AN71),AN71>SETTINGS!$B$14),"STUCK in onboarding","")))
A72: 71 | B72: UPK2-DV-033 | C72: Beyondesign | D72: Digital & Visual Arts | E72: DV-DESIGN-STUDIO | F72: Mumbai | G72: B | H72: P0 | J72: Personal 1:1 email from founder/team to published business email | K72: https://beyondesign.in/ | L72: W1 Founding cohort | AH72: =IF(AND(B72="",C72=""),"",IF(AND(X72<>"",Y72<>"",Z72<>"",AA72<>"",AB72="Y"),"YES","no")) | AI72: =IF(AH72="YES",MAX(X72,Y72,Z72,AA72),"") | AJ72: =IF(AND(B72="",C72=""),"",IF(OR(S72="Not interested",S72="Opt-out / do not contact"),"X Declined / suppressed",IF(S72="Bounced / undeliverable","X Bounced — research",IF(AC72<>"","13 Transacting",IF(AH72="YES","12 ACTIVATED",IF(Z72<>"","11 Listing live",IF(Y72<>"","10 Profile complete",IF(X72<>"","9 Approved",IF(W72<>"","8 KYC submitted",IF(V72<>"","7 Registered",IF(T72<>"","5 Interested",IF(R72<>"","4 Responded",IF(O72<>"","2 Contacted","1 Not yet contacted"))))))))))))) | AK72: =IF(AF72<>"",AF72,IF(OR(O72="",R72<>"",LEFT(AJ72,1)="X"),"",IF(Q72<>"","",IF(P72<>"",P72+SETTINGS!$B$4,O72+SETTINGS!$B$3)))) | AL72: =IF(AJ72="","",IF(LEFT(AJ72,1)="X","None — do not contact",IF(AJ72="1 Not yet contacted","Verify route today, then send M1",IF(AND(R72="",Q72<>""),"Sequence complete — no contact before "&TEXT(Q72+SETTINGS!$B$5,"yyyy-mm-dd"),IF(AND(R72="",P72<>""),"Send final note (M4)",IF(R72="","Send follow-up (M2)",IF(AJ72="12 ACTIVATED","7-day check-in; consent & referral soft ask",IF(AJ72="13 Transacting","Repeat-activity support","Onboarding: move to next stage (see playbook §6)")))))))) | AM72: =IF(ISNUMBER(AK72),IF(AK72<=TODAY(),"DUE",""),"") | AN72: =IF(COUNT(O72,P72,Q72,R72,T72,V72,W72,X72,Y72,Z72,AA72,AC72)=0,"",TODAY()-MAX(O72,P72,Q72,R72,T72,V72,W72,X72,Y72,Z72,AA72,AC72)) | AO72: =IF(AJ72="","",IF(AND(T72<>"",U72<>"Active (verified)"),"GST: escalate (no tax advice)",IF(AND(IFERROR(VALUE(LEFT(AJ72,2)),0)>=5,AH72<>"YES",ISNUMBER(AN72),AN72>SETTINGS!$B$14),"STUCK in onboarding","")))
A73: 72 | B73: UPK2-DV-009 | C73: Studio Berõ Jaipur | D73: Digital & Visual Arts | E73: DV-ARTIST-ILLUSTRATOR | F73: Jaipur | G73: A | H73: P0 | I73: under-discovered | J73: Personal 1:1 email from founder/team to published business email | K73: https://studioberojaipur.com/pages/contact-us | L73: W1 Founding cohort | AH73: =IF(AND(B73="",C73=""),"",IF(AND(X73<>"",Y73<>"",Z73<>"",AA73<>"",AB73="Y"),"YES","no")) | AI73: =IF(AH73="YES",MAX(X73,Y73,Z73,AA73),"") | AJ73: =IF(AND(B73="",C73=""),"",IF(OR(S73="Not interested",S73="Opt-out / do not contact"),"X Declined / suppressed",IF(S73="Bounced / undeliverable","X Bounced — research",IF(AC73<>"","13 Transacting",IF(AH73="YES","12 ACTIVATED",IF(Z73<>"","11 Listing live",IF(Y73<>"","10 Profile complete",IF(X73<>"","9 Approved",IF(W73<>"","8 KYC submitted",IF(V73<>"","7 Registered",IF(T73<>"","5 Interested",IF(R73<>"","4 Responded",IF(O73<>"","2 Contacted","1 Not yet contacted"))))))))))))) | AK73: =IF(AF73<>"",AF73,IF(OR(O73="",R73<>"",LEFT(AJ73,1)="X"),"",IF(Q73<>"","",IF(P73<>"",P73+SETTINGS!$B$4,O73+SETTINGS!$B$3)))) | AL73: =IF(AJ73="","",IF(LEFT(AJ73,1)="X","None — do not contact",IF(AJ73="1 Not yet contacted","Verify route today, then send M1",IF(AND(R73="",Q73<>""),"Sequence complete — no contact before "&TEXT(Q73+SETTINGS!$B$5,"yyyy-mm-dd"),IF(AND(R73="",P73<>""),"Send final note (M4)",IF(R73="","Send follow-up (M2)",IF(AJ73="12 ACTIVATED","7-day check-in; consent & referral soft ask",IF(AJ73="13 Transacting","Repeat-activity support","Onboarding: move to next stage (see playbook §6)")))))))) | AM73: =IF(ISNUMBER(AK73),IF(AK73<=TODAY(),"DUE",""),"") | AN73: =IF(COUNT(O73,P73,Q73,R73,T73,V73,W73,X73,Y73,Z73,AA73,AC73)=0,"",TODAY()-MAX(O73,P73,Q73,R73,T73,V73,W73,X73,Y73,Z73,AA73,AC73)) | AO73: =IF(AJ73="","",IF(AND(T73<>"",U73<>"Active (verified)"),"GST: escalate (no tax advice)",IF(AND(IFERROR(VALUE(LEFT(AJ73,2)),0)>=5,AH73<>"YES",ISNUMBER(AN73),AN73>SETTINGS!$B$14),"STUCK in onboarding","")))
A74: 73 | B74: UPK2-BM-189 | C74: Mehandi Wale Jaipur | D74: Beauty & Makeup | E74: BM-MEHENDI | F74: Jaipur | G74: A | H74: P0 | J74: Personal 1:1 email from founder/team to published business email | K74: https://www.mehandiwalejaipur.com/ | L74: W1 Founding cohort | AH74: =IF(AND(B74="",C74=""),"",IF(AND(X74<>"",Y74<>"",Z74<>"",AA74<>"",AB74="Y"),"YES","no")) | AI74: =IF(AH74="YES",MAX(X74,Y74,Z74,AA74),"") | AJ74: =IF(AND(B74="",C74=""),"",IF(OR(S74="Not interested",S74="Opt-out / do not contact"),"X Declined / suppressed",IF(S74="Bounced / undeliverable","X Bounced — research",IF(AC74<>"","13 Transacting",IF(AH74="YES","12 ACTIVATED",IF(Z74<>"","11 Listing live",IF(Y74<>"","10 Profile complete",IF(X74<>"","9 Approved",IF(W74<>"","8 KYC submitted",IF(V74<>"","7 Registered",IF(T74<>"","5 Interested",IF(R74<>"","4 Responded",IF(O74<>"","2 Contacted","1 Not yet contacted"))))))))))))) | AK74: =IF(AF74<>"",AF74,IF(OR(O74="",R74<>"",LEFT(AJ74,1)="X"),"",IF(Q74<>"","",IF(P74<>"",P74+SETTINGS!$B$4,O74+SETTINGS!$B$3)))) | AL74: =IF(AJ74="","",IF(LEFT(AJ74,1)="X","None — do not contact",IF(AJ74="1 Not yet contacted","Verify route today, then send M1",IF(AND(R74="",Q74<>""),"Sequence complete — no contact before "&TEXT(Q74+SETTINGS!$B$5,"yyyy-mm-dd"),IF(AND(R74="",P74<>""),"Send final note (M4)",IF(R74="","Send follow-up (M2)",IF(AJ74="12 ACTIVATED","7-day check-in; consent & referral soft ask",IF(AJ74="13 Transacting","Repeat-activity support","Onboarding: move to next stage (see playbook §6)")))))))) | AM74: =IF(ISNUMBER(AK74),IF(AK74<=TODAY(),"DUE",""),"") | AN74: =IF(COUNT(O74,P74,Q74,R74,T74,V74,W74,X74,Y74,Z74,AA74,AC74)=0,"",TODAY()-MAX(O74,P74,Q74,R74,T74,V74,W74,X74,Y74,Z74,AA74,AC74)) | AO74: =IF(AJ74="","",IF(AND(T74<>"",U74<>"Active (verified)"),"GST: escalate (no tax advice)",IF(AND(IFERROR(VALUE(LEFT(AJ74,2)),0)>=5,AH74<>"YES",ISNUMBER(AN74),AN74>SETTINGS!$B$14),"STUCK in onboarding","")))
A75: 74 | B75: UPK2-BM-278 | C75: Jaipur Mehandi Artist | D75: Beauty & Makeup | E75: BM-MEHENDI | F75: Jaipur | G75: A | H75: P0 | J75: Personal 1:1 email from founder/team to published business email | K75: https://www.jaipurmehandiartist.com/ | L75: W1 Founding cohort | AH75: =IF(AND(B75="",C75=""),"",IF(AND(X75<>"",Y75<>"",Z75<>"",AA75<>"",AB75="Y"),"YES","no")) | AI75: =IF(AH75="YES",MAX(X75,Y75,Z75,AA75),"") | AJ75: =IF(AND(B75="",C75=""),"",IF(OR(S75="Not interested",S75="Opt-out / do not contact"),"X Declined / suppressed",IF(S75="Bounced / undeliverable","X Bounced — research",IF(AC75<>"","13 Transacting",IF(AH75="YES","12 ACTIVATED",IF(Z75<>"","11 Listing live",IF(Y75<>"","10 Profile complete",IF(X75<>"","9 Approved",IF(W75<>"","8 KYC submitted",IF(V75<>"","7 Registered",IF(T75<>"","5 Interested",IF(R75<>"","4 Responded",IF(O75<>"","2 Contacted","1 Not yet contacted"))))))))))))) | AK75: =IF(AF75<>"",AF75,IF(OR(O75="",R75<>"",LEFT(AJ75,1)="X"),"",IF(Q75<>"","",IF(P75<>"",P75+SETTINGS!$B$4,O75+SETTINGS!$B$3)))) | AL75: =IF(AJ75="","",IF(LEFT(AJ75,1)="X","None — do not contact",IF(AJ75="1 Not yet contacted","Verify route today, then send M1",IF(AND(R75="",Q75<>""),"Sequence complete — no contact before "&TEXT(Q75+SETTINGS!$B$5,"yyyy-mm-dd"),IF(AND(R75="",P75<>""),"Send final note (M4)",IF(R75="","Send follow-up (M2)",IF(AJ75="12 ACTIVATED","7-day check-in; consent & referral soft ask",IF(AJ75="13 Transacting","Repeat-activity support","Onboarding: move to next stage (see playbook §6)")))))))) | AM75: =IF(ISNUMBER(AK75),IF(AK75<=TODAY(),"DUE",""),"") | AN75: =IF(COUNT(O75,P75,Q75,R75,T75,V75,W75,X75,Y75,Z75,AA75,AC75)=0,"",TODAY()-MAX(O75,P75,Q75,R75,T75,V75,W75,X75,Y75,Z75,AA75,AC75)) | AO75: =IF(AJ75="","",IF(AND(T75<>"",U75<>"Active (verified)"),"GST: escalate (no tax advice)",IF(AND(IFERROR(VALUE(LEFT(AJ75,2)),0)>=5,AH75<>"YES",ISNUMBER(AN75),AN75>SETTINGS!$B$14),"STUCK in onboarding","")))
A76: 75 | B76: UPK2-BM-049 | C76: Saloni Makeup Artist | D76: Beauty & Makeup | E76: BM-INDEPENDENT-MUA | F76: Jaipur | G76: A | H76: P0 | I76: under-discovered | J76: Personal 1:1 email from founder/team to published business email | K76: https://salonimakeupartist.com/ | L76: W1 Founding cohort | AH76: =IF(AND(B76="",C76=""),"",IF(AND(X76<>"",Y76<>"",Z76<>"",AA76<>"",AB76="Y"),"YES","no")) | AI76: =IF(AH76="YES",MAX(X76,Y76,Z76,AA76),"") | AJ76: =IF(AND(B76="",C76=""),"",IF(OR(S76="Not interested",S76="Opt-out / do not contact"),"X Declined / suppressed",IF(S76="Bounced / undeliverable","X Bounced — research",IF(AC76<>"","13 Transacting",IF(AH76="YES","12 ACTIVATED",IF(Z76<>"","11 Listing live",IF(Y76<>"","10 Profile complete",IF(X76<>"","9 Approved",IF(W76<>"","8 KYC submitted",IF(V76<>"","7 Registered",IF(T76<>"","5 Interested",IF(R76<>"","4 Responded",IF(O76<>"","2 Contacted","1 Not yet contacted"))))))))))))) | AK76: =IF(AF76<>"",AF76,IF(OR(O76="",R76<>"",LEFT(AJ76,1)="X"),"",IF(Q76<>"","",IF(P76<>"",P76+SETTINGS!$B$4,O76+SETTINGS!$B$3)))) | AL76: =IF(AJ76="","",IF(LEFT(AJ76,1)="X","None — do not contact",IF(AJ76="1 Not yet contacted","Verify route today, then send M1",IF(AND(R76="",Q76<>""),"Sequence complete — no contact before "&TEXT(Q76+SETTINGS!$B$5,"yyyy-mm-dd"),IF(AND(R76="",P76<>""),"Send final note (M4)",IF(R76="","Send follow-up (M2)",IF(AJ76="12 ACTIVATED","7-day check-in; consent & referral soft ask",IF(AJ76="13 Transacting","Repeat-activity support","Onboarding: move to next stage (see playbook §6)")))))))) | AM76: =IF(ISNUMBER(AK76),IF(AK76<=TODAY(),"DUE",""),"") | AN76: =IF(COUNT(O76,P76,Q76,R76,T76,V76,W76,X76,Y76,Z76,AA76,AC76)=0,"",TODAY()-MAX(O76,P76,Q76,R76,T76,V76,W76,X76,Y76,Z76,AA76,AC76)) | AO76: =IF(AJ76="","",IF(AND(T76<>"",U76<>"Active (verified)"),"GST: escalate (no tax advice)",IF(AND(IFERROR(VALUE(LEFT(AJ76,2)),0)>=5,AH76<>"YES",ISNUMBER(AN76),AN76>SETTINGS!$B$14),"STUCK in onboarding","")))
A77: 76 | B77: UPK2-BM-166 | C77: Pinkbyneena | D77: Beauty & Makeup | E77: BM-INDEPENDENT-MUA | F77: Bengaluru | G77: B | H77: P0 | J77: Personal 1:1 email from founder/team to published business email | K77: https://www.pinkbyneena.com/ | L77: W1 Founding cohort | AH77: =IF(AND(B77="",C77=""),"",IF(AND(X77<>"",Y77<>"",Z77<>"",AA77<>"",AB77="Y"),"YES","no")) | AI77: =IF(AH77="YES",MAX(X77,Y77,Z77,AA77),"") | AJ77: =IF(AND(B77="",C77=""),"",IF(OR(S77="Not interested",S77="Opt-out / do not contact"),"X Declined / suppressed",IF(S77="Bounced / undeliverable","X Bounced — research",IF(AC77<>"","13 Transacting",IF(AH77="YES","12 ACTIVATED",IF(Z77<>"","11 Listing live",IF(Y77<>"","10 Profile complete",IF(X77<>"","9 Approved",IF(W77<>"","8 KYC submitted",IF(V77<>"","7 Registered",IF(T77<>"","5 Interested",IF(R77<>"","4 Responded",IF(O77<>"","2 Contacted","1 Not yet contacted"))))))))))))) | AK77: =IF(AF77<>"",AF77,IF(OR(O77="",R77<>"",LEFT(AJ77,1)="X"),"",IF(Q77<>"","",IF(P77<>"",P77+SETTINGS!$B$4,O77+SETTINGS!$B$3)))) | AL77: =IF(AJ77="","",IF(LEFT(AJ77,1)="X","None — do not contact",IF(AJ77="1 Not yet contacted","Verify route today, then send M1",IF(AND(R77="",Q77<>""),"Sequence complete — no contact before "&TEXT(Q77+SETTINGS!$B$5,"yyyy-mm-dd"),IF(AND(R77="",P77<>""),"Send final note (M4)",IF(R77="","Send follow-up (M2)",IF(AJ77="12 ACTIVATED","7-day check-in; consent & referral soft ask",IF(AJ77="13 Transacting","Repeat-activity support","Onboarding: move to next stage (see playbook §6)")))))))) | AM77: =IF(ISNUMBER(AK77),IF(AK77<=TODAY(),"DUE",""),"") | AN77: =IF(COUNT(O77,P77,Q77,R77,T77,V77,W77,X77,Y77,Z77,AA77,AC77)=0,"",TODAY()-MAX(O77,P77,Q77,R77,T77,V77,W77,X77,Y77,Z77,AA77,AC77)) | AO77: =IF(AJ77="","",IF(AND(T77<>"",U77<>"Active (verified)"),"GST: escalate (no tax advice)",IF(AND(IFERROR(VALUE(LEFT(AJ77,2)),0)>=5,AH77<>"YES",ISNUMBER(AN77),AN77>SETTINGS!$B$14),"STUCK in onboarding","")))
A78: 77 | B78: UPK2-BM-230 | C78: Abhishek Mehandi Art | D78: Beauty & Makeup | E78: BM-MEHENDI | F78: Delhi NCR | G78: B | H78: P1 | J78: Personal 1:1 email from founder/team to published business email | K78: https://abhishekmehandiart.com/ | L78: W1 Founding cohort | AH78: =IF(AND(B78="",C78=""),"",IF(AND(X78<>"",Y78<>"",Z78<>"",AA78<>"",AB78="Y"),"YES","no")) | AI78: =IF(AH78="YES",MAX(X78,Y78,Z78,AA78),"") | AJ78: =IF(AND(B78="",C78=""),"",IF(OR(S78="Not interested",S78="Opt-out / do not contact"),"X Declined / suppressed",IF(S78="Bounced / undeliverable","X Bounced — research",IF(AC78<>"","13 Transacting",IF(AH78="YES","12 ACTIVATED",IF(Z78<>"","11 Listing live",IF(Y78<>"","10 Profile complete",IF(X78<>"","9 Approved",IF(W78<>"","8 KYC submitted",IF(V78<>"","7 Registered",IF(T78<>"","5 Interested",IF(R78<>"","4 Responded",IF(O78<>"","2 Contacted","1 Not yet contacted"))))))))))))) | AK78: =IF(AF78<>"",AF78,IF(OR(O78="",R78<>"",LEFT(AJ78,1)="X"),"",IF(Q78<>"","",IF(P78<>"",P78+SETTINGS!$B$4,O78+SETTINGS!$B$3)))) | AL78: =IF(AJ78="","",IF(LEFT(AJ78,1)="X","None — do not contact",IF(AJ78="1 Not yet contacted","Verify route today, then send M1",IF(AND(R78="",Q78<>""),"Sequence complete — no contact before "&TEXT(Q78+SETTINGS!$B$5,"yyyy-mm-dd"),IF(AND(R78="",P78<>""),"Send final note (M4)",IF(R78="","Send follow-up (M2)",IF(AJ78="12 ACTIVATED","7-day check-in; consent & referral soft ask",IF(AJ78="13 Transacting","Repeat-activity support","Onboarding: move to next stage (see playbook §6)")))))))) | AM78: =IF(ISNUMBER(AK78),IF(AK78<=TODAY(),"DUE",""),"") | AN78: =IF(COUNT(O78,P78,Q78,R78,T78,V78,W78,X78,Y78,Z78,AA78,AC78)=0,"",TODAY()-MAX(O78,P78,Q78,R78,T78,V78,W78,X78,Y78,Z78,AA78,AC78)) | AO78: =IF(AJ78="","",IF(AND(T78<>"",U78<>"Active (verified)"),"GST: escalate (no tax advice)",IF(AND(IFERROR(VALUE(LEFT(AJ78,2)),0)>=5,AH78<>"YES",ISNUMBER(AN78),AN78>SETTINGS!$B$14),"STUCK in onboarding","")))
A79: 78 | B79: UPK2-BM-253 | C79: Meera Bhandari Makeovers | D79: Beauty & Makeup | E79: BM-INDEPENDENT-MUA | F79: Jaipur | G79: B | H79: P0 | J79: 1:1 message via own-website contact form | K79: https://meerabhandarimakeovers.com/ | L79: W1 Founding cohort | AH79: =IF(AND(B79="",C79=""),"",IF(AND(X79<>"",Y79<>"",Z79<>"",AA79<>"",AB79="Y"),"YES","no")) | AI79: =IF(AH79="YES",MAX(X79,Y79,Z79,AA79),"") | AJ79: =IF(AND(B79="",C79=""),"",IF(OR(S79="Not interested",S79="Opt-out / do not contact"),"X Declined / suppressed",IF(S79="Bounced / undeliverable","X Bounced — research",IF(AC79<>"","13 Transacting",IF(AH79="YES","12 ACTIVATED",IF(Z79<>"","11 Listing live",IF(Y79<>"","10 Profile complete",IF(X79<>"","9 Approved",IF(W79<>"","8 KYC submitted",IF(V79<>"","7 Registered",IF(T79<>"","5 Interested",IF(R79<>"","4 Responded",IF(O79<>"","2 Contacted","1 Not yet contacted"))))))))))))) | AK79: =IF(AF79<>"",AF79,IF(OR(O79="",R79<>"",LEFT(AJ79,1)="X"),"",IF(Q79<>"","",IF(P79<>"",P79+SETTINGS!$B$4,O79+SETTINGS!$B$3)))) | AL79: =IF(AJ79="","",IF(LEFT(AJ79,1)="X","None — do not contact",IF(AJ79="1 Not yet contacted","Verify route today, then send M1",IF(AND(R79="",Q79<>""),"Sequence complete — no contact before "&TEXT(Q79+SETTINGS!$B$5,"yyyy-mm-dd"),IF(AND(R79="",P79<>""),"Send final note (M4)",IF(R79="","Send follow-up (M2)",IF(AJ79="12 ACTIVATED","7-day check-in; consent & referral soft ask",IF(AJ79="13 Transacting","Repeat-activity support","Onboarding: move to next stage (see playbook §6)")))))))) | AM79: =IF(ISNUMBER(AK79),IF(AK79<=TODAY(),"DUE",""),"") | AN79: =IF(COUNT(O79,P79,Q79,R79,T79,V79,W79,X79,Y79,Z79,AA79,AC79)=0,"",TODAY()-MAX(O79,P79,Q79,R79,T79,V79,W79,X79,Y79,Z79,AA79,AC79)) | AO79: =IF(AJ79="","",IF(AND(T79<>"",U79<>"Active (verified)"),"GST: escalate (no tax advice)",IF(AND(IFERROR(VALUE(LEFT(AJ79,2)),0)>=5,AH79<>"YES",ISNUMBER(AN79),AN79>SETTINGS!$B$14),"STUCK in onboarding","")))
A80: 79 | B80: UPK2-BM-188 | C80: Seema Sarraf Makeup Artist | D80: Beauty & Makeup | E80: BM-INDEPENDENT-MUA | F80: Jaipur | G80: B | H80: P0 | J80: Personal 1:1 email from founder/team to published business email | K80: https://seemasarraf.com/ | L80: W1 Founding cohort | AH80: =IF(AND(B80="",C80=""),"",IF(AND(X80<>"",Y80<>"",Z80<>"",AA80<>"",AB80="Y"),"YES","no")) | AI80: =IF(AH80="YES",MAX(X80,Y80,Z80,AA80),"") | AJ80: =IF(AND(B80="",C80=""),"",IF(OR(S80="Not interested",S80="Opt-out / do not contact"),"X Declined / suppressed",IF(S80="Bounced / undeliverable","X Bounced — research",IF(AC80<>"","13 Transacting",IF(AH80="YES","12 ACTIVATED",IF(Z80<>"","11 Listing live",IF(Y80<>"","10 Profile complete",IF(X80<>"","9 Approved",IF(W80<>"","8 KYC submitted",IF(V80<>"","7 Registered",IF(T80<>"","5 Interested",IF(R80<>"","4 Responded",IF(O80<>"","2 Contacted","1 Not yet contacted"))))))))))))) | AK80: =IF(AF80<>"",AF80,IF(OR(O80="",R80<>"",LEFT(AJ80,1)="X"),"",IF(Q80<>"","",IF(P80<>"",P80+SETTINGS!$B$4,O80+SETTINGS!$B$3)))) | AL80: =IF(AJ80="","",IF(LEFT(AJ80,1)="X","None — do not contact",IF(AJ80="1 Not yet contacted","Verify route today, then send M1",IF(AND(R80="",Q80<>""),"Sequence complete — no contact before "&TEXT(Q80+SETTINGS!$B$5,"yyyy-mm-dd"),IF(AND(R80="",P80<>""),"Send final note (M4)",IF(R80="","Send follow-up (M2)",IF(AJ80="12 ACTIVATED","7-day check-in; consent & referral soft ask",IF(AJ80="13 Transacting","Repeat-activity support","Onboarding: move to next stage (see playbook §6)")))))))) | AM80: =IF(ISNUMBER(AK80),IF(AK80<=TODAY(),"DUE",""),"") | AN80: =IF(COUNT(O80,P80,Q80,R80,T80,V80,W80,X80,Y80,Z80,AA80,AC80)=0,"",TODAY()-MAX(O80,P80,Q80,R80,T80,V80,W80,X80,Y80,Z80,AA80,AC80)) | AO80: =IF(AJ80="","",IF(AND(T80<>"",U80<>"Active (verified)"),"GST: escalate (no tax advice)",IF(AND(IFERROR(VALUE(LEFT(AJ80,2)),0)>=5,AH80<>"YES",ISNUMBER(AN80),AN80>SETTINGS!$B$14),"STUCK in onboarding","")))
A81: 80 | B81: UPK2-BM-171 | C81: V2 Makeover | D81: Beauty & Makeup | E81: BM-INDEPENDENT-MUA | F81: Bengaluru | G81: B | H81: P0 | J81: Personal 1:1 email from founder/team to published business email | K81: https://v2makeover.com/ | L81: W1 Founding cohort | AH81: =IF(AND(B81="",C81=""),"",IF(AND(X81<>"",Y81<>"",Z81<>"",AA81<>"",AB81="Y"),"YES","no")) | AI81: =IF(AH81="YES",MAX(X81,Y81,Z81,AA81),"") | AJ81: =IF(AND(B81="",C81=""),"",IF(OR(S81="Not interested",S81="Opt-out / do not contact"),"X Declined / suppressed",IF(S81="Bounced / undeliverable","X Bounced — research",IF(AC81<>"","13 Transacting",IF(AH81="YES","12 ACTIVATED",IF(Z81<>"","11 Listing live",IF(Y81<>"","10 Profile complete",IF(X81<>"","9 Approved",IF(W81<>"","8 KYC submitted",IF(V81<>"","7 Registered",IF(T81<>"","5 Interested",IF(R81<>"","4 Responded",IF(O81<>"","2 Contacted","1 Not yet contacted"))))))))))))) | AK81: =IF(AF81<>"",AF81,IF(OR(O81="",R81<>"",LEFT(AJ81,1)="X"),"",IF(Q81<>"","",IF(P81<>"",P81+SETTINGS!$B$4,O81+SETTINGS!$B$3)))) | AL81: =IF(AJ81="","",IF(LEFT(AJ81,1)="X","None — do not contact",IF(AJ81="1 Not yet contacted","Verify route today, then send M1",IF(AND(R81="",Q81<>""),"Sequence complete — no contact before "&TEXT(Q81+SETTINGS!$B$5,"yyyy-mm-dd"),IF(AND(R81="",P81<>""),"Send final note (M4)",IF(R81="","Send follow-up (M2)",IF(AJ81="12 ACTIVATED","7-day check-in; consent & referral soft ask",IF(AJ81="13 Transacting","Repeat-activity support","Onboarding: move to next stage (see playbook §6)")))))))) | AM81: =IF(ISNUMBER(AK81),IF(AK81<=TODAY(),"DUE",""),"") | AN81: =IF(COUNT(O81,P81,Q81,R81,T81,V81,W81,X81,Y81,Z81,AA81,AC81)=0,"",TODAY()-MAX(O81,P81,Q81,R81,T81,V81,W81,X81,Y81,Z81,AA81,AC81)) | AO81: =IF(AJ81="","",IF(AND(T81<>"",U81<>"Active (verified)"),"GST: escalate (no tax advice)",IF(AND(IFERROR(VALUE(LEFT(AJ81,2)),0)>=5,AH81<>"YES",ISNUMBER(AN81),AN81>SETTINGS!$B$14),"STUCK in onboarding","")))
A82: 81 | B82: UPK2-BM-190 | C82: Mridula Joshi Makeovers | D82: Beauty & Makeup | E82: BM-INDEPENDENT-MUA | F82: Delhi NCR | G82: B | H82: P1 | J82: Personal 1:1 email from founder/team to published business email | K82: https://mridulajoshi.in/ | L82: W1 Founding cohort | AH82: =IF(AND(B82="",C82=""),"",IF(AND(X82<>"",Y82<>"",Z82<>"",AA82<>"",AB82="Y"),"YES","no")) | AI82: =IF(AH82="YES",MAX(X82,Y82,Z82,AA82),"") | AJ82: =IF(AND(B82="",C82=""),"",IF(OR(S82="Not interested",S82="Opt-out / do not contact"),"X Declined / suppressed",IF(S82="Bounced / undeliverable","X Bounced — research",IF(AC82<>"","13 Transacting",IF(AH82="YES","12 ACTIVATED",IF(Z82<>"","11 Listing live",IF(Y82<>"","10 Profile complete",IF(X82<>"","9 Approved",IF(W82<>"","8 KYC submitted",IF(V82<>"","7 Registered",IF(T82<>"","5 Interested",IF(R82<>"","4 Responded",IF(O82<>"","2 Contacted","1 Not yet contacted"))))))))))))) | AK82: =IF(AF82<>"",AF82,IF(OR(O82="",R82<>"",LEFT(AJ82,1)="X"),"",IF(Q82<>"","",IF(P82<>"",P82+SETTINGS!$B$4,O82+SETTINGS!$B$3)))) | AL82: =IF(AJ82="","",IF(LEFT(AJ82,1)="X","None — do not contact",IF(AJ82="1 Not yet contacted","Verify route today, then send M1",IF(AND(R82="",Q82<>""),"Sequence complete — no contact before "&TEXT(Q82+SETTINGS!$B$5,"yyyy-mm-dd"),IF(AND(R82="",P82<>""),"Send final note (M4)",IF(R82="","Send follow-up (M2)",IF(AJ82="12 ACTIVATED","7-day check-in; consent & referral soft ask",IF(AJ82="13 Transacting","Repeat-activity support","Onboarding: move to next stage (see playbook §6)")))))))) | AM82: =IF(ISNUMBER(AK82),IF(AK82<=TODAY(),"DUE",""),"") | AN82: =IF(COUNT(O82,P82,Q82,R82,T82,V82,W82,X82,Y82,Z82,AA82,AC82)=0,"",TODAY()-MAX(O82,P82,Q82,R82,T82,V82,W82,X82,Y82,Z82,AA82,AC82)) | AO82: =IF(AJ82="","",IF(AND(T82<>"",U82<>"Active (verified)"),"GST: escalate (no tax advice)",IF(AND(IFERROR(VALUE(LEFT(AJ82,2)),0)>=5,AH82<>"YES",ISNUMBER(AN82),AN82>SETTINGS!$B$14),"STUCK in onboarding","")))
A83: 82 | B83: UPK2-BM-001 | C83: Wedding Guests Beauty Bar (WGBB) | D83: Beauty & Makeup | E83: BM-STUDIO | F83: Delhi NCR | G83: C | H83: P1 | J83: Personal 1:1 email from founder/team to published business email | K83: https://www.weddingguestsbeautybar.com | L83: W1 Founding cohort | AH83: =IF(AND(B83="",C83=""),"",IF(AND(X83<>"",Y83<>"",Z83<>"",AA83<>"",AB83="Y"),"YES","no")) | AI83: =IF(AH83="YES",MAX(X83,Y83,Z83,AA83),"") | AJ83: =IF(AND(B83="",C83=""),"",IF(OR(S83="Not interested",S83="Opt-out / do not contact"),"X Declined / suppressed",IF(S83="Bounced / undeliverable","X Bounced — research",IF(AC83<>"","13 Transacting",IF(AH83="YES","12 ACTIVATED",IF(Z83<>"","11 Listing live",IF(Y83<>"","10 Profile complete",IF(X83<>"","9 Approved",IF(W83<>"","8 KYC submitted",IF(V83<>"","7 Registered",IF(T83<>"","5 Interested",IF(R83<>"","4 Responded",IF(O83<>"","2 Contacted","1 Not yet contacted"))))))))))))) | AK83: =IF(AF83<>"",AF83,IF(OR(O83="",R83<>"",LEFT(AJ83,1)="X"),"",IF(Q83<>"","",IF(P83<>"",P83+SETTINGS!$B$4,O83+SETTINGS!$B$3)))) | AL83: =IF(AJ83="","",IF(LEFT(AJ83,1)="X","None — do not contact",IF(AJ83="1 Not yet contacted","Verify route today, then send M1",IF(AND(R83="",Q83<>""),"Sequence complete — no contact before "&TEXT(Q83+SETTINGS!$B$5,"yyyy-mm-dd"),IF(AND(R83="",P83<>""),"Send final note (M4)",IF(R83="","Send follow-up (M2)",IF(AJ83="12 ACTIVATED","7-day check-in; consent & referral soft ask",IF(AJ83="13 Transacting","Repeat-activity support","Onboarding: move to next stage (see playbook §6)")))))))) | AM83: =IF(ISNUMBER(AK83),IF(AK83<=TODAY(),"DUE",""),"") | AN83: =IF(COUNT(O83,P83,Q83,R83,T83,V83,W83,X83,Y83,Z83,AA83,AC83)=0,"",TODAY()-MAX(O83,P83,Q83,R83,T83,V83,W83,X83,Y83,Z83,AA83,AC83)) | AO83: =IF(AJ83="","",IF(AND(T83<>"",U83<>"Active (verified)"),"GST: escalate (no tax advice)",IF(AND(IFERROR(VALUE(LEFT(AJ83,2)),0)>=5,AH83<>"YES",ISNUMBER(AN83),AN83>SETTINGS!$B$14),"STUCK in onboarding","")))
A84: 83 | B84: UPK2-BM-240 | C84: Yogesh Mehandi Art | D84: Beauty & Makeup | E84: BM-MEHENDI | F84: Delhi NCR | G84: B | H84: P1 | J84: Personal 1:1 email from founder/team to published business email | K84: https://yogeshmehandiart.com/ | L84: W1 Founding cohort | AH84: =IF(AND(B84="",C84=""),"",IF(AND(X84<>"",Y84<>"",Z84<>"",AA84<>"",AB84="Y"),"YES","no")) | AI84: =IF(AH84="YES",MAX(X84,Y84,Z84,AA84),"") | AJ84: =IF(AND(B84="",C84=""),"",IF(OR(S84="Not interested",S84="Opt-out / do not contact"),"X Declined / suppressed",IF(S84="Bounced / undeliverable","X Bounced — research",IF(AC84<>"","13 Transacting",IF(AH84="YES","12 ACTIVATED",IF(Z84<>"","11 Listing live",IF(Y84<>"","10 Profile complete",IF(X84<>"","9 Approved",IF(W84<>"","8 KYC submitted",IF(V84<>"","7 Registered",IF(T84<>"","5 Interested",IF(R84<>"","4 Responded",IF(O84<>"","2 Contacted","1 Not yet contacted"))))))))))))) | AK84: =IF(AF84<>"",AF84,IF(OR(O84="",R84<>"",LEFT(AJ84,1)="X"),"",IF(Q84<>"","",IF(P84<>"",P84+SETTINGS!$B$4,O84+SETTINGS!$B$3)))) | AL84: =IF(AJ84="","",IF(LEFT(AJ84,1)="X","None — do not contact",IF(AJ84="1 Not yet contacted","Verify route today, then send M1",IF(AND(R84="",Q84<>""),"Sequence complete — no contact before "&TEXT(Q84+SETTINGS!$B$5,"yyyy-mm-dd"),IF(AND(R84="",P84<>""),"Send final note (M4)",IF(R84="","Send follow-up (M2)",IF(AJ84="12 ACTIVATED","7-day check-in; consent & referral soft ask",IF(AJ84="13 Transacting","Repeat-activity support","Onboarding: move to next stage (see playbook §6)")))))))) | AM84: =IF(ISNUMBER(AK84),IF(AK84<=TODAY(),"DUE",""),"") | AN84: =IF(COUNT(O84,P84,Q84,R84,T84,V84,W84,X84,Y84,Z84,AA84,AC84)=0,"",TODAY()-MAX(O84,P84,Q84,R84,T84,V84,W84,X84,Y84,Z84,AA84,AC84)) | AO84: =IF(AJ84="","",IF(AND(T84<>"",U84<>"Active (verified)"),"GST: escalate (no tax advice)",IF(AND(IFERROR(VALUE(LEFT(AJ84,2)),0)>=5,AH84<>"YES",ISNUMBER(AN84),AN84>SETTINGS!$B$14),"STUCK in onboarding","")))
A85: 84 | B85: UPK2-BM-252 | C85: Raj Mehandi Designer | D85: Beauty & Makeup | E85: BM-MEHENDI | F85: Delhi NCR | G85: B | H85: P0 | J85: Personal 1:1 email from founder/team to published business email | K85: https://www.rajmehandidesigner.com/ | L85: W1 Founding cohort | AH85: =IF(AND(B85="",C85=""),"",IF(AND(X85<>"",Y85<>"",Z85<>"",AA85<>"",AB85="Y"),"YES","no")) | AI85: =IF(AH85="YES",MAX(X85,Y85,Z85,AA85),"") | AJ85: =IF(AND(B85="",C85=""),"",IF(OR(S85="Not interested",S85="Opt-out / do not contact"),"X Declined / suppressed",IF(S85="Bounced / undeliverable","X Bounced — research",IF(AC85<>"","13 Transacting",IF(AH85="YES","12 ACTIVATED",IF(Z85<>"","11 Listing live",IF(Y85<>"","10 Profile complete",IF(X85<>"","9 Approved",IF(W85<>"","8 KYC submitted",IF(V85<>"","7 Registered",IF(T85<>"","5 Interested",IF(R85<>"","4 Responded",IF(O85<>"","2 Contacted","1 Not yet contacted"))))))))))))) | AK85: =IF(AF85<>"",AF85,IF(OR(O85="",R85<>"",LEFT(AJ85,1)="X"),"",IF(Q85<>"","",IF(P85<>"",P85+SETTINGS!$B$4,O85+SETTINGS!$B$3)))) | AL85: =IF(AJ85="","",IF(LEFT(AJ85,1)="X","None — do not contact",IF(AJ85="1 Not yet contacted","Verify route today, then send M1",IF(AND(R85="",Q85<>""),"Sequence complete — no contact before "&TEXT(Q85+SETTINGS!$B$5,"yyyy-mm-dd"),IF(AND(R85="",P85<>""),"Send final note (M4)",IF(R85="","Send follow-up (M2)",IF(AJ85="12 ACTIVATED","7-day check-in; consent & referral soft ask",IF(AJ85="13 Transacting","Repeat-activity support","Onboarding: move to next stage (see playbook §6)")))))))) | AM85: =IF(ISNUMBER(AK85),IF(AK85<=TODAY(),"DUE",""),"") | AN85: =IF(COUNT(O85,P85,Q85,R85,T85,V85,W85,X85,Y85,Z85,AA85,AC85)=0,"",TODAY()-MAX(O85,P85,Q85,R85,T85,V85,W85,X85,Y85,Z85,AA85,AC85)) | AO85: =IF(AJ85="","",IF(AND(T85<>"",U85<>"Active (verified)"),"GST: escalate (no tax advice)",IF(AND(IFERROR(VALUE(LEFT(AJ85,2)),0)>=5,AH85<>"YES",ISNUMBER(AN85),AN85>SETTINGS!$B$14),"STUCK in onboarding","")))
A86: 85 | B86: UPK2-LM-245 | C86: Infini Studios | D86: Lens & Motion | E86: LM-WEDDING | F86: Bengaluru | G86: A | H86: P0 | I86: under-discovered | J86: Personal 1:1 email from founder/team to published business email | K86: https://infinistudios.in/en/events | L86: W1 Founding cohort | AH86: =IF(AND(B86="",C86=""),"",IF(AND(X86<>"",Y86<>"",Z86<>"",AA86<>"",AB86="Y"),"YES","no")) | AI86: =IF(AH86="YES",MAX(X86,Y86,Z86,AA86),"") | AJ86: =IF(AND(B86="",C86=""),"",IF(OR(S86="Not interested",S86="Opt-out / do not contact"),"X Declined / suppressed",IF(S86="Bounced / undeliverable","X Bounced — research",IF(AC86<>"","13 Transacting",IF(AH86="YES","12 ACTIVATED",IF(Z86<>"","11 Listing live",IF(Y86<>"","10 Profile complete",IF(X86<>"","9 Approved",IF(W86<>"","8 KYC submitted",IF(V86<>"","7 Registered",IF(T86<>"","5 Interested",IF(R86<>"","4 Responded",IF(O86<>"","2 Contacted","1 Not yet contacted"))))))))))))) | AK86: =IF(AF86<>"",AF86,IF(OR(O86="",R86<>"",LEFT(AJ86,1)="X"),"",IF(Q86<>"","",IF(P86<>"",P86+SETTINGS!$B$4,O86+SETTINGS!$B$3)))) | AL86: =IF(AJ86="","",IF(LEFT(AJ86,1)="X","None — do not contact",IF(AJ86="1 Not yet contacted","Verify route today, then send M1",IF(AND(R86="",Q86<>""),"Sequence complete — no contact before "&TEXT(Q86+SETTINGS!$B$5,"yyyy-mm-dd"),IF(AND(R86="",P86<>""),"Send final note (M4)",IF(R86="","Send follow-up (M2)",IF(AJ86="12 ACTIVATED","7-day check-in; consent & referral soft ask",IF(AJ86="13 Transacting","Repeat-activity support","Onboarding: move to next stage (see playbook §6)")))))))) | AM86: =IF(ISNUMBER(AK86),IF(AK86<=TODAY(),"DUE",""),"") | AN86: =IF(COUNT(O86,P86,Q86,R86,T86,V86,W86,X86,Y86,Z86,AA86,AC86)=0,"",TODAY()-MAX(O86,P86,Q86,R86,T86,V86,W86,X86,Y86,Z86,AA86,AC86)) | AO86: =IF(AJ86="","",IF(AND(T86<>"",U86<>"Active (verified)"),"GST: escalate (no tax advice)",IF(AND(IFERROR(VALUE(LEFT(AJ86,2)),0)>=5,AH86<>"YES",ISNUMBER(AN86),AN86>SETTINGS!$B$14),"STUCK in onboarding","")))
A87: 86 | B87: UPK2-LM-249 | C87: SunGlam Films | D87: Lens & Motion | E87: LM-WEDDING | F87: Bengaluru | G87: A | H87: P0 | I87: under-discovered | J87: Personal 1:1 email from founder/team to published business email | K87: https://www.sunglamfilms.com/ | L87: W1 Founding cohort | AH87: =IF(AND(B87="",C87=""),"",IF(AND(X87<>"",Y87<>"",Z87<>"",AA87<>"",AB87="Y"),"YES","no")) | AI87: =IF(AH87="YES",MAX(X87,Y87,Z87,AA87),"") | AJ87: =IF(AND(B87="",C87=""),"",IF(OR(S87="Not interested",S87="Opt-out / do not contact"),"X Declined / suppressed",IF(S87="Bounced / undeliverable","X Bounced — research",IF(AC87<>"","13 Transacting",IF(AH87="YES","12 ACTIVATED",IF(Z87<>"","11 Listing live",IF(Y87<>"","10 Profile complete",IF(X87<>"","9 Approved",IF(W87<>"","8 KYC submitted",IF(V87<>"","7 Registered",IF(T87<>"","5 Interested",IF(R87<>"","4 Responded",IF(O87<>"","2 Contacted","1 Not yet contacted"))))))))))))) | AK87: =IF(AF87<>"",AF87,IF(OR(O87="",R87<>"",LEFT(AJ87,1)="X"),"",IF(Q87<>"","",IF(P87<>"",P87+SETTINGS!$B$4,O87+SETTINGS!$B$3)))) | AL87: =IF(AJ87="","",IF(LEFT(AJ87,1)="X","None — do not contact",IF(AJ87="1 Not yet contacted","Verify route today, then send M1",IF(AND(R87="",Q87<>""),"Sequence complete — no contact before "&TEXT(Q87+SETTINGS!$B$5,"yyyy-mm-dd"),IF(AND(R87="",P87<>""),"Send final note (M4)",IF(R87="","Send follow-up (M2)",IF(AJ87="12 ACTIVATED","7-day check-in; consent & referral soft ask",IF(AJ87="13 Transacting","Repeat-activity support","Onboarding: move to next stage (see playbook §6)")))))))) | AM87: =IF(ISNUMBER(AK87),IF(AK87<=TODAY(),"DUE",""),"") | AN87: =IF(COUNT(O87,P87,Q87,R87,T87,V87,W87,X87,Y87,Z87,AA87,AC87)=0,"",TODAY()-MAX(O87,P87,Q87,R87,T87,V87,W87,X87,Y87,Z87,AA87,AC87)) | AO87: =IF(AJ87="","",IF(AND(T87<>"",U87<>"Active (verified)"),"GST: escalate (no tax advice)",IF(AND(IFERROR(VALUE(LEFT(AJ87,2)),0)>=5,AH87<>"YES",ISNUMBER(AN87),AN87>SETTINGS!$B$14),"STUCK in onboarding","")))
A88: 87 | B88: UPK2-LM-425 | C88: The Chronicle Weddings | D88: Lens & Motion | E88: LM-WEDDING | F88: Bengaluru | G88: A | H88: P1 | I88: under-discovered | J88: 1:1 message via own-website contact form | K88: https://thechronicleweddings.com/contacts | L88: W1 Founding cohort | AH88: =IF(AND(B88="",C88=""),"",IF(AND(X88<>"",Y88<>"",Z88<>"",AA88<>"",AB88="Y"),"YES","no")) | AI88: =IF(AH88="YES",MAX(X88,Y88,Z88,AA88),"") | AJ88: =IF(AND(B88="",C88=""),"",IF(OR(S88="Not interested",S88="Opt-out / do not contact"),"X Declined / suppressed",IF(S88="Bounced / undeliverable","X Bounced — research",IF(AC88<>"","13 Transacting",IF(AH88="YES","12 ACTIVATED",IF(Z88<>"","11 Listing live",IF(Y88<>"","10 Profile complete",IF(X88<>"","9 Approved",IF(W88<>"","8 KYC submitted",IF(V88<>"","7 Registered",IF(T88<>"","5 Interested",IF(R88<>"","4 Responded",IF(O88<>"","2 Contacted","1 Not yet contacted"))))))))))))) | AK88: =IF(AF88<>"",AF88,IF(OR(O88="",R88<>"",LEFT(AJ88,1)="X"),"",IF(Q88<>"","",IF(P88<>"",P88+SETTINGS!$B$4,O88+SETTINGS!$B$3)))) | AL88: =IF(AJ88="","",IF(LEFT(AJ88,1)="X","None — do not contact",IF(AJ88="1 Not yet contacted","Verify route today, then send M1",IF(AND(R88="",Q88<>""),"Sequence complete — no contact before "&TEXT(Q88+SETTINGS!$B$5,"yyyy-mm-dd"),IF(AND(R88="",P88<>""),"Send final note (M4)",IF(R88="","Send follow-up (M2)",IF(AJ88="12 ACTIVATED","7-day check-in; consent & referral soft ask",IF(AJ88="13 Transacting","Repeat-activity support","Onboarding: move to next stage (see playbook §6)")))))))) | AM88: =IF(ISNUMBER(AK88),IF(AK88<=TODAY(),"DUE",""),"") | AN88: =IF(COUNT(O88,P88,Q88,R88,T88,V88,W88,X88,Y88,Z88,AA88,AC88)=0,"",TODAY()-MAX(O88,P88,Q88,R88,T88,V88,W88,X88,Y88,Z88,AA88,AC88)) | AO88: =IF(AJ88="","",IF(AND(T88<>"",U88<>"Active (verified)"),"GST: escalate (no tax advice)",IF(AND(IFERROR(VALUE(LEFT(AJ88,2)),0)>=5,AH88<>"YES",ISNUMBER(AN88),AN88>SETTINGS!$B$14),"STUCK in onboarding","")))
A89: 88 | B89: UPK2-LM-209 | C89: Dee Color Photography | D89: Lens & Motion | E89: LM-WEDDING | F89: Delhi NCR | G89: B | H89: P0 | J89: Personal 1:1 email from founder/team to published business email | K89: https://deecolor.com/ | L89: W1 Founding cohort | AH89: =IF(AND(B89="",C89=""),"",IF(AND(X89<>"",Y89<>"",Z89<>"",AA89<>"",AB89="Y"),"YES","no")) | AI89: =IF(AH89="YES",MAX(X89,Y89,Z89,AA89),"") | AJ89: =IF(AND(B89="",C89=""),"",IF(OR(S89="Not interested",S89="Opt-out / do not contact"),"X Declined / suppressed",IF(S89="Bounced / undeliverable","X Bounced — research",IF(AC89<>"","13 Transacting",IF(AH89="YES","12 ACTIVATED",IF(Z89<>"","11 Listing live",IF(Y89<>"","10 Profile complete",IF(X89<>"","9 Approved",IF(W89<>"","8 KYC submitted",IF(V89<>"","7 Registered",IF(T89<>"","5 Interested",IF(R89<>"","4 Responded",IF(O89<>"","2 Contacted","1 Not yet contacted"))))))))))))) | AK89: =IF(AF89<>"",AF89,IF(OR(O89="",R89<>"",LEFT(AJ89,1)="X"),"",IF(Q89<>"","",IF(P89<>"",P89+SETTINGS!$B$4,O89+SETTINGS!$B$3)))) | AL89: =IF(AJ89="","",IF(LEFT(AJ89,1)="X","None — do not contact",IF(AJ89="1 Not yet contacted","Verify route today, then send M1",IF(AND(R89="",Q89<>""),"Sequence complete — no contact before "&TEXT(Q89+SETTINGS!$B$5,"yyyy-mm-dd"),IF(AND(R89="",P89<>""),"Send final note (M4)",IF(R89="","Send follow-up (M2)",IF(AJ89="12 ACTIVATED","7-day check-in; consent & referral soft ask",IF(AJ89="13 Transacting","Repeat-activity support","Onboarding: move to next stage (see playbook §6)")))))))) | AM89: =IF(ISNUMBER(AK89),IF(AK89<=TODAY(),"DUE",""),"") | AN89: =IF(COUNT(O89,P89,Q89,R89,T89,V89,W89,X89,Y89,Z89,AA89,AC89)=0,"",TODAY()-MAX(O89,P89,Q89,R89,T89,V89,W89,X89,Y89,Z89,AA89,AC89)) | AO89: =IF(AJ89="","",IF(AND(T89<>"",U89<>"Active (verified)"),"GST: escalate (no tax advice)",IF(AND(IFERROR(VALUE(LEFT(AJ89,2)),0)>=5,AH89<>"YES",ISNUMBER(AN89),AN89>SETTINGS!$B$14),"STUCK in onboarding","")))
A90: 89 | B90: UPK2-LM-220 | C90: Aureate Weddings | D90: Lens & Motion | E90: LM-WEDDING | F90: Delhi NCR | G90: B | H90: P0 | J90: Personal 1:1 email from founder/team to published business email | K90: https://aureateweddings.com/ | L90: W1 Founding cohort | AH90: =IF(AND(B90="",C90=""),"",IF(AND(X90<>"",Y90<>"",Z90<>"",AA90<>"",AB90="Y"),"YES","no")) | AI90: =IF(AH90="YES",MAX(X90,Y90,Z90,AA90),"") | AJ90: =IF(AND(B90="",C90=""),"",IF(OR(S90="Not interested",S90="Opt-out / do not contact"),"X Declined / suppressed",IF(S90="Bounced / undeliverable","X Bounced — research",IF(AC90<>"","13 Transacting",IF(AH90="YES","12 ACTIVATED",IF(Z90<>"","11 Listing live",IF(Y90<>"","10 Profile complete",IF(X90<>"","9 Approved",IF(W90<>"","8 KYC submitted",IF(V90<>"","7 Registered",IF(T90<>"","5 Interested",IF(R90<>"","4 Responded",IF(O90<>"","2 Contacted","1 Not yet contacted"))))))))))))) | AK90: =IF(AF90<>"",AF90,IF(OR(O90="",R90<>"",LEFT(AJ90,1)="X"),"",IF(Q90<>"","",IF(P90<>"",P90+SETTINGS!$B$4,O90+SETTINGS!$B$3)))) | AL90: =IF(AJ90="","",IF(LEFT(AJ90,1)="X","None — do not contact",IF(AJ90="1 Not yet contacted","Verify route today, then send M1",IF(AND(R90="",Q90<>""),"Sequence complete — no contact before "&TEXT(Q90+SETTINGS!$B$5,"yyyy-mm-dd"),IF(AND(R90="",P90<>""),"Send final note (M4)",IF(R90="","Send follow-up (M2)",IF(AJ90="12 ACTIVATED","7-day check-in; consent & referral soft ask",IF(AJ90="13 Transacting","Repeat-activity support","Onboarding: move to next stage (see playbook §6)")))))))) | AM90: =IF(ISNUMBER(AK90),IF(AK90<=TODAY(),"DUE",""),"") | AN90: =IF(COUNT(O90,P90,Q90,R90,T90,V90,W90,X90,Y90,Z90,AA90,AC90)=0,"",TODAY()-MAX(O90,P90,Q90,R90,T90,V90,W90,X90,Y90,Z90,AA90,AC90)) | AO90: =IF(AJ90="","",IF(AND(T90<>"",U90<>"Active (verified)"),"GST: escalate (no tax advice)",IF(AND(IFERROR(VALUE(LEFT(AJ90,2)),0)>=5,AH90<>"YES",ISNUMBER(AN90),AN90>SETTINGS!$B$14),"STUCK in onboarding","")))
A91: 90 | B91: UPK2-LM-223 | C91: Bombay Paparazzi | D91: Lens & Motion | E91: LM-WEDDING | F91: Mumbai | G91: B | H91: P0 | J91: Personal 1:1 email from founder/team to published business email | K91: https://bombaypaparazzi.com/ | L91: W1 Founding cohort | AH91: =IF(AND(B91="",C91=""),"",IF(AND(X91<>"",Y91<>"",Z91<>"",AA91<>"",AB91="Y"),"YES","no")) | AI91: =IF(AH91="YES",MAX(X91,Y91,Z91,AA91),"") | AJ91: =IF(AND(B91="",C91=""),"",IF(OR(S91="Not interested",S91="Opt-out / do not contact"),"X Declined / suppressed",IF(S91="Bounced / undeliverable","X Bounced — research",IF(AC91<>"","13 Transacting",IF(AH91="YES","12 ACTIVATED",IF(Z91<>"","11 Listing live",IF(Y91<>"","10 Profile complete",IF(X91<>"","9 Approved",IF(W91<>"","8 KYC submitted",IF(V91<>"","7 Registered",IF(T91<>"","5 Interested",IF(R91<>"","4 Responded",IF(O91<>"","2 Contacted","1 Not yet contacted"))))))))))))) | AK91: =IF(AF91<>"",AF91,IF(OR(O91="",R91<>"",LEFT(AJ91,1)="X"),"",IF(Q91<>"","",IF(P91<>"",P91+SETTINGS!$B$4,O91+SETTINGS!$B$3)))) | AL91: =IF(AJ91="","",IF(LEFT(AJ91,1)="X","None — do not contact",IF(AJ91="1 Not yet contacted","Verify route today, then send M1",IF(AND(R91="",Q91<>""),"Sequence complete — no contact before "&TEXT(Q91+SETTINGS!$B$5,"yyyy-mm-dd"),IF(AND(R91="",P91<>""),"Send final note (M4)",IF(R91="","Send follow-up (M2)",IF(AJ91="12 ACTIVATED","7-day check-in; consent & referral soft ask",IF(AJ91="13 Transacting","Repeat-activity support","Onboarding: move to next stage (see playbook §6)")))))))) | AM91: =IF(ISNUMBER(AK91),IF(AK91<=TODAY(),"DUE",""),"") | AN91: =IF(COUNT(O91,P91,Q91,R91,T91,V91,W91,X91,Y91,Z91,AA91,AC91)=0,"",TODAY()-MAX(O91,P91,Q91,R91,T91,V91,W91,X91,Y91,Z91,AA91,AC91)) | AO91: =IF(AJ91="","",IF(AND(T91<>"",U91<>"Active (verified)"),"GST: escalate (no tax advice)",IF(AND(IFERROR(VALUE(LEFT(AJ91,2)),0)>=5,AH91<>"YES",ISNUMBER(AN91),AN91>SETTINGS!$B$14),"STUCK in onboarding","")))
A92: 91 | B92: UPK2-LM-356 | C92: Ashish Sahi | D92: Lens & Motion | E92: LM-ARCH-INTERIOR | F92: Mumbai | G92: C | H92: P0 | I92: under-discovered | J92: Personal 1:1 email from founder/team to published business email | K92: https://www.ashishsahi.com/ | L92: W1 Founding cohort | AH92: =IF(AND(B92="",C92=""),"",IF(AND(X92<>"",Y92<>"",Z92<>"",AA92<>"",AB92="Y"),"YES","no")) | AI92: =IF(AH92="YES",MAX(X92,Y92,Z92,AA92),"") | AJ92: =IF(AND(B92="",C92=""),"",IF(OR(S92="Not interested",S92="Opt-out / do not contact"),"X Declined / suppressed",IF(S92="Bounced / undeliverable","X Bounced — research",IF(AC92<>"","13 Transacting",IF(AH92="YES","12 ACTIVATED",IF(Z92<>"","11 Listing live",IF(Y92<>"","10 Profile complete",IF(X92<>"","9 Approved",IF(W92<>"","8 KYC submitted",IF(V92<>"","7 Registered",IF(T92<>"","5 Interested",IF(R92<>"","4 Responded",IF(O92<>"","2 Contacted","1 Not yet contacted"))))))))))))) | AK92: =IF(AF92<>"",AF92,IF(OR(O92="",R92<>"",LEFT(AJ92,1)="X"),"",IF(Q92<>"","",IF(P92<>"",P92+SETTINGS!$B$4,O92+SETTINGS!$B$3)))) | AL92: =IF(AJ92="","",IF(LEFT(AJ92,1)="X","None — do not contact",IF(AJ92="1 Not yet contacted","Verify route today, then send M1",IF(AND(R92="",Q92<>""),"Sequence complete — no contact before "&TEXT(Q92+SETTINGS!$B$5,"yyyy-mm-dd"),IF(AND(R92="",P92<>""),"Send final note (M4)",IF(R92="","Send follow-up (M2)",IF(AJ92="12 ACTIVATED","7-day check-in; consent & referral soft ask",IF(AJ92="13 Transacting","Repeat-activity support","Onboarding: move to next stage (see playbook §6)")))))))) | AM92: =IF(ISNUMBER(AK92),IF(AK92<=TODAY(),"DUE",""),"") | AN92: =IF(COUNT(O92,P92,Q92,R92,T92,V92,W92,X92,Y92,Z92,AA92,AC92)=0,"",TODAY()-MAX(O92,P92,Q92,R92,T92,V92,W92,X92,Y92,Z92,AA92,AC92)) | AO92: =IF(AJ92="","",IF(AND(T92<>"",U92<>"Active (verified)"),"GST: escalate (no tax advice)",IF(AND(IFERROR(VALUE(LEFT(AJ92,2)),0)>=5,AH92<>"YES",ISNUMBER(AN92),AN92>SETTINGS!$B$14),"STUCK in onboarding","")))
A93: 92 | B93: UPK-LM-003 | C93: Two Faces Media | D93: Lens & Motion | E93: LM-COMMERCIAL-FASHION | F93: Mumbai | G93: A | H93: P0 | I93: under-discovered | J93: Personal 1:1 email from founder/team to published business email | K93: https://twofacesmedia.com/ | L93: W1 Founding cohort | AH93: =IF(AND(B93="",C93=""),"",IF(AND(X93<>"",Y93<>"",Z93<>"",AA93<>"",AB93="Y"),"YES","no")) | AI93: =IF(AH93="YES",MAX(X93,Y93,Z93,AA93),"") | AJ93: =IF(AND(B93="",C93=""),"",IF(OR(S93="Not interested",S93="Opt-out / do not contact"),"X Declined / suppressed",IF(S93="Bounced / undeliverable","X Bounced — research",IF(AC93<>"","13 Transacting",IF(AH93="YES","12 ACTIVATED",IF(Z93<>"","11 Listing live",IF(Y93<>"","10 Profile complete",IF(X93<>"","9 Approved",IF(W93<>"","8 KYC submitted",IF(V93<>"","7 Registered",IF(T93<>"","5 Interested",IF(R93<>"","4 Responded",IF(O93<>"","2 Contacted","1 Not yet contacted"))))))))))))) | AK93: =IF(AF93<>"",AF93,IF(OR(O93="",R93<>"",LEFT(AJ93,1)="X"),"",IF(Q93<>"","",IF(P93<>"",P93+SETTINGS!$B$4,O93+SETTINGS!$B$3)))) | AL93: =IF(AJ93="","",IF(LEFT(AJ93,1)="X","None — do not contact",IF(AJ93="1 Not yet contacted","Verify route today, then send M1",IF(AND(R93="",Q93<>""),"Sequence complete — no contact before "&TEXT(Q93+SETTINGS!$B$5,"yyyy-mm-dd"),IF(AND(R93="",P93<>""),"Send final note (M4)",IF(R93="","Send follow-up (M2)",IF(AJ93="12 ACTIVATED","7-day check-in; consent & referral soft ask",IF(AJ93="13 Transacting","Repeat-activity support","Onboarding: move to next stage (see playbook §6)")))))))) | AM93: =IF(ISNUMBER(AK93),IF(AK93<=TODAY(),"DUE",""),"") | AN93: =IF(COUNT(O93,P93,Q93,R93,T93,V93,W93,X93,Y93,Z93,AA93,AC93)=0,"",TODAY()-MAX(O93,P93,Q93,R93,T93,V93,W93,X93,Y93,Z93,AA93,AC93)) | AO93: =IF(AJ93="","",IF(AND(T93<>"",U93<>"Active (verified)"),"GST: escalate (no tax advice)",IF(AND(IFERROR(VALUE(LEFT(AJ93,2)),0)>=5,AH93<>"YES",ISNUMBER(AN93),AN93>SETTINGS!$B$14),"STUCK in onboarding","")))
A94: 93 | B94: UPK2-LM-238 | C94: North Light Studio | D94: Lens & Motion | E94: LM-ARCH-INTERIOR | F94: Mumbai | G94: B | H94: P0 | I94: under-discovered | J94: Personal 1:1 email from founder/team to published business email | K94: https://www.northlightstudio.in/ | L94: W1 Founding cohort | AH94: =IF(AND(B94="",C94=""),"",IF(AND(X94<>"",Y94<>"",Z94<>"",AA94<>"",AB94="Y"),"YES","no")) | AI94: =IF(AH94="YES",MAX(X94,Y94,Z94,AA94),"") | AJ94: =IF(AND(B94="",C94=""),"",IF(OR(S94="Not interested",S94="Opt-out / do not contact"),"X Declined / suppressed",IF(S94="Bounced / undeliverable","X Bounced — research",IF(AC94<>"","13 Transacting",IF(AH94="YES","12 ACTIVATED",IF(Z94<>"","11 Listing live",IF(Y94<>"","10 Profile complete",IF(X94<>"","9 Approved",IF(W94<>"","8 KYC submitted",IF(V94<>"","7 Registered",IF(T94<>"","5 Interested",IF(R94<>"","4 Responded",IF(O94<>"","2 Contacted","1 Not yet contacted"))))))))))))) | AK94: =IF(AF94<>"",AF94,IF(OR(O94="",R94<>"",LEFT(AJ94,1)="X"),"",IF(Q94<>"","",IF(P94<>"",P94+SETTINGS!$B$4,O94+SETTINGS!$B$3)))) | AL94: =IF(AJ94="","",IF(LEFT(AJ94,1)="X","None — do not contact",IF(AJ94="1 Not yet contacted","Verify route today, then send M1",IF(AND(R94="",Q94<>""),"Sequence complete — no contact before "&TEXT(Q94+SETTINGS!$B$5,"yyyy-mm-dd"),IF(AND(R94="",P94<>""),"Send final note (M4)",IF(R94="","Send follow-up (M2)",IF(AJ94="12 ACTIVATED","7-day check-in; consent & referral soft ask",IF(AJ94="13 Transacting","Repeat-activity support","Onboarding: move to next stage (see playbook §6)")))))))) | AM94: =IF(ISNUMBER(AK94),IF(AK94<=TODAY(),"DUE",""),"") | AN94: =IF(COUNT(O94,P94,Q94,R94,T94,V94,W94,X94,Y94,Z94,AA94,AC94)=0,"",TODAY()-MAX(O94,P94,Q94,R94,T94,V94,W94,X94,Y94,Z94,AA94,AC94)) | AO94: =IF(AJ94="","",IF(AND(T94<>"",U94<>"Active (verified)"),"GST: escalate (no tax advice)",IF(AND(IFERROR(VALUE(LEFT(AJ94,2)),0)>=5,AH94<>"YES",ISNUMBER(AN94),AN94>SETTINGS!$B$14),"STUCK in onboarding","")))
A95: 94 | B95: UPK2-LM-278 | C95: Sameer Belvalkar Photography | D95: Lens & Motion | E95: LM-COMMERCIAL-FASHION | F95: Mumbai | G95: C | H95: P0 | I95: under-discovered | J95: Personal 1:1 email from founder/team to published business email | K95: https://sameerbelvalkar.com/ | L95: W1 Founding cohort | AH95: =IF(AND(B95="",C95=""),"",IF(AND(X95<>"",Y95<>"",Z95<>"",AA95<>"",AB95="Y"),"YES","no")) | AI95: =IF(AH95="YES",MAX(X95,Y95,Z95,AA95),"") | AJ95: =IF(AND(B95="",C95=""),"",IF(OR(S95="Not interested",S95="Opt-out / do not contact"),"X Declined / suppressed",IF(S95="Bounced / undeliverable","X Bounced — research",IF(AC95<>"","13 Transacting",IF(AH95="YES","12 ACTIVATED",IF(Z95<>"","11 Listing live",IF(Y95<>"","10 Profile complete",IF(X95<>"","9 Approved",IF(W95<>"","8 KYC submitted",IF(V95<>"","7 Registered",IF(T95<>"","5 Interested",IF(R95<>"","4 Responded",IF(O95<>"","2 Contacted","1 Not yet contacted"))))))))))))) | AK95: =IF(AF95<>"",AF95,IF(OR(O95="",R95<>"",LEFT(AJ95,1)="X"),"",IF(Q95<>"","",IF(P95<>"",P95+SETTINGS!$B$4,O95+SETTINGS!$B$3)))) | AL95: =IF(AJ95="","",IF(LEFT(AJ95,1)="X","None — do not contact",IF(AJ95="1 Not yet contacted","Verify route today, then send M1",IF(AND(R95="",Q95<>""),"Sequence complete — no contact before "&TEXT(Q95+SETTINGS!$B$5,"yyyy-mm-dd"),IF(AND(R95="",P95<>""),"Send final note (M4)",IF(R95="","Send follow-up (M2)",IF(AJ95="12 ACTIVATED","7-day check-in; consent & referral soft ask",IF(AJ95="13 Transacting","Repeat-activity support","Onboarding: move to next stage (see playbook §6)")))))))) | AM95: =IF(ISNUMBER(AK95),IF(AK95<=TODAY(),"DUE",""),"") | AN95: =IF(COUNT(O95,P95,Q95,R95,T95,V95,W95,X95,Y95,Z95,AA95,AC95)=0,"",TODAY()-MAX(O95,P95,Q95,R95,T95,V95,W95,X95,Y95,Z95,AA95,AC95)) | AO95: =IF(AJ95="","",IF(AND(T95<>"",U95<>"Active (verified)"),"GST: escalate (no tax advice)",IF(AND(IFERROR(VALUE(LEFT(AJ95,2)),0)>=5,AH95<>"YES",ISNUMBER(AN95),AN95>SETTINGS!$B$14),"STUCK in onboarding","")))
A96: 95 | B96: UPK2-LM-277 | C96: Mohsin Taha Photography | D96: Lens & Motion | E96: LM-ARCH-INTERIOR | F96: Mumbai | G96: B | H96: P0 | I96: under-discovered | J96: Personal 1:1 email from founder/team to published business email | K96: https://www.mohsintaha.com/ | L96: W1 Founding cohort | AH96: =IF(AND(B96="",C96=""),"",IF(AND(X96<>"",Y96<>"",Z96<>"",AA96<>"",AB96="Y"),"YES","no")) | AI96: =IF(AH96="YES",MAX(X96,Y96,Z96,AA96),"") | AJ96: =IF(AND(B96="",C96=""),"",IF(OR(S96="Not interested",S96="Opt-out / do not contact"),"X Declined / suppressed",IF(S96="Bounced / undeliverable","X Bounced — research",IF(AC96<>"","13 Transacting",IF(AH96="YES","12 ACTIVATED",IF(Z96<>"","11 Listing live",IF(Y96<>"","10 Profile complete",IF(X96<>"","9 Approved",IF(W96<>"","8 KYC submitted",IF(V96<>"","7 Registered",IF(T96<>"","5 Interested",IF(R96<>"","4 Responded",IF(O96<>"","2 Contacted","1 Not yet contacted"))))))))))))) | AK96: =IF(AF96<>"",AF96,IF(OR(O96="",R96<>"",LEFT(AJ96,1)="X"),"",IF(Q96<>"","",IF(P96<>"",P96+SETTINGS!$B$4,O96+SETTINGS!$B$3)))) | AL96: =IF(AJ96="","",IF(LEFT(AJ96,1)="X","None — do not contact",IF(AJ96="1 Not yet contacted","Verify route today, then send M1",IF(AND(R96="",Q96<>""),"Sequence complete — no contact before "&TEXT(Q96+SETTINGS!$B$5,"yyyy-mm-dd"),IF(AND(R96="",P96<>""),"Send final note (M4)",IF(R96="","Send follow-up (M2)",IF(AJ96="12 ACTIVATED","7-day check-in; consent & referral soft ask",IF(AJ96="13 Transacting","Repeat-activity support","Onboarding: move to next stage (see playbook §6)")))))))) | AM96: =IF(ISNUMBER(AK96),IF(AK96<=TODAY(),"DUE",""),"") | AN96: =IF(COUNT(O96,P96,Q96,R96,T96,V96,W96,X96,Y96,Z96,AA96,AC96)=0,"",TODAY()-MAX(O96,P96,Q96,R96,T96,V96,W96,X96,Y96,Z96,AA96,AC96)) | AO96: =IF(AJ96="","",IF(AND(T96<>"",U96<>"Active (verified)"),"GST: escalate (no tax advice)",IF(AND(IFERROR(VALUE(LEFT(AJ96,2)),0)>=5,AH96<>"YES",ISNUMBER(AN96),AN96>SETTINGS!$B$14),"STUCK in onboarding","")))
A97: 96 | B97: UPK2-LM-353 | C97: The Endless Forms | D97: Lens & Motion | E97: LM-ARCH-INTERIOR | F97: Mumbai | G97: B | H97: P0 | I97: under-discovered | J97: Personal 1:1 email from founder/team to published business email | K97: https://yadnyeshjoshi.com/contact | L97: W1 Founding cohort | AH97: =IF(AND(B97="",C97=""),"",IF(AND(X97<>"",Y97<>"",Z97<>"",AA97<>"",AB97="Y"),"YES","no")) | AI97: =IF(AH97="YES",MAX(X97,Y97,Z97,AA97),"") | AJ97: =IF(AND(B97="",C97=""),"",IF(OR(S97="Not interested",S97="Opt-out / do not contact"),"X Declined / suppressed",IF(S97="Bounced / undeliverable","X Bounced — research",IF(AC97<>"","13 Transacting",IF(AH97="YES","12 ACTIVATED",IF(Z97<>"","11 Listing live",IF(Y97<>"","10 Profile complete",IF(X97<>"","9 Approved",IF(W97<>"","8 KYC submitted",IF(V97<>"","7 Registered",IF(T97<>"","5 Interested",IF(R97<>"","4 Responded",IF(O97<>"","2 Contacted","1 Not yet contacted"))))))))))))) | AK97: =IF(AF97<>"",AF97,IF(OR(O97="",R97<>"",LEFT(AJ97,1)="X"),"",IF(Q97<>"","",IF(P97<>"",P97+SETTINGS!$B$4,O97+SETTINGS!$B$3)))) | AL97: =IF(AJ97="","",IF(LEFT(AJ97,1)="X","None — do not contact",IF(AJ97="1 Not yet contacted","Verify route today, then send M1",IF(AND(R97="",Q97<>""),"Sequence complete — no contact before "&TEXT(Q97+SETTINGS!$B$5,"yyyy-mm-dd"),IF(AND(R97="",P97<>""),"Send final note (M4)",IF(R97="","Send follow-up (M2)",IF(AJ97="12 ACTIVATED","7-day check-in; consent & referral soft ask",IF(AJ97="13 Transacting","Repeat-activity support","Onboarding: move to next stage (see playbook §6)")))))))) | AM97: =IF(ISNUMBER(AK97),IF(AK97<=TODAY(),"DUE",""),"") | AN97: =IF(COUNT(O97,P97,Q97,R97,T97,V97,W97,X97,Y97,Z97,AA97,AC97)=0,"",TODAY()-MAX(O97,P97,Q97,R97,T97,V97,W97,X97,Y97,Z97,AA97,AC97)) | AO97: =IF(AJ97="","",IF(AND(T97<>"",U97<>"Active (verified)"),"GST: escalate (no tax advice)",IF(AND(IFERROR(VALUE(LEFT(AJ97,2)),0)>=5,AH97<>"YES",ISNUMBER(AN97),AN97>SETTINGS!$B$14),"STUCK in onboarding","")))
A98: 97 | B98: UPK2-CM-050 | C98: Kunal Jessani | D98: Content & Media | E98: CM-EMCEE-HOST | F98: Mumbai | G98: A | H98: P0 | J98: Personal 1:1 email from founder/team to published business email | K98: https://kunaljessani.com/connect-with-us/ | L98: W1 Founding cohort | AH98: =IF(AND(B98="",C98=""),"",IF(AND(X98<>"",Y98<>"",Z98<>"",AA98<>"",AB98="Y"),"YES","no")) | AI98: =IF(AH98="YES",MAX(X98,Y98,Z98,AA98),"") | AJ98: =IF(AND(B98="",C98=""),"",IF(OR(S98="Not interested",S98="Opt-out / do not contact"),"X Declined / suppressed",IF(S98="Bounced / undeliverable","X Bounced — research",IF(AC98<>"","13 Transacting",IF(AH98="YES","12 ACTIVATED",IF(Z98<>"","11 Listing live",IF(Y98<>"","10 Profile complete",IF(X98<>"","9 Approved",IF(W98<>"","8 KYC submitted",IF(V98<>"","7 Registered",IF(T98<>"","5 Interested",IF(R98<>"","4 Responded",IF(O98<>"","2 Contacted","1 Not yet contacted"))))))))))))) | AK98: =IF(AF98<>"",AF98,IF(OR(O98="",R98<>"",LEFT(AJ98,1)="X"),"",IF(Q98<>"","",IF(P98<>"",P98+SETTINGS!$B$4,O98+SETTINGS!$B$3)))) | AL98: =IF(AJ98="","",IF(LEFT(AJ98,1)="X","None — do not contact",IF(AJ98="1 Not yet contacted","Verify route today, then send M1",IF(AND(R98="",Q98<>""),"Sequence complete — no contact before "&TEXT(Q98+SETTINGS!$B$5,"yyyy-mm-dd"),IF(AND(R98="",P98<>""),"Send final note (M4)",IF(R98="","Send follow-up (M2)",IF(AJ98="12 ACTIVATED","7-day check-in; consent & referral soft ask",IF(AJ98="13 Transacting","Repeat-activity support","Onboarding: move to next stage (see playbook §6)")))))))) | AM98: =IF(ISNUMBER(AK98),IF(AK98<=TODAY(),"DUE",""),"") | AN98: =IF(COUNT(O98,P98,Q98,R98,T98,V98,W98,X98,Y98,Z98,AA98,AC98)=0,"",TODAY()-MAX(O98,P98,Q98,R98,T98,V98,W98,X98,Y98,Z98,AA98,AC98)) | AO98: =IF(AJ98="","",IF(AND(T98<>"",U98<>"Active (verified)"),"GST: escalate (no tax advice)",IF(AND(IFERROR(VALUE(LEFT(AJ98,2)),0)>=5,AH98<>"YES",ISNUMBER(AN98),AN98>SETTINGS!$B$14),"STUCK in onboarding","")))
A99: 98 | B99: UPK2-CM-051 | C99: Ansh Chaudhary | D99: Content & Media | E99: CM-EMCEE-HOST | F99: Delhi NCR | G99: A | H99: P0 | J99: Personal 1:1 email from founder/team to published business email | K99: https://anchoransh.com | L99: W1 Founding cohort | AH99: =IF(AND(B99="",C99=""),"",IF(AND(X99<>"",Y99<>"",Z99<>"",AA99<>"",AB99="Y"),"YES","no")) | AI99: =IF(AH99="YES",MAX(X99,Y99,Z99,AA99),"") | AJ99: =IF(AND(B99="",C99=""),"",IF(OR(S99="Not interested",S99="Opt-out / do not contact"),"X Declined / suppressed",IF(S99="Bounced / undeliverable","X Bounced — research",IF(AC99<>"","13 Transacting",IF(AH99="YES","12 ACTIVATED",IF(Z99<>"","11 Listing live",IF(Y99<>"","10 Profile complete",IF(X99<>"","9 Approved",IF(W99<>"","8 KYC submitted",IF(V99<>"","7 Registered",IF(T99<>"","5 Interested",IF(R99<>"","4 Responded",IF(O99<>"","2 Contacted","1 Not yet contacted"))))))))))))) | AK99: =IF(AF99<>"",AF99,IF(OR(O99="",R99<>"",LEFT(AJ99,1)="X"),"",IF(Q99<>"","",IF(P99<>"",P99+SETTINGS!$B$4,O99+SETTINGS!$B$3)))) | AL99: =IF(AJ99="","",IF(LEFT(AJ99,1)="X","None — do not contact",IF(AJ99="1 Not yet contacted","Verify route today, then send M1",IF(AND(R99="",Q99<>""),"Sequence complete — no contact before "&TEXT(Q99+SETTINGS!$B$5,"yyyy-mm-dd"),IF(AND(R99="",P99<>""),"Send final note (M4)",IF(R99="","Send follow-up (M2)",IF(AJ99="12 ACTIVATED","7-day check-in; consent & referral soft ask",IF(AJ99="13 Transacting","Repeat-activity support","Onboarding: move to next stage (see playbook §6)")))))))) | AM99: =IF(ISNUMBER(AK99),IF(AK99<=TODAY(),"DUE",""),"") | AN99: =IF(COUNT(O99,P99,Q99,R99,T99,V99,W99,X99,Y99,Z99,AA99,AC99)=0,"",TODAY()-MAX(O99,P99,Q99,R99,T99,V99,W99,X99,Y99,Z99,AA99,AC99)) | AO99: =IF(AJ99="","",IF(AND(T99<>"",U99<>"Active (verified)"),"GST: escalate (no tax advice)",IF(AND(IFERROR(VALUE(LEFT(AJ99,2)),0)>=5,AH99<>"YES",ISNUMBER(AN99),AN99>SETTINGS!$B$14),"STUCK in onboarding","")))
A100: 99 | B100: UPK2-CM-052 | C100: Tina Behl | D100: Content & Media | E100: CM-EMCEE-HOST | F100: Delhi NCR | G100: A | H100: P0 | J100: 1:1 Instagram DM from Uepaki professional account | K100: https://www.instagram.com/tina.behl | L100: W1 Founding cohort | AH100: =IF(AND(B100="",C100=""),"",IF(AND(X100<>"",Y100<>"",Z100<>"",AA100<>"",AB100="Y"),"YES","no")) | AI100: =IF(AH100="YES",MAX(X100,Y100,Z100,AA100),"") | AJ100: =IF(AND(B100="",C100=""),"",IF(OR(S100="Not interested",S100="Opt-out / do not contact"),"X Declined / suppressed",IF(S100="Bounced / undeliverable","X Bounced — research",IF(AC100<>"","13 Transacting",IF(AH100="YES","12 ACTIVATED",IF(Z100<>"","11 Listing live",IF(Y100<>"","10 Profile complete",IF(X100<>"","9 Approved",IF(W100<>"","8 KYC submitted",IF(V100<>"","7 Registered",IF(T100<>"","5 Interested",IF(R100<>"","4 Responded",IF(O100<>"","2 Contacted","1 Not yet contacted"))))))))))))) | AK100: =IF(AF100<>"",AF100,IF(OR(O100="",R100<>"",LEFT(AJ100,1)="X"),"",IF(Q100<>"","",IF(P100<>"",P100+SETTINGS!$B$4,O100+SETTINGS!$B$3)))) | AL100: =IF(AJ100="","",IF(LEFT(AJ100,1)="X","None — do not contact",IF(AJ100="1 Not yet contacted","Verify route today, then send M1",IF(AND(R100="",Q100<>""),"Sequence complete — no contact before "&TEXT(Q100+SETTINGS!$B$5,"yyyy-mm-dd"),IF(AND(R100="",P100<>""),"Send final note (M4)",IF(R100="","Send follow-up (M2)",IF(AJ100="12 ACTIVATED","7-day check-in; consent & referral soft ask",IF(AJ100="13 Transacting","Repeat-activity support","Onboarding: move to next stage (see playbook §6)")))))))) | AM100: =IF(ISNUMBER(AK100),IF(AK100<=TODAY(),"DUE",""),"") | AN100: =IF(COUNT(O100,P100,Q100,R100,T100,V100,W100,X100,Y100,Z100,AA100,AC100)=0,"",TODAY()-MAX(O100,P100,Q100,R100,T100,V100,W100,X100,Y100,Z100,AA100,AC100)) | AO100: =IF(AJ100="","",IF(AND(T100<>"",U100<>"Active (verified)"),"GST: escalate (no tax advice)",IF(AND(IFERROR(VALUE(LEFT(AJ100,2)),0)>=5,AH100<>"YES",ISNUMBER(AN100),AN100>SETTINGS!$B$14),"STUCK in onboarding","")))
A101: 100 | B101: UPK2-CM-045 | C101: Krishna (Emcee Krishna) | D101: Content & Media | E101: CM-EMCEE-HOST | F101: Mumbai | G101: B | H101: P0 | J101: 1:1 Instagram DM from Uepaki professional account | K101: https://www.instagram.com/emceekrishna | L101: W1 Founding cohort | AH101: =IF(AND(B101="",C101=""),"",IF(AND(X101<>"",Y101<>"",Z101<>"",AA101<>"",AB101="Y"),"YES","no")) | AI101: =IF(AH101="YES",MAX(X101,Y101,Z101,AA101),"") | AJ101: =IF(AND(B101="",C101=""),"",IF(OR(S101="Not interested",S101="Opt-out / do not contact"),"X Declined / suppressed",IF(S101="Bounced / undeliverable","X Bounced — research",IF(AC101<>"","13 Transacting",IF(AH101="YES","12 ACTIVATED",IF(Z101<>"","11 Listing live",IF(Y101<>"","10 Profile complete",IF(X101<>"","9 Approved",IF(W101<>"","8 KYC submitted",IF(V101<>"","7 Registered",IF(T101<>"","5 Interested",IF(R101<>"","4 Responded",IF(O101<>"","2 Contacted","1 Not yet contacted"))))))))))))) | AK101: =IF(AF101<>"",AF101,IF(OR(O101="",R101<>"",LEFT(AJ101,1)="X"),"",IF(Q101<>"","",IF(P101<>"",P101+SETTINGS!$B$4,O101+SETTINGS!$B$3)))) | AL101: =IF(AJ101="","",IF(LEFT(AJ101,1)="X","None — do not contact",IF(AJ101="1 Not yet contacted","Verify route today, then send M1",IF(AND(R101="",Q101<>""),"Sequence complete — no contact before "&TEXT(Q101+SETTINGS!$B$5,"yyyy-mm-dd"),IF(AND(R101="",P101<>""),"Send final note (M4)",IF(R101="","Send follow-up (M2)",IF(AJ101="12 ACTIVATED","7-day check-in; consent & referral soft ask",IF(AJ101="13 Transacting","Repeat-activity support","Onboarding: move to next stage (see playbook §6)")))))))) | AM101: =IF(ISNUMBER(AK101),IF(AK101<=TODAY(),"DUE",""),"") | AN101: =IF(COUNT(O101,P101,Q101,R101,T101,V101,W101,X101,Y101,Z101,AA101,AC101)=0,"",TODAY()-MAX(O101,P101,Q101,R101,T101,V101,W101,X101,Y101,Z101,AA101,AC101)) | AO101: =IF(AJ101="","",IF(AND(T101<>"",U101<>"Active (verified)"),"GST: escalate (no tax advice)",IF(AND(IFERROR(VALUE(LEFT(AJ101,2)),0)>=5,AH101<>"YES",ISNUMBER(AN101),AN101>SETTINGS!$B$14),"STUCK in onboarding","")))
A102: 101 | B102: UPK2-FL-209 | C102: Chotibuti | D102: Fashion & Lifestyle | E102: FL-OCCASION-BRIDAL | F102: Delhi NCR | G102: A | H102: P0 | I102: stockist-listed | J102: Personal 1:1 email from founder/team to published business email | K102: https://chotibuti.com/ | L102: W2 Expansion | AH102: =IF(AND(B102="",C102=""),"",IF(AND(X102<>"",Y102<>"",Z102<>"",AA102<>"",AB102="Y"),"YES","no")) | AI102: =IF(AH102="YES",MAX(X102,Y102,Z102,AA102),"") | AJ102: =IF(AND(B102="",C102=""),"",IF(OR(S102="Not interested",S102="Opt-out / do not contact"),"X Declined / suppressed",IF(S102="Bounced / undeliverable","X Bounced — research",IF(AC102<>"","13 Transacting",IF(AH102="YES","12 ACTIVATED",IF(Z102<>"","11 Listing live",IF(Y102<>"","10 Profile complete",IF(X102<>"","9 Approved",IF(W102<>"","8 KYC submitted",IF(V102<>"","7 Registered",IF(T102<>"","5 Interested",IF(R102<>"","4 Responded",IF(O102<>"","2 Contacted","1 Not yet contacted"))))))))))))) | AK102: =IF(AF102<>"",AF102,IF(OR(O102="",R102<>"",LEFT(AJ102,1)="X"),"",IF(Q102<>"","",IF(P102<>"",P102+SETTINGS!$B$4,O102+SETTINGS!$B$3)))) | AL102: =IF(AJ102="","",IF(LEFT(AJ102,1)="X","None — do not contact",IF(AJ102="1 Not yet contacted","Verify route today, then send M1",IF(AND(R102="",Q102<>""),"Sequence complete — no contact before "&TEXT(Q102+SETTINGS!$B$5,"yyyy-mm-dd"),IF(AND(R102="",P102<>""),"Send final note (M4)",IF(R102="","Send follow-up (M2)",IF(AJ102="12 ACTIVATED","7-day check-in; consent & referral soft ask",IF(AJ102="13 Transacting","Repeat-activity support","Onboarding: move to next stage (see playbook §6)")))))))) | AM102: =IF(ISNUMBER(AK102),IF(AK102<=TODAY(),"DUE",""),"") | AN102: =IF(COUNT(O102,P102,Q102,R102,T102,V102,W102,X102,Y102,Z102,AA102,AC102)=0,"",TODAY()-MAX(O102,P102,Q102,R102,T102,V102,W102,X102,Y102,Z102,AA102,AC102)) | AO102: =IF(AJ102="","",IF(AND(T102<>"",U102<>"Active (verified)"),"GST: escalate (no tax advice)",IF(AND(IFERROR(VALUE(LEFT(AJ102,2)),0)>=5,AH102<>"YES",ISNUMBER(AN102),AN102>SETTINGS!$B$14),"STUCK in onboarding","")))
A103: 102 | B103: UPK2-FL-197 | C103: Sica Jewellery | D103: Fashion & Lifestyle | E103: FL-JEWELLERY | F103: Mumbai | G103: A | H103: P0 | I103: stockist-listed|large catalogue | J103: Personal 1:1 email from founder/team to published business email | K103: https://sicajewellery.com/pages/contact-us | L103: W2 Expansion | AH103: =IF(AND(B103="",C103=""),"",IF(AND(X103<>"",Y103<>"",Z103<>"",AA103<>"",AB103="Y"),"YES","no")) | AI103: =IF(AH103="YES",MAX(X103,Y103,Z103,AA103),"") | AJ103: =IF(AND(B103="",C103=""),"",IF(OR(S103="Not interested",S103="Opt-out / do not contact"),"X Declined / suppressed",IF(S103="Bounced / undeliverable","X Bounced — research",IF(AC103<>"","13 Transacting",IF(AH103="YES","12 ACTIVATED",IF(Z103<>"","11 Listing live",IF(Y103<>"","10 Profile complete",IF(X103<>"","9 Approved",IF(W103<>"","8 KYC submitted",IF(V103<>"","7 Registered",IF(T103<>"","5 Interested",IF(R103<>"","4 Responded",IF(O103<>"","2 Contacted","1 Not yet contacted"))))))))))))) | AK103: =IF(AF103<>"",AF103,IF(OR(O103="",R103<>"",LEFT(AJ103,1)="X"),"",IF(Q103<>"","",IF(P103<>"",P103+SETTINGS!$B$4,O103+SETTINGS!$B$3)))) | AL103: =IF(AJ103="","",IF(LEFT(AJ103,1)="X","None — do not contact",IF(AJ103="1 Not yet contacted","Verify route today, then send M1",IF(AND(R103="",Q103<>""),"Sequence complete — no contact before "&TEXT(Q103+SETTINGS!$B$5,"yyyy-mm-dd"),IF(AND(R103="",P103<>""),"Send final note (M4)",IF(R103="","Send follow-up (M2)",IF(AJ103="12 ACTIVATED","7-day check-in; consent & referral soft ask",IF(AJ103="13 Transacting","Repeat-activity support","Onboarding: move to next stage (see playbook §6)")))))))) | AM103: =IF(ISNUMBER(AK103),IF(AK103<=TODAY(),"DUE",""),"") | AN103: =IF(COUNT(O103,P103,Q103,R103,T103,V103,W103,X103,Y103,Z103,AA103,AC103)=0,"",TODAY()-MAX(O103,P103,Q103,R103,T103,V103,W103,X103,Y103,Z103,AA103,AC103)) | AO103: =IF(AJ103="","",IF(AND(T103<>"",U103<>"Active (verified)"),"GST: escalate (no tax advice)",IF(AND(IFERROR(VALUE(LEFT(AJ103,2)),0)>=5,AH103<>"YES",ISNUMBER(AN103),AN103>SETTINGS!$B$14),"STUCK in onboarding","")))
A104: 103 | B104: UPK2-FL-190 | C104: Ankit V Kapoor | D104: Fashion & Lifestyle | E104: FL-ACCESSORIES | F104: Delhi NCR | G104: A | H104: P0 | I104: stockist-listed|large catalogue | J104: Personal 1:1 email from founder/team to published business email | K104: https://www.ankitvkapoor.com/pages/contact | L104: W2 Expansion | AH104: =IF(AND(B104="",C104=""),"",IF(AND(X104<>"",Y104<>"",Z104<>"",AA104<>"",AB104="Y"),"YES","no")) | AI104: =IF(AH104="YES",MAX(X104,Y104,Z104,AA104),"") | AJ104: =IF(AND(B104="",C104=""),"",IF(OR(S104="Not interested",S104="Opt-out / do not contact"),"X Declined / suppressed",IF(S104="Bounced / undeliverable","X Bounced — research",IF(AC104<>"","13 Transacting",IF(AH104="YES","12 ACTIVATED",IF(Z104<>"","11 Listing live",IF(Y104<>"","10 Profile complete",IF(X104<>"","9 Approved",IF(W104<>"","8 KYC submitted",IF(V104<>"","7 Registered",IF(T104<>"","5 Interested",IF(R104<>"","4 Responded",IF(O104<>"","2 Contacted","1 Not yet contacted"))))))))))))) | AK104: =IF(AF104<>"",AF104,IF(OR(O104="",R104<>"",LEFT(AJ104,1)="X"),"",IF(Q104<>"","",IF(P104<>"",P104+SETTINGS!$B$4,O104+SETTINGS!$B$3)))) | AL104: =IF(AJ104="","",IF(LEFT(AJ104,1)="X","None — do not contact",IF(AJ104="1 Not yet contacted","Verify route today, then send M1",IF(AND(R104="",Q104<>""),"Sequence complete — no contact before "&TEXT(Q104+SETTINGS!$B$5,"yyyy-mm-dd"),IF(AND(R104="",P104<>""),"Send final note (M4)",IF(R104="","Send follow-up (M2)",IF(AJ104="12 ACTIVATED","7-day check-in; consent & referral soft ask",IF(AJ104="13 Transacting","Repeat-activity support","Onboarding: move to next stage (see playbook §6)")))))))) | AM104: =IF(ISNUMBER(AK104),IF(AK104<=TODAY(),"DUE",""),"") | AN104: =IF(COUNT(O104,P104,Q104,R104,T104,V104,W104,X104,Y104,Z104,AA104,AC104)=0,"",TODAY()-MAX(O104,P104,Q104,R104,T104,V104,W104,X104,Y104,Z104,AA104,AC104)) | AO104: =IF(AJ104="","",IF(AND(T104<>"",U104<>"Active (verified)"),"GST: escalate (no tax advice)",IF(AND(IFERROR(VALUE(LEFT(AJ104,2)),0)>=5,AH104<>"YES",ISNUMBER(AN104),AN104>SETTINGS!$B$14),"STUCK in onboarding","")))
A105: 104 | B105: UPK2-FL-198 | C105: Silky Bindra | D105: Fashion & Lifestyle | E105: FL-OCCASION-BRIDAL | F105: Delhi NCR | G105: A | H105: P0 | I105: stockist-listed|large catalogue | J105: Personal 1:1 email from founder/team to published business email | K105: https://www.silkybindra.com/pages/contact | L105: W2 Expansion | AH105: =IF(AND(B105="",C105=""),"",IF(AND(X105<>"",Y105<>"",Z105<>"",AA105<>"",AB105="Y"),"YES","no")) | AI105: =IF(AH105="YES",MAX(X105,Y105,Z105,AA105),"") | AJ105: =IF(AND(B105="",C105=""),"",IF(OR(S105="Not interested",S105="Opt-out / do not contact"),"X Declined / suppressed",IF(S105="Bounced / undeliverable","X Bounced — research",IF(AC105<>"","13 Transacting",IF(AH105="YES","12 ACTIVATED",IF(Z105<>"","11 Listing live",IF(Y105<>"","10 Profile complete",IF(X105<>"","9 Approved",IF(W105<>"","8 KYC submitted",IF(V105<>"","7 Registered",IF(T105<>"","5 Interested",IF(R105<>"","4 Responded",IF(O105<>"","2 Contacted","1 Not yet contacted"))))))))))))) | AK105: =IF(AF105<>"",AF105,IF(OR(O105="",R105<>"",LEFT(AJ105,1)="X"),"",IF(Q105<>"","",IF(P105<>"",P105+SETTINGS!$B$4,O105+SETTINGS!$B$3)))) | AL105: =IF(AJ105="","",IF(LEFT(AJ105,1)="X","None — do not contact",IF(AJ105="1 Not yet contacted","Verify route today, then send M1",IF(AND(R105="",Q105<>""),"Sequence complete — no contact before "&TEXT(Q105+SETTINGS!$B$5,"yyyy-mm-dd"),IF(AND(R105="",P105<>""),"Send final note (M4)",IF(R105="","Send follow-up (M2)",IF(AJ105="12 ACTIVATED","7-day check-in; consent & referral soft ask",IF(AJ105="13 Transacting","Repeat-activity support","Onboarding: move to next stage (see playbook §6)")))))))) | AM105: =IF(ISNUMBER(AK105),IF(AK105<=TODAY(),"DUE",""),"") | AN105: =IF(COUNT(O105,P105,Q105,R105,T105,V105,W105,X105,Y105,Z105,AA105,AC105)=0,"",TODAY()-MAX(O105,P105,Q105,R105,T105,V105,W105,X105,Y105,Z105,AA105,AC105)) | AO105: =IF(AJ105="","",IF(AND(T105<>"",U105<>"Active (verified)"),"GST: escalate (no tax advice)",IF(AND(IFERROR(VALUE(LEFT(AJ105,2)),0)>=5,AH105<>"YES",ISNUMBER(AN105),AN105>SETTINGS!$B$14),"STUCK in onboarding","")))
A106: 105 | B106: UPK2-FL-309 | C106: The Slow Studio | D106: Fashion & Lifestyle | E106: FL-JEWELLERY | F106: Delhi NCR | G106: A | H106: P0 | I106: stockist-listed | J106: Personal 1:1 email from founder/team to published business email | K106: https://theslowstudio.com/pages/contact | L106: W2 Expansion | AH106: =IF(AND(B106="",C106=""),"",IF(AND(X106<>"",Y106<>"",Z106<>"",AA106<>"",AB106="Y"),"YES","no")) | AI106: =IF(AH106="YES",MAX(X106,Y106,Z106,AA106),"") | AJ106: =IF(AND(B106="",C106=""),"",IF(OR(S106="Not interested",S106="Opt-out / do not contact"),"X Declined / suppressed",IF(S106="Bounced / undeliverable","X Bounced — research",IF(AC106<>"","13 Transacting",IF(AH106="YES","12 ACTIVATED",IF(Z106<>"","11 Listing live",IF(Y106<>"","10 Profile complete",IF(X106<>"","9 Approved",IF(W106<>"","8 KYC submitted",IF(V106<>"","7 Registered",IF(T106<>"","5 Interested",IF(R106<>"","4 Responded",IF(O106<>"","2 Contacted","1 Not yet contacted"))))))))))))) | AK106: =IF(AF106<>"",AF106,IF(OR(O106="",R106<>"",LEFT(AJ106,1)="X"),"",IF(Q106<>"","",IF(P106<>"",P106+SETTINGS!$B$4,O106+SETTINGS!$B$3)))) | AL106: =IF(AJ106="","",IF(LEFT(AJ106,1)="X","None — do not contact",IF(AJ106="1 Not yet contacted","Verify route today, then send M1",IF(AND(R106="",Q106<>""),"Sequence complete — no contact before "&TEXT(Q106+SETTINGS!$B$5,"yyyy-mm-dd"),IF(AND(R106="",P106<>""),"Send final note (M4)",IF(R106="","Send follow-up (M2)",IF(AJ106="12 ACTIVATED","7-day check-in; consent & referral soft ask",IF(AJ106="13 Transacting","Repeat-activity support","Onboarding: move to next stage (see playbook §6)")))))))) | AM106: =IF(ISNUMBER(AK106),IF(AK106<=TODAY(),"DUE",""),"") | AN106: =IF(COUNT(O106,P106,Q106,R106,T106,V106,W106,X106,Y106,Z106,AA106,AC106)=0,"",TODAY()-MAX(O106,P106,Q106,R106,T106,V106,W106,X106,Y106,Z106,AA106,AC106)) | AO106: =IF(AJ106="","",IF(AND(T106<>"",U106<>"Active (verified)"),"GST: escalate (no tax advice)",IF(AND(IFERROR(VALUE(LEFT(AJ106,2)),0)>=5,AH106<>"YES",ISNUMBER(AN106),AN106>SETTINGS!$B$14),"STUCK in onboarding","")))
A107: 106 | B107: UPK2-FL-343 | C107: Label Niyami | D107: Fashion & Lifestyle | E107: FL-CONTEMPORARY | F107: Mumbai | G107: A | H107: P0 | I107: stockist-listed | J107: Personal 1:1 email from founder/team to published business email | K107: https://labelniyami.com/pages/contact | L107: W2 Expansion | AH107: =IF(AND(B107="",C107=""),"",IF(AND(X107<>"",Y107<>"",Z107<>"",AA107<>"",AB107="Y"),"YES","no")) | AI107: =IF(AH107="YES",MAX(X107,Y107,Z107,AA107),"") | AJ107: =IF(AND(B107="",C107=""),"",IF(OR(S107="Not interested",S107="Opt-out / do not contact"),"X Declined / suppressed",IF(S107="Bounced / undeliverable","X Bounced — research",IF(AC107<>"","13 Transacting",IF(AH107="YES","12 ACTIVATED",IF(Z107<>"","11 Listing live",IF(Y107<>"","10 Profile complete",IF(X107<>"","9 Approved",IF(W107<>"","8 KYC submitted",IF(V107<>"","7 Registered",IF(T107<>"","5 Interested",IF(R107<>"","4 Responded",IF(O107<>"","2 Contacted","1 Not yet contacted"))))))))))))) | AK107: =IF(AF107<>"",AF107,IF(OR(O107="",R107<>"",LEFT(AJ107,1)="X"),"",IF(Q107<>"","",IF(P107<>"",P107+SETTINGS!$B$4,O107+SETTINGS!$B$3)))) | AL107: =IF(AJ107="","",IF(LEFT(AJ107,1)="X","None — do not contact",IF(AJ107="1 Not yet contacted","Verify route today, then send M1",IF(AND(R107="",Q107<>""),"Sequence complete — no contact before "&TEXT(Q107+SETTINGS!$B$5,"yyyy-mm-dd"),IF(AND(R107="",P107<>""),"Send final note (M4)",IF(R107="","Send follow-up (M2)",IF(AJ107="12 ACTIVATED","7-day check-in; consent & referral soft ask",IF(AJ107="13 Transacting","Repeat-activity support","Onboarding: move to next stage (see playbook §6)")))))))) | AM107: =IF(ISNUMBER(AK107),IF(AK107<=TODAY(),"DUE",""),"") | AN107: =IF(COUNT(O107,P107,Q107,R107,T107,V107,W107,X107,Y107,Z107,AA107,AC107)=0,"",TODAY()-MAX(O107,P107,Q107,R107,T107,V107,W107,X107,Y107,Z107,AA107,AC107)) | AO107: =IF(AJ107="","",IF(AND(T107<>"",U107<>"Active (verified)"),"GST: escalate (no tax advice)",IF(AND(IFERROR(VALUE(LEFT(AJ107,2)),0)>=5,AH107<>"YES",ISNUMBER(AN107),AN107>SETTINGS!$B$14),"STUCK in onboarding","")))
A108: 107 | B108: UPK2-FL-322 | C108: Asaga | D108: Fashion & Lifestyle | E108: FL-OCCASION-BRIDAL | F108: Mumbai | G108: A | H108: P0 | I108: stockist-listed|large catalogue | J108: 1:1 message via own-website contact form | K108: https://www.asaga.in/pages/contact-us | L108: W2 Expansion | AH108: =IF(AND(B108="",C108=""),"",IF(AND(X108<>"",Y108<>"",Z108<>"",AA108<>"",AB108="Y"),"YES","no")) | AI108: =IF(AH108="YES",MAX(X108,Y108,Z108,AA108),"") | AJ108: =IF(AND(B108="",C108=""),"",IF(OR(S108="Not interested",S108="Opt-out / do not contact"),"X Declined / suppressed",IF(S108="Bounced / undeliverable","X Bounced — research",IF(AC108<>"","13 Transacting",IF(AH108="YES","12 ACTIVATED",IF(Z108<>"","11 Listing live",IF(Y108<>"","10 Profile complete",IF(X108<>"","9 Approved",IF(W108<>"","8 KYC submitted",IF(V108<>"","7 Registered",IF(T108<>"","5 Interested",IF(R108<>"","4 Responded",IF(O108<>"","2 Contacted","1 Not yet contacted"))))))))))))) | AK108: =IF(AF108<>"",AF108,IF(OR(O108="",R108<>"",LEFT(AJ108,1)="X"),"",IF(Q108<>"","",IF(P108<>"",P108+SETTINGS!$B$4,O108+SETTINGS!$B$3)))) | AL108: =IF(AJ108="","",IF(LEFT(AJ108,1)="X","None — do not contact",IF(AJ108="1 Not yet contacted","Verify route today, then send M1",IF(AND(R108="",Q108<>""),"Sequence complete — no contact before "&TEXT(Q108+SETTINGS!$B$5,"yyyy-mm-dd"),IF(AND(R108="",P108<>""),"Send final note (M4)",IF(R108="","Send follow-up (M2)",IF(AJ108="12 ACTIVATED","7-day check-in; consent & referral soft ask",IF(AJ108="13 Transacting","Repeat-activity support","Onboarding: move to next stage (see playbook §6)")))))))) | AM108: =IF(ISNUMBER(AK108),IF(AK108<=TODAY(),"DUE",""),"") | AN108: =IF(COUNT(O108,P108,Q108,R108,T108,V108,W108,X108,Y108,Z108,AA108,AC108)=0,"",TODAY()-MAX(O108,P108,Q108,R108,T108,V108,W108,X108,Y108,Z108,AA108,AC108)) | AO108: =IF(AJ108="","",IF(AND(T108<>"",U108<>"Active (verified)"),"GST: escalate (no tax advice)",IF(AND(IFERROR(VALUE(LEFT(AJ108,2)),0)>=5,AH108<>"YES",ISNUMBER(AN108),AN108>SETTINGS!$B$14),"STUCK in onboarding","")))
A109: 108 | B109: UPK2-FL-325 | C109: Banana Labs | D109: Fashion & Lifestyle | E109: FL-CONTEMPORARY | F109: Delhi NCR | G109: A | H109: P0 | I109: stockist-listed|large catalogue | J109: 1:1 message via own-website contact form | K109: https://bananalabs.in/pages/contact-us | L109: W2 Expansion | AH109: =IF(AND(B109="",C109=""),"",IF(AND(X109<>"",Y109<>"",Z109<>"",AA109<>"",AB109="Y"),"YES","no")) | AI109: =IF(AH109="YES",MAX(X109,Y109,Z109,AA109),"") | AJ109: =IF(AND(B109="",C109=""),"",IF(OR(S109="Not interested",S109="Opt-out / do not contact"),"X Declined / suppressed",IF(S109="Bounced / undeliverable","X Bounced — research",IF(AC109<>"","13 Transacting",IF(AH109="YES","12 ACTIVATED",IF(Z109<>"","11 Listing live",IF(Y109<>"","10 Profile complete",IF(X109<>"","9 Approved",IF(W109<>"","8 KYC submitted",IF(V109<>"","7 Registered",IF(T109<>"","5 Interested",IF(R109<>"","4 Responded",IF(O109<>"","2 Contacted","1 Not yet contacted"))))))))))))) | AK109: =IF(AF109<>"",AF109,IF(OR(O109="",R109<>"",LEFT(AJ109,1)="X"),"",IF(Q109<>"","",IF(P109<>"",P109+SETTINGS!$B$4,O109+SETTINGS!$B$3)))) | AL109: =IF(AJ109="","",IF(LEFT(AJ109,1)="X","None — do not contact",IF(AJ109="1 Not yet contacted","Verify route today, then send M1",IF(AND(R109="",Q109<>""),"Sequence complete — no contact before "&TEXT(Q109+SETTINGS!$B$5,"yyyy-mm-dd"),IF(AND(R109="",P109<>""),"Send final note (M4)",IF(R109="","Send follow-up (M2)",IF(AJ109="12 ACTIVATED","7-day check-in; consent & referral soft ask",IF(AJ109="13 Transacting","Repeat-activity support","Onboarding: move to next stage (see playbook §6)")))))))) | AM109: =IF(ISNUMBER(AK109),IF(AK109<=TODAY(),"DUE",""),"") | AN109: =IF(COUNT(O109,P109,Q109,R109,T109,V109,W109,X109,Y109,Z109,AA109,AC109)=0,"",TODAY()-MAX(O109,P109,Q109,R109,T109,V109,W109,X109,Y109,Z109,AA109,AC109)) | AO109: =IF(AJ109="","",IF(AND(T109<>"",U109<>"Active (verified)"),"GST: escalate (no tax advice)",IF(AND(IFERROR(VALUE(LEFT(AJ109,2)),0)>=5,AH109<>"YES",ISNUMBER(AN109),AN109>SETTINGS!$B$14),"STUCK in onboarding","")))
A110: 109 | B110: UPK2-FL-372 | C110: Simone Handcrafted | D110: Fashion & Lifestyle | E110: FL-OCCASION-BRIDAL | F110: Mumbai | G110: A | H110: P0 | I110: stockist-listed | J110: Personal 1:1 email from founder/team to published business email | K110: https://simonehandcrafted.com/ | L110: W2 Expansion | AH110: =IF(AND(B110="",C110=""),"",IF(AND(X110<>"",Y110<>"",Z110<>"",AA110<>"",AB110="Y"),"YES","no")) | AI110: =IF(AH110="YES",MAX(X110,Y110,Z110,AA110),"") | AJ110: =IF(AND(B110="",C110=""),"",IF(OR(S110="Not interested",S110="Opt-out / do not contact"),"X Declined / suppressed",IF(S110="Bounced / undeliverable","X Bounced — research",IF(AC110<>"","13 Transacting",IF(AH110="YES","12 ACTIVATED",IF(Z110<>"","11 Listing live",IF(Y110<>"","10 Profile complete",IF(X110<>"","9 Approved",IF(W110<>"","8 KYC submitted",IF(V110<>"","7 Registered",IF(T110<>"","5 Interested",IF(R110<>"","4 Responded",IF(O110<>"","2 Contacted","1 Not yet contacted"))))))))))))) | AK110: =IF(AF110<>"",AF110,IF(OR(O110="",R110<>"",LEFT(AJ110,1)="X"),"",IF(Q110<>"","",IF(P110<>"",P110+SETTINGS!$B$4,O110+SETTINGS!$B$3)))) | AL110: =IF(AJ110="","",IF(LEFT(AJ110,1)="X","None — do not contact",IF(AJ110="1 Not yet contacted","Verify route today, then send M1",IF(AND(R110="",Q110<>""),"Sequence complete — no contact before "&TEXT(Q110+SETTINGS!$B$5,"yyyy-mm-dd"),IF(AND(R110="",P110<>""),"Send final note (M4)",IF(R110="","Send follow-up (M2)",IF(AJ110="12 ACTIVATED","7-day check-in; consent & referral soft ask",IF(AJ110="13 Transacting","Repeat-activity support","Onboarding: move to next stage (see playbook §6)")))))))) | AM110: =IF(ISNUMBER(AK110),IF(AK110<=TODAY(),"DUE",""),"") | AN110: =IF(COUNT(O110,P110,Q110,R110,T110,V110,W110,X110,Y110,Z110,AA110,AC110)=0,"",TODAY()-MAX(O110,P110,Q110,R110,T110,V110,W110,X110,Y110,Z110,AA110,AC110)) | AO110: =IF(AJ110="","",IF(AND(T110<>"",U110<>"Active (verified)"),"GST: escalate (no tax advice)",IF(AND(IFERROR(VALUE(LEFT(AJ110,2)),0)>=5,AH110<>"YES",ISNUMBER(AN110),AN110>SETTINGS!$B$14),"STUCK in onboarding","")))
A111: 110 | B111: UPK2-FL-184 | C111: Mahima Mahajan | D111: Fashion & Lifestyle | E111: FL-OCCASION-BRIDAL | F111: Delhi NCR | G111: B | H111: P0 | I111: stockist-listed|large catalogue | J111: Personal 1:1 email from founder/team to published business email | K111: https://www.mahimamahajan.in/pages/contact-us | L111: W2 Expansion | AH111: =IF(AND(B111="",C111=""),"",IF(AND(X111<>"",Y111<>"",Z111<>"",AA111<>"",AB111="Y"),"YES","no")) | AI111: =IF(AH111="YES",MAX(X111,Y111,Z111,AA111),"") | AJ111: =IF(AND(B111="",C111=""),"",IF(OR(S111="Not interested",S111="Opt-out / do not contact"),"X Declined / suppressed",IF(S111="Bounced / undeliverable","X Bounced — research",IF(AC111<>"","13 Transacting",IF(AH111="YES","12 ACTIVATED",IF(Z111<>"","11 Listing live",IF(Y111<>"","10 Profile complete",IF(X111<>"","9 Approved",IF(W111<>"","8 KYC submitted",IF(V111<>"","7 Registered",IF(T111<>"","5 Interested",IF(R111<>"","4 Responded",IF(O111<>"","2 Contacted","1 Not yet contacted"))))))))))))) | AK111: =IF(AF111<>"",AF111,IF(OR(O111="",R111<>"",LEFT(AJ111,1)="X"),"",IF(Q111<>"","",IF(P111<>"",P111+SETTINGS!$B$4,O111+SETTINGS!$B$3)))) | AL111: =IF(AJ111="","",IF(LEFT(AJ111,1)="X","None — do not contact",IF(AJ111="1 Not yet contacted","Verify route today, then send M1",IF(AND(R111="",Q111<>""),"Sequence complete — no contact before "&TEXT(Q111+SETTINGS!$B$5,"yyyy-mm-dd"),IF(AND(R111="",P111<>""),"Send final note (M4)",IF(R111="","Send follow-up (M2)",IF(AJ111="12 ACTIVATED","7-day check-in; consent & referral soft ask",IF(AJ111="13 Transacting","Repeat-activity support","Onboarding: move to next stage (see playbook §6)")))))))) | AM111: =IF(ISNUMBER(AK111),IF(AK111<=TODAY(),"DUE",""),"") | AN111: =IF(COUNT(O111,P111,Q111,R111,T111,V111,W111,X111,Y111,Z111,AA111,AC111)=0,"",TODAY()-MAX(O111,P111,Q111,R111,T111,V111,W111,X111,Y111,Z111,AA111,AC111)) | AO111: =IF(AJ111="","",IF(AND(T111<>"",U111<>"Active (verified)"),"GST: escalate (no tax advice)",IF(AND(IFERROR(VALUE(LEFT(AJ111,2)),0)>=5,AH111<>"YES",ISNUMBER(AN111),AN111>SETTINGS!$B$14),"STUCK in onboarding","")))
A112: 111 | B112: UPK2-FL-245 | C112: Sole House | D112: Fashion & Lifestyle | E112: FL-JEWELLERY | F112: Delhi NCR | G112: B | H112: P0 | I112: stockist-listed | J112: Personal 1:1 email from founder/team to published business email | K112: https://solehouse.in/pages/contact | L112: W2 Expansion | AH112: =IF(AND(B112="",C112=""),"",IF(AND(X112<>"",Y112<>"",Z112<>"",AA112<>"",AB112="Y"),"YES","no")) | AI112: =IF(AH112="YES",MAX(X112,Y112,Z112,AA112),"") | AJ112: =IF(AND(B112="",C112=""),"",IF(OR(S112="Not interested",S112="Opt-out / do not contact"),"X Declined / suppressed",IF(S112="Bounced / undeliverable","X Bounced — research",IF(AC112<>"","13 Transacting",IF(AH112="YES","12 ACTIVATED",IF(Z112<>"","11 Listing live",IF(Y112<>"","10 Profile complete",IF(X112<>"","9 Approved",IF(W112<>"","8 KYC submitted",IF(V112<>"","7 Registered",IF(T112<>"","5 Interested",IF(R112<>"","4 Responded",IF(O112<>"","2 Contacted","1 Not yet contacted"))))))))))))) | AK112: =IF(AF112<>"",AF112,IF(OR(O112="",R112<>"",LEFT(AJ112,1)="X"),"",IF(Q112<>"","",IF(P112<>"",P112+SETTINGS!$B$4,O112+SETTINGS!$B$3)))) | AL112: =IF(AJ112="","",IF(LEFT(AJ112,1)="X","None — do not contact",IF(AJ112="1 Not yet contacted","Verify route today, then send M1",IF(AND(R112="",Q112<>""),"Sequence complete — no contact before "&TEXT(Q112+SETTINGS!$B$5,"yyyy-mm-dd"),IF(AND(R112="",P112<>""),"Send final note (M4)",IF(R112="","Send follow-up (M2)",IF(AJ112="12 ACTIVATED","7-day check-in; consent & referral soft ask",IF(AJ112="13 Transacting","Repeat-activity support","Onboarding: move to next stage (see playbook §6)")))))))) | AM112: =IF(ISNUMBER(AK112),IF(AK112<=TODAY(),"DUE",""),"") | AN112: =IF(COUNT(O112,P112,Q112,R112,T112,V112,W112,X112,Y112,Z112,AA112,AC112)=0,"",TODAY()-MAX(O112,P112,Q112,R112,T112,V112,W112,X112,Y112,Z112,AA112,AC112)) | AO112: =IF(AJ112="","",IF(AND(T112<>"",U112<>"Active (verified)"),"GST: escalate (no tax advice)",IF(AND(IFERROR(VALUE(LEFT(AJ112,2)),0)>=5,AH112<>"YES",ISNUMBER(AN112),AN112>SETTINGS!$B$14),"STUCK in onboarding","")))
A113: 112 | B113: UPK2-FL-233 | C113: Moontara | D113: Fashion & Lifestyle | E113: FL-CONTEMPORARY | F113: Jaipur | G113: B | H113: P0 | I113: stockist-listed | J113: Personal 1:1 email from founder/team to published business email | K113: https://www.moontara.in/pages/contact-us | L113: W2 Expansion | AH113: =IF(AND(B113="",C113=""),"",IF(AND(X113<>"",Y113<>"",Z113<>"",AA113<>"",AB113="Y"),"YES","no")) | AI113: =IF(AH113="YES",MAX(X113,Y113,Z113,AA113),"") | AJ113: =IF(AND(B113="",C113=""),"",IF(OR(S113="Not interested",S113="Opt-out / do not contact"),"X Declined / suppressed",IF(S113="Bounced / undeliverable","X Bounced — research",IF(AC113<>"","13 Transacting",IF(AH113="YES","12 ACTIVATED",IF(Z113<>"","11 Listing live",IF(Y113<>"","10 Profile complete",IF(X113<>"","9 Approved",IF(W113<>"","8 KYC submitted",IF(V113<>"","7 Registered",IF(T113<>"","5 Interested",IF(R113<>"","4 Responded",IF(O113<>"","2 Contacted","1 Not yet contacted"))))))))))))) | AK113: =IF(AF113<>"",AF113,IF(OR(O113="",R113<>"",LEFT(AJ113,1)="X"),"",IF(Q113<>"","",IF(P113<>"",P113+SETTINGS!$B$4,O113+SETTINGS!$B$3)))) | AL113: =IF(AJ113="","",IF(LEFT(AJ113,1)="X","None — do not contact",IF(AJ113="1 Not yet contacted","Verify route today, then send M1",IF(AND(R113="",Q113<>""),"Sequence complete — no contact before "&TEXT(Q113+SETTINGS!$B$5,"yyyy-mm-dd"),IF(AND(R113="",P113<>""),"Send final note (M4)",IF(R113="","Send follow-up (M2)",IF(AJ113="12 ACTIVATED","7-day check-in; consent & referral soft ask",IF(AJ113="13 Transacting","Repeat-activity support","Onboarding: move to next stage (see playbook §6)")))))))) | AM113: =IF(ISNUMBER(AK113),IF(AK113<=TODAY(),"DUE",""),"") | AN113: =IF(COUNT(O113,P113,Q113,R113,T113,V113,W113,X113,Y113,Z113,AA113,AC113)=0,"",TODAY()-MAX(O113,P113,Q113,R113,T113,V113,W113,X113,Y113,Z113,AA113,AC113)) | AO113: =IF(AJ113="","",IF(AND(T113<>"",U113<>"Active (verified)"),"GST: escalate (no tax advice)",IF(AND(IFERROR(VALUE(LEFT(AJ113,2)),0)>=5,AH113<>"YES",ISNUMBER(AN113),AN113>SETTINGS!$B$14),"STUCK in onboarding","")))
... A133: 132 | B133: UPK2-FL-266 | C133: Umbar | D133: Fashion & Lifestyle | E133: FL-CONTEMPORARY | F133: Delhi NCR | G133: B | H133: P0 | I133: stockist-listed | J133: Personal 1:1 email from founder/team to published business email | K133: https://www.umbar.com/pages/contact | L133: W2 Expansion | AH133: =IF(AND(B133="",C133=""),"",IF(AND(X133<>"",Y133<>"",Z133<>"",AA133<>"",AB133="Y"),"YES","no")) | AI133: =IF(AH133="YES",MAX(X133,Y133,Z133,AA133),"") | AJ133: =IF(AND(B133="",C133=""),"",IF(OR(S133="Not interested",S133="Opt-out / do not contact"),"X Declined / suppressed",IF(S133="Bounced / undeliverable","X Bounced — research",IF(AC133<>"","13 Transacting",IF(AH133="YES","12 ACTIVATED",IF(Z133<>"","11 Listing live",IF(Y133<>"","10 Profile complete",IF(X133<>"","9 Approved",IF(W133<>"","8 KYC submitted",IF(V133<>"","7 Registered",IF(T133<>"","5 Interested",IF(R133<>"","4 Responded",IF(O133<>"","2 Contacted","1 Not yet contacted"))))))))))))) | AK133: =IF(AF133<>"",AF133,IF(OR(O133="",R133<>"",LEFT(AJ133,1)="X"),"",IF(Q133<>"","",IF(P133<>"",P133+SETTINGS!$B$4,O133+SETTINGS!$B$3)))) | AL133: =IF(AJ133="","",IF(LEFT(AJ133,1)="X","None — do not contact",IF(AJ133="1 Not yet contacted","Verify route today, then send M1",IF(AND(R133="",Q133<>""),"Sequence complete — no contact before "&TEXT(Q133+SETTINGS!$B$5,"yyyy-mm-dd"),IF(AND(R133="",P133<>""),"Send final note (M4)",IF(R133="","Send follow-up (M2)",IF(AJ133="12 ACTIVATED","7-day check-in; consent & referral soft ask",IF(AJ133="13 Transacting","Repeat-activity support","Onboarding: move to next stage (see playbook §6)")))))))) | AM133: =IF(ISNUMBER(AK133),IF(AK133<=TODAY(),"DUE",""),"") | AN133: =IF(COUNT(O133,P133,Q133,R133,T133,V133,W133,X133,Y133,Z133,AA133,AC133)=0,"",TODAY()-MAX(O133,P133,Q133,R133,T133,V133,W133,X133,Y133,Z133,AA133,AC133)) | AO133: =IF(AJ133="","",IF(AND(T133<>"",U133<>"Active (verified)"),"GST: escalate (no tax advice)",IF(AND(IFERROR(VALUE(LEFT(AJ133,2)),0)>=5,AH133<>"YES",ISNUMBER(AN133),AN133>SETTINGS!$B$14),"STUCK in onboarding","")))
...

Sheet CAMPAIGNS
A1: Campaign | B1: Purpose | C1: Audience | D1: Planned contacts | E1: Channel(s) | F1: Gate(s) required (BLOCKERS IDs) | G1: Planned start | H1: Owner | I1: Status
A2: W-1 Journey test (friendly) | B2: Prove registration → KYC → approval → profile → listing → payout works, before any cold contact | C2: 5–10 professionals from the founder's own network, across product and service categories | D2: 10 | E2: Warm, in person / call | F2: G2, G6, G7 | H2: Founder | I2: Planned
A3: X Legacy accounts (dormant) | B3: NOT an acquisition campaign. Founder: legacy sellers registered 3–5 years ago, none active. Only the legally required terms-migration notice; anyone who replies is handled as Inbound | C3: Dormant legacy registrations | E3: Service notice only (legal wording) | F3: G9, G3 | H3: Founder + Legal | I3: Not an acquisition campaign
A4: W0 Pilot | B4: Learn message/CTA; first cold-to-activated journeys | C4: Golden 300 v2 ranks 1–25 (Delhi NCR, Mumbai) | D4: 25 | E4: Email; Instagram DM | F4: G1–G8 | H4: Founder | I4: Planned
A5: W1 Founding cohort | B5: First pods in 4 anchor cities | C5: Ranks 26–100 | D5: 75 | E5: Email; Instagram DM; LinkedIn (practices) | F5: W0 exit + G1–G10 | H5: Outreach lead | I5: Planned
A6: W2 Expansion | B6: Category balance; complete pods | C6: Ranks 101–300 | D6: 200 | E6: Proven channels only | F6: W1 exit | H6: Outreach lead | I6: Planned
A7: W3 Reserve & enrichment | B7: Fill pod gaps (Beauty, Content) via enriched routes | C7: Enrichment queue + founding reserve | E7: Email; Instagram DM | F7: W2 exit | H7: Outreach lead | I7: Planned
A8: W4 Launch window | B8: Premium names by warm introduction; opted-in launch updates | C8: P3 premium (warm only); opted-in professionals | E8: Warm introduction; AiSensy (opted-in only) | F8: Complete pods; consent register | H8: Founder | I8: Planned
A9: Inbound | B9: Professionals who approach Uepaki | C9: — | E9: — | F9: — | H9: Onboarding lead | I9: Ongoing
A10: Peer introduction | B10: Unpaid, consent-based introductions | C10: Peers named by activated professionals | E10: 1:1 | F10: Introducer consent | H10: Outreach lead | I10: From W1

Sheet CAMPAIGN_DASHBOARD
A1: Campaign dashboard (live from PROSPECTS)
A2: Rules apply only after the contact minimum in SETTINGS. "Too early" means do not judge yet.
A4: Campaign | B4: Prospects | C4: Contacted | D4: Bounced | E4: Delivered | F4: Responded | G4: Positive | H4: Declined/opt-out | I4: Registered | J4: Approved | K4: Activated | L4: Transacting | M4: Reply rate | N4: Interest rate (of responded) | O4: Activation per contacted | P4: Bounce rate | Q4: Opt-out rate | R4: Rule status
