Workbook

Sheet README
A1: Uepaki — First 25 Acquisition List (Wave 0: controlled pilot)
A3: Purpose: a controlled pilot to learn which message, CTA and route work — NOT a registration push. Success = learning + first activated founding professionals.
A4: Composition: 25 contact-ready P0 professionals in Delhi NCR and Mumbai across all six categories, 2–6 per category, spread across 17 segments; tier mix weighted to independents (A/B); no tier D/E.
A5: Sequencing: send in 5 daily batches of 5 (one per category where possible), founder-signed, each message individually written from the "Why selected" and "Lead angle" columns. Follow-up: one value-adding follow-up on day 4–5, one final note on day 10–12, then stop.
A6: Experiment E01: alternate rows within each category receive message M-A (craft/identity-led) or M-B (business-infrastructure-led). Keep everything else constant. Read the result only as directional (n≈12 per arm).
A7: Pre-conditions before sending: (1) founder decides what founding-programme wording may be used 1:1 (see OS report §2 decision FP-OUT); (2) a working registration path and the ₹1 + GST disclosure; (3) one person owns the reply inbox within 24h.
A9: Source: UEPAKI_PRELAUNCH_PROFESSIONAL_DATABASE_V2.xlsx, sheet 01_MASTER_V2 (V2.1 canonical master, research date 2026-10-08, 3,584 records). The source file is not modified.
A10: This list holds NO phone numbers, emails or WhatsApp links. Look up the verified business route in the master by Prospect ID at the moment of outreach, and re-check it is still published.
A11: CONTACTABLE ≠ CONSENT. No record has marketing or WhatsApp opt-in. First contact is 1:1, human-written, professional, and stops on the first "no". Bulk WhatsApp/AiSensy only after a recorded opt-in.
A12: Acq Priority (OS) is the operating priority defined in UEPAKI_SELLER_ACQUISITION_OPERATING_SYSTEM (§6). It replaces the inflated DB priority for outreach sequencing; the DB priority is shown alongside for reference.
A13: Readiness (ARS) = Acquisition Readiness Score, 0–100: commercial activity 20, recency 15, join likelihood 15, contactability 15, seeking clients 10, marketplace affinity 10, quality 10, category fit 5; minus penalties for low evidence, open verification flags and unknown city. Fame, follower count and tier are NOT inputs.
A14: Founding Candidate Score = 0.5 × ARS + 0.3 × Founding Potential (DB) + 0.2 × Network Potential (DB) (+2 if evidence High, +2 if activity ≤3 months).
... A16: Tracker columns (green headers) are for the outreach team. Stage uses the funnel in UEPAKI_ACQUISITION_FUNNEL_AND_KPI_FRAMEWORK.md.

Sheet LIST
A1: Rank | B1: Wave | C1: Prospect ID | D1: Name | E1: Category | F1: Segment | G1: Ecosystem Pod | H1: Subcategory | I1: City | J1: Tier | K1: Business Type | L1: Acq Priority (OS) | M1: Source Priority (DB) | N1: Readiness (ARS) | O1: ARS pctl in category | P1: Founding Candidate Score | Q1: Founding Potential (DB) | R1: Network Potential (DB) | S1: Contact Class | T1: Recommended First Channel | U1: Public route reference (no personal data) | V1: Recent activity (DB) | W1: Commercial signal (DB) | X1: Platform association (DB) | Y1: Why selected | Z1: Lead angle | AA1: Likely objection (DB) | AB1: Category objection themes | AC1: Experiment cell | AD1: Owner | AE1: Stage | AF1: Date first contact | AG1: Channel used | AH1: Message variant sent | AI1: Follow-up 1 date | AJ1: Follow-up 2 date | AK1: Replied (Y/N) | AL1: Reply date | AM1: Outcome | AN1: Info requested (Y/N) | AO1: Registration started | AP1: Registration completed | AQ1: Approved (KYC) | AR1: Profile completed | AS1: First listing date | AT1: Activated (Y/N) | AU1: First enquiry/order/booking date | AV1: WhatsApp opt-in recorded (Y/N, date, method) | AW1: Do-not-contact (Y/N) | AX1: Notes
A2: 1 | B2: Wave 0 — Controlled pilot | C2: UPK2-BM-163 | D2: Arun Mehandi | E2: Beauty & Makeup | F2: BM-MEHENDI | G2: Wedding & Occasion | H2: Mehendi Artist | I2: Mumbai | J2: C — Strong Mid-tier | K2: Independent mehendi artist | L2: P0 | M2: P1 | N2: 86.5 | O2: 100 | P2: 80.1 | Q2: 88 | R2: 52 | S2: C1-DIRECT-VERIFIED | T2: Personal 1:1 email from founder/team to published business email | U2: https://arunmehandi.com/ | V2: 2026-03 — latest client review on WedMeGood profile | W2: 210 client reviews on WedMeGood (rating 4.9); starting price Rs 4,000; | X2: WedMeGood (Vendor profile (Mehendi Artists, Handpicked membership, on WMG 8 years)) | Y2: Readiness 86 (top 1% in category) | Commercial: 210 client reviews on WedMeGood (rating 4.9); starting price Rs 4,000; | Active: 2026-03 — latest client review on WedMeGood profile | Z2: Lead with a specific design style. Ask how bookings arrive today. Service/booking availability at launch is being confirmed (EV-09). | AA2: Bookings already come via WedMeGood, Instagram and WhatsApp referrals | AB2: Bookings already via wedding portals/Instagram; off-platform client contact (SP-4a open); peak-season time | AC2: E01-M-A Craft-led
A3: 2 | B3: Wave 0 — Controlled pilot | C3: UPK2-BM-178 | D3: Himani Bhandula Makeup Artist | E3: Beauty & Makeup | F3: BM-INDEPENDENT-MUA | G3: Wedding & Occasion | H3: Bridal & party makeup artist | I3: Delhi NCR | J3: B — Established Independent | K3: Independent makeup artist | L3: P0 | M3: P0 | N3: 82.3 | O3: 100 | P3: 71.2 | Q3: 77 | R3: 35 | S3: C1-DIRECT-VERIFIED | T3: 1:1 message via own-website contact form | U3: https://himanibhandula.com/contact/ | V3: 2026-09 — latest client review on WedMeGood profile | W3: 40 client reviews on WedMeGood (rating 5); 8 of latest 10 shown reviews dated 2025–26; starting price ₹18,000 per function listed | X3: WedMeGood (Vendor profile with client reviews); Own website (First-party site) | Y3: Readiness 82 (top 1% in category) | Commercial: 40 client reviews on WedMeGood (rating 5); 8 of latest 10 shown reviews dated 2025–26; st… | Active: 2026-09 — latest client review on WedMeGood profile | Independent/emerging tier — fame not a factor | Z3: Lead with their bridal portfolio. Ask how bookings arrive today. Be explicit that service/booking availability at launch is being confirmed (EV-09). | AA3: Bookings already arrive via WedMeGood/Instagram; may see limited need for another platform | AB3: Bookings already via wedding portals/Instagram; off-platform client contact (SP-4a open); peak-season time | AC3: E01-M-B Business-infrastructure-led
A4: 3 | B4: Wave 0 — Controlled pilot | C4: UPK2-BM-208 | D4: Roopali Talwar Makeup Artist | E4: Beauty & Makeup | F4: BM-INDEPENDENT-MUA | G4: Wedding & Occasion | H4: Bridal & party makeup artist | I4: Delhi NCR | J4: B — Established Independent | K4: Independent makeup artist | L4: P0 | M4: P0 | N4: 79.8 | O4: 99 | P4: 71 | Q4: 77 | R4: 40 | S4: C1-DIRECT-VERIFIED | T4: 1:1 message via own-website contact form | U4: https://roopalitalwar.com/ | V4: 2026-01 — latest client review on WedMeGood profile | W4: 62 client reviews on WedMeGood (rating 5); 2 of latest 10 shown reviews dated 2025–26; starting price ₹45,000 per function listed | X4: WedMeGood (Vendor profile with client reviews); Own website (First-party site) | Y4: Readiness 80 (top 2% in category) | Commercial: 62 client reviews on WedMeGood (rating 5); 2 of latest 10 shown reviews dated 2025–26; st… | Active: 2026-01 — latest client review on WedMeGood profile | Independent/emerging tier — fame not a factor | Z4: Lead with their bridal portfolio. Ask how bookings arrive today. Be explicit that service/booking availability at launch is being confirmed (EV-09). | AA4: Bookings already arrive via WedMeGood/Instagram; may see limited need for another platform | AB4: Bookings already via wedding portals/Instagram; off-platform client contact (SP-4a open); peak-season time | AC4: E01-M-A Craft-led
A5: 4 | B5: Wave 0 — Controlled pilot | C5: UPK2-BM-004 | D5: MG Makeovers | E5: Beauty & Makeup | F5: BM-STUDIO | G5: Wedding & Occasion | H5: Bridal Makeup Artist & Studio Salon | I5: Delhi NCR | J5: C — Strong Mid-tier | K5: Studio salon | L5: P0 | M5: P1 | N5: 76 | O5: 98 | P5: 67.2 | Q5: 74 | R5: 35 | S5: C1-DIRECT-VERIFIED | T5: Personal 1:1 email from founder/team to published business email | U5: https://www.mgmakeovers.com/contact-us | V5: 2026 — site copyright 2026 | W5: Gurgaon studio; HD ₹20,000 / airbrush ₹25,000 listed; online booking with WhatsApp confirmation; nail/lash studio | X5: Own website (First-party site) | Y5: Readiness 76 (top 3% in category) | Commercial: Gurgaon studio; HD ₹20,000 / airbrush ₹25,000 listed; online booking with WhatsApp confir… | Active: 2026 — site copyright 2026 | Z5: Lead with the studio's body of work and team. Ask how bookings arrive today. Service/booking availability at launch is being confirmed (EV-09). | AA5: Salon operations focus | AB5: Bookings already via wedding portals/Instagram; off-platform client contact (SP-4a open); peak-season time | AC5: E01-M-B Business-infrastructure-led
A6: 5 | B6: Wave 0 — Controlled pilot | C6: UPK2-BM-394 | D6: Satish Mehandi Art | E6: Beauty & Makeup | F6: BM-MEHENDI | G6: Wedding & Occasion | H6: Mehendi / henna artist | I6: Delhi NCR | J6: C — Strong Mid-tier | K6: Independent mehendi artist / team | L6: P0 | M6: P1 | N6: 68.7 | O6: 72 | P6: 67 | Q6: 72 | R6: 55 | S6: C3-PRO-SOCIAL | T6: 1:1 Instagram DM from Uepaki professional account | U6: https://satishmehandiart.in/ | V6: 2025-10 — latest client review on WedMeGood profile | W6: 150 client reviews on WedMeGood (rating 4.7); 1 of latest 10 shown reviews dated 2025–26; starting price ₹3100 onwards per package/function listed | X6: WedMeGood (Vendor profile with client reviews); Own website (First-party site) | Y6: Readiness 69 (top 29% in category) | Commercial: 150 client reviews on WedMeGood (rating 4.7); 1 of latest 10 shown reviews dated 2025–26;… | Active: 2025-10 — latest client review on WedMeGood profile | Z6: Lead with a specific design style. Ask how bookings arrive today. Service/booking availability at launch is being confirmed (EV-09). | AA6: Bookings already arrive via WedMeGood/Instagram; may see limited need for another platform | AB6: Bookings already via wedding portals/Instagram; off-platform client contact (SP-4a open); peak-season time | AC6: E01-M-A Craft-led
A7: 6 | B7: Wave 0 — Controlled pilot | C7: UPK2-BM-014 | D7: Liberte by Hiral | E7: Beauty & Makeup | F7: BM-INDEPENDENT-MUA | G7: Wedding & Occasion | H7: Minimal/Cruelty-free Bridal MUA | I7: Mumbai | J7: B — Established Independent | K7: Independent professional | L7: P0 | M7: P0 | N7: 74.1 | O7: 96 | P7: 64.4 | Q7: 71 | R7: 30 | S7: C1-DIRECT-VERIFIED | T7: Personal 1:1 email from founder/team to published business email | U7: https://shahhirral.wixsite.com/libertebyhiral | V7: 2026-09 — WeddingSutra vendor profile last modified (page metadata) | W7: Cruelty-free bridal makeup (per WS bio) | X7: WeddingSutra (Vendor showcase profile (Makeup Artists)) | Y7: Readiness 74 (top 5% in category) | Commercial: Cruelty-free bridal makeup (per WS bio) | Active: 2026-09 — WeddingSutra vendor profile last modified (page metadata) | Independent/emerging tier — fame not a factor | Z7: Lead with their bridal portfolio. Ask how bookings arrive today. Be explicit that service/booking availability at launch is being confirmed (EV-09). | AA7: Bookings already flow via Instagram/WhatsApp and wedding portals | AB7: Bookings already via wedding portals/Instagram; off-platform client contact (SP-4a open); peak-season time | AC7: E01-M-B Business-infrastructure-led
A8: 7 | B8: Wave 0 — Controlled pilot | C8: UPK2-FL-163 | D8: Bhumika Sharma | E8: Fashion & Lifestyle | F8: FL-OCCASION-BRIDAL | G8: Wedding & Occasion | H8: Occasion & bridal wear (lehengas, sarees, festive sets) | I8: Delhi NCR | J8: B — Established Independent | K8: Label/brand (D2C store) | L8: P0 | M8: P0 | N8: 87 | O8: 100 | P8: 79.3 | Q8: 86 | R8: 50 | S8: C1-DIRECT-VERIFIED | T8: Personal 1:1 email from founder/team to published business email | U8: https://www.bhumikasharma.in/pages/contact | V8: 2026-09 — newest product published on own Shopify store (Nitibha Kaul in Zarinah Lehenga) per products.json | W8: Own online store live with 250+ products listed; stocked by multi-designer retailer(s): Aza Fashions, Ogaan | X8: Aza Fashions (stocked designer (designer index)); Ogaan (stocked designer (designer index)) | Y8: Readiness 87 (top 1% in category) | Commercial: Own online store live with 250+ products listed; stocked by multi-designer retailer(s): A… | Active: 2026-09 — newest product published on own Shopify store (Nitibha Kaul… | Marketplace-familiar: Aza Fashions); Ogaan) | Independent/emerging tier — fame not a factor | Z8: Lead with the label's craft and name. Ask how made-to-order/bridal enquiries reach them today. Position Uepaki as an additional professional channel, not a replacement for stockists. | AA8: Already has own D2C store and established multi-designer stockists | AB8: Own D2C store/stockists already; "who else is on it?"; commission vs stockist margin | AC8: E01-M-A Craft-led
A9: 8 | B9: Wave 0 — Controlled pilot | C9: UPK2-FL-164 | D9: Devnaagri | E9: Fashion & Lifestyle | F9: FL-OCCASION-BRIDAL | G9: Wedding & Occasion | H9: Occasion & bridal wear (lehengas, sarees, festive sets) | I9: Delhi NCR | J9: B — Established Independent | K9: Label/brand (D2C store) | L9: P0 | M9: P0 | N9: 87 | O9: 100 | P9: 79.3 | Q9: 86 | R9: 50 | S9: C1-DIRECT-VERIFIED | T9: Personal 1:1 email from founder/team to published business email | U9: https://www.devnaagri.com/pages/contact-us | V9: 2026-10 — newest product published on own Shopify store (Sara Ali Khan in Inaya - Blush Pink Farshi Salwar Set) per products.json | W9: Own online store live with 250+ products listed; stocked by multi-designer retailer(s): Aza Fashions, Ogaan | X9: Aza Fashions (stocked designer (designer index)); Ogaan (stocked designer (designer index)) | Y9: Readiness 87 (top 1% in category) | Commercial: Own online store live with 250+ products listed; stocked by multi-designer retailer(s): A… | Active: 2026-10 — newest product published on own Shopify store (Sara Ali Kha… | Marketplace-familiar: Aza Fashions); Ogaan) | Independent/emerging tier — fame not a factor | Z9: Lead with the label's craft and name. Ask how made-to-order/bridal enquiries reach them today. Position Uepaki as an additional professional channel, not a replacement for stockists. | AA9: Already has own D2C store and established multi-designer stockists | AB9: Own D2C store/stockists already; "who else is on it?"; commission vs stockist margin | AC9: E01-M-B Business-infrastructure-led
A10: 9 | B10: Wave 0 — Controlled pilot | C10: UPK2-FL-165 | D10: Miss Jo | E10: Fashion & Lifestyle | F10: FL-JEWELLERY | G10: Wedding & Occasion | H10: Designer jewellery | I10: Delhi NCR | J10: B — Established Independent | K10: Label/brand (D2C store) | L10: P0 | M10: P0 | N10: 87 | O10: 100 | P10: 79.3 | Q10: 86 | R10: 50 | S10: C1-DIRECT-VERIFIED | T10: Personal 1:1 email from founder/team to published business email | U10: https://missjo.com/pages/contact | V10: 2026-08 — newest product published on own Shopify store (Oval Shaped Solitaire Wedding Bands) per products.json | W10: Own online store live with 250+ products listed; stocked by multi-designer retailer(s): Aza Fashions, Ogaan | X10: Aza Fashions (stocked designer (designer index)); Ogaan (stocked designer (designer index)) | Y10: Readiness 87 (top 1% in category) | Commercial: Own online store live with 250+ products listed; stocked by multi-designer retailer(s): A… | Active: 2026-08 — newest product published on own Shopify store (Oval Shaped… | Marketplace-familiar: Aza Fashions); Ogaan) | Independent/emerging tier — fame not a factor | Z10: Lead with a specific collection. Position as an additional channel under the label's own name. No sales promises. | AA10: Already has own D2C store and established multi-designer stockists | AB10: Own D2C store/stockists already; "who else is on it?"; commission vs stockist margin | AC10: E01-M-A Craft-led
A11: 10 | B11: Wave 0 — Controlled pilot | C11: UPK2-FL-167 | D11: The Leather Garden | E11: Fashion & Lifestyle | F11: FL-ACCESSORIES | G11: Brand & Everyday Style | H11: Designer bags & accessories | I11: Delhi NCR | J11: B — Established Independent | K11: Label/brand (D2C store) | L11: P0 | M11: P0 | N11: 87 | O11: 100 | P11: 79.3 | Q11: 86 | R11: 50 | S11: C1-DIRECT-VERIFIED | T11: Personal 1:1 email from founder/team to published business email | U11: https://theleathergarden.com/collections/notebook | V11: 2026-09 — newest product published on own Shopify store (Mini Holly) per products.json | W11: Own online store live with 250+ products listed; stocked by multi-designer retailer(s): Aza Fashions, Ogaan | X11: Aza Fashions (stocked designer (designer index)); Ogaan (stocked designer (designer index)) | Y11: Readiness 87 (top 1% in category) | Commercial: Own online store live with 250+ products listed; stocked by multi-designer retailer(s): A… | Active: 2026-09 — newest product published on own Shopify store (Mini Holly)… | Marketplace-familiar: Aza Fashions); Ogaan) | Independent/emerging tier — fame not a factor | Z11: Lead with a specific product line. Position as an additional channel under the label's own name. | AA11: Already has own D2C store and established multi-designer stockists | AB11: Own D2C store/stockists already; "who else is on it?"; commission vs stockist margin | AC11: E01-M-B Business-infrastructure-led
A12: 11 | B12: Wave 0 — Controlled pilot | C12: UPK2-FL-173 | D12: Kamaali Couture | E12: Fashion & Lifestyle | F12: FL-CONTEMPORARY | G12: Brand & Everyday Style | H12: Contemporary ready-to-wear / festive pret | I12: Delhi NCR | J12: B — Established Independent | K12: Label/brand (D2C store) | L12: P0 | M12: P0 | N12: 86 | O12: 99 | P12: 78.5 | Q12: 85 | R12: 50 | S12: C1-DIRECT-VERIFIED | T12: Personal 1:1 email from founder/team to published business email | U12: https://kamaali.in/pages/contact-us-1 | V12: 2026-09 — newest product published on own Shopify store (Liela) per products.json | W12: Own online store live with 231 products listed; stocked by multi-designer retailer(s): Aza Fashions, Ogaan | X12: Aza Fashions (stocked designer (designer index)); Ogaan (stocked designer (designer index)) | Y12: Readiness 86 (top 2% in category) | Commercial: Own online store live with 231 products listed; stocked by multi-designer retailer(s): Az… | Active: 2026-09 — newest product published on own Shopify store (Liela) per p… | Marketplace-familiar: Aza Fashions); Ogaan) | Independent/emerging tier — fame not a factor | Z12: Lead with the label's own range and identity. Position as an additional channel next to own store and stockists. No sales or reach promises. | AA12: Already has own D2C store and established multi-designer stockists | AB12: Own D2C store/stockists already; "who else is on it?"; commission vs stockist margin | AC12: E01-M-A Craft-led
A13: 12 | B13: Wave 0 — Controlled pilot | C13: UPK2-SD-305 | D13: Emanate Home | E13: Space & Design | F13: SD-PRODUCT-MAKER | G13: Home & Space | H13: Luxury lighting & bespoke home accessories | I13: Delhi NCR | J13: C — Strong Mid-tier | K13: Lighting brand | L13: P0 | M13: P1 | N13: 71.5 | O13: 78 | P13: 70.8 | Q13: 77 | R13: 60 | S13: C1-DIRECT-VERIFIED | T13: Personal 1:1 email from founder/team to published business email | U13: https://www.emanatehome.com/ | V13: 2026-10 — listed as exhibitor at India Design ID Mumbai 2026 (indiadesignid.com) | W13: Exhibitor at India Design ID (2022, 2026) | X13: India Design ID (exhibitor) | Y13: Readiness 72 (top 23% in category) | Commercial: Exhibitor at India Design ID (2022, 2026) | Active: 2026-10 — listed as exhibitor at India Design ID Mumbai 2026 (indiade… | Z13: Lead with a specific piece. Products and commissions under the maker's own name; link to studios in the Home & Space pod. | AA13: Already sells via own site/showroom and trade fairs. | AB13: Work comes via referrals; project-based work fit; profile upkeep effort | AC13: E01-M-A Craft-led
... A19: 18 | B19: Wave 0 — Controlled pilot | C19: UPK2-LM-223 | D19: Bombay Paparazzi | E19: Lens & Motion | F19: LM-WEDDING | G19: Wedding & Occasion | H19: Wedding photography & filmmaking studio | I19: Mumbai | J19: B — Established Independent | K19: Studio / production house | L19: P0 | M19: P0 | N19: 80.6 | O19: 98 | P19: 69.3 | Q19: 78 | R19: 28 | S19: C1-DIRECT-VERIFIED | T19: Personal 1:1 email from founder/team to published business email | U19: https://bombaypaparazzi.com/ | V19: 2026-07 — latest client review on WedMeGood profile (wedmegood.com) | W19: 52 client reviews on WedMeGood (rating 5); Photo + Video packages starting ₹75,000 | X19: WedMeGood (Vendor listing with client reviews) | Y19: Readiness 81 (top 3% in category) | Commercial: 52 client reviews on WedMeGood (rating 5); Photo + Video packages starting ₹75,000 | Active: 2026-07 — latest client review on WedMeGood profile (wedmegood.com) | Independent/emerging tier — fame not a factor | Z19: Lead with a specific film or series. Photographers sit at the centre of the wedding ecosystem — invite as a founding peer of designers, MUAs and planners. | AA19: Enquiries already come via WedMeGood, own website and Instagram | AB19: Leads via referrals/portals; off-platform contact; time to maintain another profile | AC19: E01-M-B Business-infrastructure-led
A20: 19 | B20: Wave 0 — Controlled pilot | C20: UPK2-LM-238 | D20: North Light Studio | E20: Lens & Motion | F20: LM-ARCH-INTERIOR | G20: Home & Space | H20: Commercial photography & video (food, product, hospitality, architecture) | I20: Mumbai | J20: B — Established Independent | K20: Micro studio (2-10) | L20: P0 | M20: P0 | N20: 75.2 | O20: 77 | P20: 68.7 | Q20: 77 | R20: 40 | S20: C1-DIRECT-VERIFIED | T20: Personal 1:1 email from founder/team to published business email | U20: https://www.northlightstudio.in/ | V20: 2026-09 — photo credit on The Architects Diary project feature (https://thearchitectsdiary.com/arched-abode-builds-a-soft-architectural-rhy… | W20: Commissioned project photography credited by design publications; enquiry route on own site | Y20: Readiness 75 (top 24% in category) | Commercial: Commissioned project photography credited by design publications; enquiry route on own si… | Active: 2026-09 — photo credit on The Architects Diary project feature (https… | Independent/emerging tier — fame not a factor | Z20: Lead with a specific project they documented. Link to the Home & Space pod (studios and makers). | AA20: Work is commission/referral-driven through architect networks; may not see need for a marketplace | AB20: Leads via referrals/portals; off-platform contact; time to maintain another profile | AC20: E01-M-A Craft-led
A21: 20 | B21: Wave 0 — Controlled pilot | C21: UPK2-LM-031 | D21: Digital Studio | E21: Lens & Motion | F21: LM-COMMERCIAL-FASHION | G21: Brand & Everyday Style | H21: Product photography & industrial/corporate video production | I21: Mumbai | J21: B — Established Independent | K21: Photo/video production studio | L21: P0 | M21: P1 | N21: 73.5 | O21: 72 | P21: 65.6 | Q21: 73 | R21: 35 | S21: C1-DIRECT-VERIFIED | T21: Personal 1:1 email from founder/team to published business email | U21: https://www.digitalstudio.in/ | V21: 2026-10 — site live with service pages (digitalstudio.in) | W21: Own website advertises paid product photography & industrial/corporate video production services with enquiry routes | Y21: Readiness 74 (top 29% in category) | Commercial: Own website advertises paid product photography & industrial/corporate video production s… | Active: 2026-10 — site live with service pages (digitalstudio.in) | Independent/emerging tier — fame not a factor | Z21: Lead with product/fashion work. Link to labels in the Brand & Everyday Style pod. | AA21: Leads already come via own site/Instagram | AB21: Leads via referrals/portals; off-platform contact; time to maintain another profile | AC21: E01-M-B Business-infrastructure-led
A22: 21 | B22: Wave 0 — Controlled pilot | C22: UPK2-CM-046 | D22: Amol Soni | E22: Content & Media | F22: CM-EMCEE-HOST | G22: Wedding & Occasion | H22: Wedding & event emcee / anchor | I22: Mumbai | J22: A — Emerging / High-potential | K22: Independent professional | L22: P0 | M22: P0 | N22: 74 | O22: 98 | P22: 61.8 | Q22: 66 | R22: 25 | S22: C1-DIRECT-VERIFIED | T22: Personal 1:1 email from founder/team to published business email | U22: https://www.entertaineramolsoni.com/ | V22: 2026-08 — WeddingSutra vendor profile updated; carries WeddingSutra Favorites 2026 badge | W22: Listed by WeddingSutra as a wedding emcee serving Mumbai | X22: WeddingSutra (vendor showcase profile (Emcees)) | Y22: Readiness 74 (top 3% in category) | Commercial: Listed by WeddingSutra as a wedding emcee serving Mumbai | Active: 2026-08 — WeddingSutra vendor profile updated; carries WeddingSutra F… | Independent/emerging tier — fame not a factor | Z22: Lead with the event formats they host. Services as a professional; clients, not followers. | AA22: Gets bookings via Instagram and wedding marketplaces already; may see another profile as low priority. | AB22: Work via agencies/creator platforms; wants proof brands/clients are present | AC22: E01-M-A Craft-led
A23: 22 | B23: Wave 0 — Controlled pilot | C23: UPK2-CM-016 | D23: Sirimiri – The Lifestyle Blogazine | E23: Content & Media | F23: CM-BLOGGER-WRITER | G23: Brand & Everyday Style | H23: Lifestyle blogger, writer, author | I23: Mumbai | J23: B — Established Independent | K23: Independent creator/blog | L23: P0 | M23: P0 | N23: 70.8 | O23: 88 | P23: 59.3 | Q23: 63 | R23: 25 | S23: C1-DIRECT-VERIFIED | T23: 1:1 message via own-website contact form | U23: https://sirimiri.in/ | V23: 2026 — homepage references 2026 | W23: Has a 'sponsored post' category and book reviews; About: Mumbai-based blogger, writer, author | X23: Feedspot (Listed in Indian lifestyle blogs) | Y23: Readiness 71 (top 13% in category) | Commercial: Has a 'sponsored post' category and book reviews; About: Mumbai-based blogger, writer, au… | Active: 2026 — homepage references 2026 | Independent/emerging tier — fame not a factor | Z23: Lead with their writing/beat. Content work as a professional service for brands; clients, not audience. | AA23: Works through agencies/creator platforms; wants evidence brands are on the platform. | AB23: Work via agencies/creator platforms; wants proof brands/clients are present | AC23: E01-M-B Business-infrastructure-led
A24: 23 | B24: Wave 0 — Controlled pilot | C24: UPK2-CM-050 | D24: Kunal Jessani | E24: Content & Media | F24: CM-EMCEE-HOST | G24: Wedding & Occasion | H24: Wedding & event emcee / anchor | I24: Mumbai | J24: A — Emerging / High-potential | K24: Independent professional | L24: P0 | M24: P0 | N24: 73.2 | O24: 96 | P24: 60.8 | Q24: 64 | R24: 25 | S24: C1-DIRECT-VERIFIED | T24: Personal 1:1 email from founder/team to published business email | U24: https://kunaljessani.com/connect-with-us/ | V24: 2026-06 — WeddingSutra vendor profile updated | W24: Listed by WeddingSutra as a wedding emcee serving Mumbai | X24: WeddingSutra (vendor showcase profile (Emcees)) | Y24: Readiness 73 (top 5% in category) | Commercial: Listed by WeddingSutra as a wedding emcee serving Mumbai | Active: 2026-06 — WeddingSutra vendor profile updated | Independent/emerging tier — fame not a factor | Z24: Lead with the event formats they host. Services as a professional; clients, not followers. | AA24: Gets bookings via Instagram and wedding marketplaces already; may see another profile as low priority. | AB24: Work via agencies/creator platforms; wants proof brands/clients are present | AC24: E01-M-A Craft-led
A25: 24 | B25: Wave 0 — Controlled pilot | C25: UPK2-DV-003 | D25: Ink n Bliss | E25: Digital & Visual Arts | F25: DV-CALLIGRAPHY-STATIONERY | G25: Wedding & Occasion | H25: Calligraphy & engraving studio (weddings, corporate) | I25: Mumbai | J25: B — Established Independent | K25: Calligraphy studio | L25: P0 | M25: P0 | N25: 77.9 | O25: 98 | P25: 67.8 | Q25: 76 | R25: 30 | S25: C1-DIRECT-VERIFIED | T25: Personal 1:1 email from founder/team to published business email | U25: https://www.inknbliss.com/contact | V25: 2026 — site references 2026 | W25: Custom calligraphy for weddings & corporates; has collaborations page | X25: Nibtique (Directory listing) | Y25: Readiness 78 (top 3% in category) | Commercial: Custom calligraphy for weddings & corporates; has collaborations page | Active: 2026 — site references 2026 | Independent/emerging tier — fame not a factor | Z25: Lead with a specific commission (stationery/engraving). Artists who sell both work and commissioned services. | AA25: Event-booking business may already be booked via Instagram | AB25: Commission pricing control; IP of artwork; price pressure | AC25: E01-M-A Craft-led
A26: 25 | B26: Wave 0 — Controlled pilot | C26: UPK2-DV-037 | D26: CRAFX Studio | E26: Digital & Visual Arts | F26: DV-DESIGN-STUDIO | G26: Brand & Everyday Style | H26: Branding, packaging, motion & 3D design agency | I26: Mumbai | J26: B — Established Independent | K26: Independent branding & design agency | L26: P0 | M26: P1 | N26: 75 | O26: 91 | P26: 66 | Q26: 75 | R26: 30 | S26: C1-DIRECT-VERIFIED | T26: Personal 1:1 email from founder/team to published business email | U26: https://www.crafxstudio.com/ | V26: 2026 — site ©2026 | W26: 500+ projects across 12+ countries (per own profile) | X26: Dribbble (profile) | Y26: Readiness 75 (top 10% in category) | Commercial: 500+ projects across 12+ countries (per own profile) | Active: 2026 — site ©2026 | Independent/emerging tier — fame not a factor | Z26: Lead with a specific identity/packaging project. Design services under the studio's own name; link to labels in the Brand pod. | AA26: Agency scale | AB26: Commission pricing control; IP of artwork; price pressure | AC26: E01-M-B Business-infrastructure-led

Sheet STAGES
A1: Stage (dropdown values) | B1: Counts when — see UEPAKI_ACQUISITION_FUNNEL_AND_KPI_FRAMEWORK.md
A2: 0 Prospect | B2: Record exists in master
A3: 1 Contactable | B3: Verified C1/C3 route re-checked on outreach day
A4: 2 Contacted | B4: 1:1 human-written message sent
A5: 3 Delivered | B5: No bounce/failure within 48h
A6: 4 Engaged | B6: Any human reply within 21 days (incl. no)
A7: 5 Interested | B7: Positive intent: asks about joining / agrees to call / asks for terms
A8: 6 Info requested | B8: Terms/steps sent on request, or call held
A9: 7 Registration started | B9: Seller account exists for their identity
A10: 8 Registration completed | B10: Flow finished incl. ₹1 + GST web charge
A11: 9 KYC/Approved | B11: Approved to sell under current checks (confirm live checks)
A12: 10 Profile completed | B12: Meets profile standard incl. consent-to-be-named recorded
... A18: X Bounced/undeliverable | B18: Route failed — back to research

Sheet SUMMARY
A1: Composition
A3: Category
A4: Beauty & Makeup | B4: 6 | C4: =B4/25
A5: Fashion & Lifestyle | B5: 5 | C5: =B5/25
A6: Space & Design | B6: 5 | C6: =B6/25
A7: Lens & Motion | B7: 4 | C7: =B7/25
A8: Content & Media | B8: 3 | C8: =B8/25
A9: Digital & Visual Arts | B9: 2 | C9: =B9/25
A11: City
A12: Delhi NCR | B12: 13 | C12: =B12/25
A13: Mumbai | B13: 12 | C13: =B13/25
A15: Segment
A16: BM-INDEPENDENT-MUA | B16: 3 | C16: =B16/25
A17: BM-MEHENDI | B17: 2 | C17: =B17/25
A18: FL-OCCASION-BRIDAL | B18: 2 | C18: =B18/25
A19: SD-PRODUCT-MAKER | B19: 2 | C19: =B19/25
A20: SD-ARCHITECTURE | B20: 2 | C20: =B20/25
A21: LM-WEDDING | B21: 2 | C21: =B21/25
A22: CM-EMCEE-HOST | B22: 2 | C22: =B22/25
A23: BM-STUDIO | B23: 1 | C23: =B23/25
A24: FL-JEWELLERY | B24: 1 | C24: =B24/25
A25: FL-ACCESSORIES | B25: 1 | C25: =B25/25
A26: FL-CONTEMPORARY | B26: 1 | C26: =B26/25
A27: SD-INTERIOR | B27: 1 | C27: =B27/25
... A32: DV-DESIGN-STUDIO | B32: 1 | C32: =B32/25
A34: Ecosystem Pod
A35: Wedding & Occasion | B35: 14 | C35: =B35/25
A36: Home & Space | B36: 6 | C36: =B36/25
A37: Brand & Everyday Style | B37: 5 | C37: =B37/25
A39: Tier
A40: B — Established Independent | B40: 16 | C40: =B40/25
A41: C — Strong Mid-tier | B41: 7 | C41: =B41/25
A42: A — Emerging / High-potential | B42: 2 | C42: =B42/25
A44: Contact Class
A45: C1-DIRECT-VERIFIED | B45: 24 | C45: =B45/25
A46: C3-PRO-SOCIAL | B46: 1 | C46: =B46/25
A48: Acq Priority (OS)
A49: P0 | B49: 25 | C49: =B49/25
A51: Wave
A52: Wave 0 — Controlled pilot | B52: 25 | C52: =B52/25

Sheet FUNNEL_LIVE
A1: Live funnel counts from LIST!Stage (counts records whose current stage ≥ each step)
A3: Stage | B3: Records at this stage now | C3: Reached this stage or later | D3: Step conversion vs previous
A4: 1 Contactable | B4: =COUNTIF(LIST!AE:AE,"1 Contactable") | C4: =SUM(B4:B16)
A5: 2 Contacted | B5: =COUNTIF(LIST!AE:AE,"2 Contacted") | C5: =SUM(B5:B16) | D5: =IF(C4=0,"",C5/C4)
A6: 3 Delivered | B6: =COUNTIF(LIST!AE:AE,"3 Delivered") | C6: =SUM(B6:B16) | D6: =IF(C5=0,"",C6/C5)
A7: 4 Engaged | B7: =COUNTIF(LIST!AE:AE,"4 Engaged") | C7: =SUM(B7:B16) | D7: =IF(C6=0,"",C7/C6)
A8: 5 Interested | B8: =COUNTIF(LIST!AE:AE,"5 Interested") | C8: =SUM(B8:B16) | D8: =IF(C7=0,"",C8/C7)
A9: 6 Info requested | B9: =COUNTIF(LIST!AE:AE,"6 Info requested") | C9: =SUM(B9:B16) | D9: =IF(C8=0,"",C9/C8)
A10: 7 Registration started | B10: =COUNTIF(LIST!AE:AE,"7 Registration started") | C10: =SUM(B10:B16) | D10: =IF(C9=0,"",C10/C9)
A11: 8 Registration completed | B11: =COUNTIF(LIST!AE:AE,"8 Registration completed") | C11: =SUM(B11:B16) | D11: =IF(C10=0,"",C11/C10)
A12: 9 KYC/Approved | B12: =COUNTIF(LIST!AE:AE,"9 KYC/Approved") | C12: =SUM(B12:B16) | D12: =IF(C11=0,"",C12/C11)
A13: 10 Profile completed | B13: =COUNTIF(LIST!AE:AE,"10 Profile completed") | C13: =SUM(B13:B16) | D13: =IF(C12=0,"",C13/C12)
A14: 11 First listing | B14: =COUNTIF(LIST!AE:AE,"11 First listing") | C14: =SUM(B14:B16) | D14: =IF(C13=0,"",C14/C13)
A15: 12 Activated | B15: =COUNTIF(LIST!AE:AE,"12 Activated") | C15: =SUM(B15:B16) | D15: =IF(C14=0,"",C15/C14)
A16: 13 First enquiry/order/booking | B16: =COUNTIF(LIST!AE:AE,"13 First enquiry/order/booking") | C16: =SUM(B16:B16) | D16: =IF(C15=0,"",C16/C15)
A18: Declined | B18: =COUNTIF(LIST!AE:AE,"X Declined")
A19: Do-not-contact | B19: =COUNTIF(LIST!AE:AE,"X Do-not-contact")
A20: Bounced/undeliverable | B20: =COUNTIF(LIST!AE:AE,"X Bounced/undeliverable")
A22: Note: declined/DNC/bounced records drop out of "reached or later"; read step conversions alongside them.
