Workbook

Sheet README
A1: Uepaki — Seller Activation Checklist & Conversion Tracker
A3: Purpose: track every interested professional from interest to activation, first transaction and repeat activity, and calculate conversion KPIs automatically.
A4: How to use: add one row per professional in TRACKER when they become Interested (stage 5 of the funnel). Enter DATES in the white date columns and Y/N in the Y/N columns. Green-header columns are calculated — do not type in them.
A5: ACTIVATED = Approved (KYC + store) + Profile completed + First listing live + Payout details complete + Account standing OK. Recorded automatically with the activation date.
A6: Thresholds in THRESHOLDS are DIAGNOSTIC TEST THRESHOLDS — not Uepaki benchmarks. Replace them with observed rates after Waves 0–1.
A7: Items marked CONFIRM in CHECKLIST_ITEMS depend on product behaviour not yet verified in the live flow (KYC checks Q-KYC/CA-KYC; EV-09 launch features). Confirm before Wave 0.
A8: GST flag: in the current code, order placement requires a verified, active GSTIN (EV-01 c). The flag prompts an escalation — staff must not give tax advice.
A9: Founding column applies the PROPOSED qualifying rule (registration completed + approved + first live listing). It is not in effect until the founder decides FP-QUAL.
A10: No contact details are stored here. Use Prospect ID / Seller ID to link to the master database and the admin system.
A11: Sheets: TRACKER · KPI · THRESHOLDS · CHECKLIST_ITEMS · DETAILED_CHECKLIST (printable, one professional) · ESCALATION_LOG · LISTS

Sheet THRESHOLDS
A1: Diagnostic TEST thresholds — not Uepaki benchmarks. Edit after Waves 0–1.
A2: Conversion | B2: Investigate if below | C2: Healthy signal at or above | D2: Window (days) | E2: Note
A3: Interested → Registration completed | B3: 0.3 | C3: 0.5 | D3: 14
A4: Registration → Approved | B4: 0.7 | C4: 0.85 | D4: 7 | E4: Also investigate if median approval > 3 business days
A5: Approved → Profile completed | B5: 0.6 | C5: 0.8 | D5: 7
A6: Profile → First listing | B6: 0.7 | C6: 0.9 | D6: 7
A7: First listing → Activated | B7: 0.8 | C7: 0.95 | D7: 7
A8: Activated → First transaction | D8: 30 | E8: Post-launch; measure first, then set
A9: First transaction → Repeat | D9: 60 | E9: Measure first
A10: Interested → Activated (overall) | B10: 0.25 | C10: 0.4 | D10: 30
A11: Minimum cohort size to read a rate | B11: 10 | E11: Below this: "Insufficient data"
A12: Days in one stage before STUCK alert | B12: 3 | E12: Operational alert
A13: Median days registration → approval: investigate above | B13: 3 | E13: Calendar days used as proxy for business days

Sheet TRACKER
A1: Prospect / Seller ID | B1: Name (as they use it) | C1: Category | D1: City | E1: Wave / source | F1: Owner | G1: Interested date | H1: Information sent date | I1: Readiness check done (Y/N) | J1: GSTIN status | K1: Registration started date | L1: Registration completed date (₹1 + GST paid) | M1: KYC submitted date | N1: Approved date (KYC + store) | O1: Profile completed date | P1: Portfolio ≥ 6 images (Y/N) | Q1: First listing live date | R1: Payout details complete date | S1: Account standing OK (Y/N) | T1: Consent: named to peers (Y/N) | U1: Consent: social promotion (Y/N) | V1: Consent: WhatsApp updates (Y/N) | W1: First enquiry/order/booking date | X1: Repeat activity date | Y1: Notes | Z1: ACTIVATED? | AA1: Activation date | AB1: Current stage | AC1: Checklist completion | AD1: Days since last step | AE1: Alert | AF1: GST flag | AG1: Days interested → registered | AH1: Days registered → approved | AI1: Days approved → activated | AJ1: Founding (proposed FP-QUAL)
Z2: =IF(A2="","",IF(AND(N2<>"",O2<>"",Q2<>"",R2<>"",S2="Y"),"YES","no")) | AA2: =IF(Z2="YES",MAX(N2,O2,Q2,R2),"") | AB2: =IF(A2="","",IF(X2<>"","13 Repeat activity",IF(W2<>"","12 First enquiry/order/booking",IF(Z2="YES","11 ACTIVATED",IF(Q2<>"","10 First listing live",IF(O2<>"","9 Profile completed",IF(N2<>"","8 Approved",IF(M2<>"","7 KYC submitted",IF(L2<>"","6 Registration completed",IF(K2<>"","5b Registration started",IF(H2<>"","5a Information sent",IF(G2<>"","5 Interested","—")))))))))))) | AC2: =IF(A2="","",(COUNT(G2,H2,K2,L2,M2,N2,O2,Q2,R2)+(I2="Y")+(P2="Y")+(S2="Y"))/12) | AD2: =IF(OR(A2="",COUNT(G2:X2)=0),"",TODAY()-MAX(G2,H2,K2,L2,M2,N2,O2,Q2,R2,W2,X2)) | AE2: =IF(A2="","",IF(AND(Z2<>"YES",AD2<>"",AD2>THRESHOLDS!$B$12),"STUCK — act today","")) | AF2: =IF(A2="","",IF(J2="Active (verified)","",IF(J2="","Ask GST status (readiness R2)","Escalate to founder: orders need verified GSTIN in current code — no tax advice"))) | AG2: =IF(AND(G2<>"",L2<>""),L2-G2,"") | AH2: =IF(AND(L2<>"",N2<>""),N2-L2,"") | AI2: =IF(AND(N2<>"",AA2<>""),AA2-N2,"") | AJ2: =IF(AND(L2<>"",N2<>"",Q2<>""),"Qualifies (if FP-QUAL adopted)","")
Z3: =IF(A3="","",IF(AND(N3<>"",O3<>"",Q3<>"",R3<>"",S3="Y"),"YES","no")) | AA3: =IF(Z3="YES",MAX(N3,O3,Q3,R3),"") | AB3: =IF(A3="","",IF(X3<>"","13 Repeat activity",IF(W3<>"","12 First enquiry/order/booking",IF(Z3="YES","11 ACTIVATED",IF(Q3<>"","10 First listing live",IF(O3<>"","9 Profile completed",IF(N3<>"","8 Approved",IF(M3<>"","7 KYC submitted",IF(L3<>"","6 Registration completed",IF(K3<>"","5b Registration started",IF(H3<>"","5a Information sent",IF(G3<>"","5 Interested","—")))))))))))) | AC3: =IF(A3="","",(COUNT(G3,H3,K3,L3,M3,N3,O3,Q3,R3)+(I3="Y")+(P3="Y")+(S3="Y"))/12) | AD3: =IF(OR(A3="",COUNT(G3:X3)=0),"",TODAY()-MAX(G3,H3,K3,L3,M3,N3,O3,Q3,R3,W3,X3)) | AE3: =IF(A3="","",IF(AND(Z3<>"YES",AD3<>"",AD3>THRESHOLDS!$B$12),"STUCK — act today","")) | AF3: =IF(A3="","",IF(J3="Active (verified)","",IF(J3="","Ask GST status (readiness R2)","Escalate to founder: orders need verified GSTIN in current code — no tax advice"))) | AG3: =IF(AND(G3<>"",L3<>""),L3-G3,"") | AH3: =IF(AND(L3<>"",N3<>""),N3-L3,"") | AI3: =IF(AND(N3<>"",AA3<>""),AA3-N3,"") | AJ3: =IF(AND(L3<>"",N3<>"",Q3<>""),"Qualifies (if FP-QUAL adopted)","")
Z4: =IF(A4="","",IF(AND(N4<>"",O4<>"",Q4<>"",R4<>"",S4="Y"),"YES","no")) | AA4: =IF(Z4="YES",MAX(N4,O4,Q4,R4),"") | AB4: =IF(A4="","",IF(X4<>"","13 Repeat activity",IF(W4<>"","12 First enquiry/order/booking",IF(Z4="YES","11 ACTIVATED",IF(Q4<>"","10 First listing live",IF(O4<>"","9 Profile completed",IF(N4<>"","8 Approved",IF(M4<>"","7 KYC submitted",IF(L4<>"","6 Registration completed",IF(K4<>"","5b Registration started",IF(H4<>"","5a Information sent",IF(G4<>"","5 Interested","—")))))))))))) | AC4: =IF(A4="","",(COUNT(G4,H4,K4,L4,M4,N4,O4,Q4,R4)+(I4="Y")+(P4="Y")+(S4="Y"))/12) | AD4: =IF(OR(A4="",COUNT(G4:X4)=0),"",TODAY()-MAX(G4,H4,K4,L4,M4,N4,O4,Q4,R4,W4,X4)) | AE4: =IF(A4="","",IF(AND(Z4<>"YES",AD4<>"",AD4>THRESHOLDS!$B$12),"STUCK — act today","")) | AF4: =IF(A4="","",IF(J4="Active (verified)","",IF(J4="","Ask GST status (readiness R2)","Escalate to founder: orders need verified GSTIN in current code — no tax advice"))) | AG4: =IF(AND(G4<>"",L4<>""),L4-G4,"") | AH4: =IF(AND(L4<>"",N4<>""),N4-L4,"") | AI4: =IF(AND(N4<>"",AA4<>""),AA4-N4,"") | AJ4: =IF(AND(L4<>"",N4<>"",Q4<>""),"Qualifies (if FP-QUAL adopted)","")
Z5: =IF(A5="","",IF(AND(N5<>"",O5<>"",Q5<>"",R5<>"",S5="Y"),"YES","no")) | AA5: =IF(Z5="YES",MAX(N5,O5,Q5,R5),"") | AB5: =IF(A5="","",IF(X5<>"","13 Repeat activity",IF(W5<>"","12 First enquiry/order/booking",IF(Z5="YES","11 ACTIVATED",IF(Q5<>"","10 First listing live",IF(O5<>"","9 Profile completed",IF(N5<>"","8 Approved",IF(M5<>"","7 KYC submitted",IF(L5<>"","6 Registration completed",IF(K5<>"","5b Registration started",IF(H5<>"","5a Information sent",IF(G5<>"","5 Interested","—")))))))))))) | AC5: =IF(A5="","",(COUNT(G5,H5,K5,L5,M5,N5,O5,Q5,R5)+(I5="Y")+(P5="Y")+(S5="Y"))/12) | AD5: =IF(OR(A5="",COUNT(G5:X5)=0),"",TODAY()-MAX(G5,H5,K5,L5,M5,N5,O5,Q5,R5,W5,X5)) | AE5: =IF(A5="","",IF(AND(Z5<>"YES",AD5<>"",AD5>THRESHOLDS!$B$12),"STUCK — act today","")) | AF5: =IF(A5="","",IF(J5="Active (verified)","",IF(J5="","Ask GST status (readiness R2)","Escalate to founder: orders need verified GSTIN in current code — no tax advice"))) | AG5: =IF(AND(G5<>"",L5<>""),L5-G5,"") | AH5: =IF(AND(L5<>"",N5<>""),N5-L5,"") | AI5: =IF(AND(N5<>"",AA5<>""),AA5-N5,"") | AJ5: =IF(AND(L5<>"",N5<>"",Q5<>""),"Qualifies (if FP-QUAL adopted)","")
Z6: =IF(A6="","",IF(AND(N6<>"",O6<>"",Q6<>"",R6<>"",S6="Y"),"YES","no")) | AA6: =IF(Z6="YES",MAX(N6,O6,Q6,R6),"") | AB6: =IF(A6="","",IF(X6<>"","13 Repeat activity",IF(W6<>"","12 First enquiry/order/booking",IF(Z6="YES","11 ACTIVATED",IF(Q6<>"","10 First listing live",IF(O6<>"","9 Profile completed",IF(N6<>"","8 Approved",IF(M6<>"","7 KYC submitted",IF(L6<>"","6 Registration completed",IF(K6<>"","5b Registration started",IF(H6<>"","5a Information sent",IF(G6<>"","5 Interested","—")))))))))))) | AC6: =IF(A6="","",(COUNT(G6,H6,K6,L6,M6,N6,O6,Q6,R6)+(I6="Y")+(P6="Y")+(S6="Y"))/12) | AD6: =IF(OR(A6="",COUNT(G6:X6)=0),"",TODAY()-MAX(G6,H6,K6,L6,M6,N6,O6,Q6,R6,W6,X6)) | AE6: =IF(A6="","",IF(AND(Z6<>"YES",AD6<>"",AD6>THRESHOLDS!$B$12),"STUCK — act today","")) | AF6: =IF(A6="","",IF(J6="Active (verified)","",IF(J6="","Ask GST status (readiness R2)","Escalate to founder: orders need verified GSTIN in current code — no tax advice"))) | AG6: =IF(AND(G6<>"",L6<>""),L6-G6,"") | AH6: =IF(AND(L6<>"",N6<>""),N6-L6,"") | AI6: =IF(AND(N6<>"",AA6<>""),AA6-N6,"") | AJ6: =IF(AND(L6<>"",N6<>"",Q6<>""),"Qualifies (if FP-QUAL adopted)","")
Z7: =IF(A7="","",IF(AND(N7<>"",O7<>"",Q7<>"",R7<>"",S7="Y"),"YES","no")) | AA7: =IF(Z7="YES",MAX(N7,O7,Q7,R7),"") | AB7: =IF(A7="","",IF(X7<>"","13 Repeat activity",IF(W7<>"","12 First enquiry/order/booking",IF(Z7="YES","11 ACTIVATED",IF(Q7<>"","10 First listing live",IF(O7<>"","9 Profile completed",IF(N7<>"","8 Approved",IF(M7<>"","7 KYC submitted",IF(L7<>"","6 Registration completed",IF(K7<>"","5b Registration started",IF(H7<>"","5a Information sent",IF(G7<>"","5 Interested","—")))))))))))) | AC7: =IF(A7="","",(COUNT(G7,H7,K7,L7,M7,N7,O7,Q7,R7)+(I7="Y")+(P7="Y")+(S7="Y"))/12) | AD7: =IF(OR(A7="",COUNT(G7:X7)=0),"",TODAY()-MAX(G7,H7,K7,L7,M7,N7,O7,Q7,R7,W7,X7)) | AE7: =IF(A7="","",IF(AND(Z7<>"YES",AD7<>"",AD7>THRESHOLDS!$B$12),"STUCK — act today","")) | AF7: =IF(A7="","",IF(J7="Active (verified)","",IF(J7="","Ask GST status (readiness R2)","Escalate to founder: orders need verified GSTIN in current code — no tax advice"))) | AG7: =IF(AND(G7<>"",L7<>""),L7-G7,"") | AH7: =IF(AND(L7<>"",N7<>""),N7-L7,"") | AI7: =IF(AND(N7<>"",AA7<>""),AA7-N7,"") | AJ7: =IF(AND(L7<>"",N7<>"",Q7<>""),"Qualifies (if FP-QUAL adopted)","")
Z8: =IF(A8="","",IF(AND(N8<>"",O8<>"",Q8<>"",R8<>"",S8="Y"),"YES","no")) | AA8: =IF(Z8="YES",MAX(N8,O8,Q8,R8),"") | AB8: =IF(A8="","",IF(X8<>"","13 Repeat activity",IF(W8<>"","12 First enquiry/order/booking",IF(Z8="YES","11 ACTIVATED",IF(Q8<>"","10 First listing live",IF(O8<>"","9 Profile completed",IF(N8<>"","8 Approved",IF(M8<>"","7 KYC submitted",IF(L8<>"","6 Registration completed",IF(K8<>"","5b Registration started",IF(H8<>"","5a Information sent",IF(G8<>"","5 Interested","—")))))))))))) | AC8: =IF(A8="","",(COUNT(G8,H8,K8,L8,M8,N8,O8,Q8,R8)+(I8="Y")+(P8="Y")+(S8="Y"))/12) | AD8: =IF(OR(A8="",COUNT(G8:X8)=0),"",TODAY()-MAX(G8,H8,K8,L8,M8,N8,O8,Q8,R8,W8,X8)) | AE8: =IF(A8="","",IF(AND(Z8<>"YES",AD8<>"",AD8>THRESHOLDS!$B$12),"STUCK — act today","")) | AF8: =IF(A8="","",IF(J8="Active (verified)","",IF(J8="","Ask GST status (readiness R2)","Escalate to founder: orders need verified GSTIN in current code — no tax advice"))) | AG8: =IF(AND(G8<>"",L8<>""),L8-G8,"") | AH8: =IF(AND(L8<>"",N8<>""),N8-L8,"") | AI8: =IF(AND(N8<>"",AA8<>""),AA8-N8,"") | AJ8: =IF(AND(L8<>"",N8<>"",Q8<>""),"Qualifies (if FP-QUAL adopted)","")
Z9: =IF(A9="","",IF(AND(N9<>"",O9<>"",Q9<>"",R9<>"",S9="Y"),"YES","no")) | AA9: =IF(Z9="YES",MAX(N9,O9,Q9,R9),"") | AB9: =IF(A9="","",IF(X9<>"","13 Repeat activity",IF(W9<>"","12 First enquiry/order/booking",IF(Z9="YES","11 ACTIVATED",IF(Q9<>"","10 First listing live",IF(O9<>"","9 Profile completed",IF(N9<>"","8 Approved",IF(M9<>"","7 KYC submitted",IF(L9<>"","6 Registration completed",IF(K9<>"","5b Registration started",IF(H9<>"","5a Information sent",IF(G9<>"","5 Interested","—")))))))))))) | AC9: =IF(A9="","",(COUNT(G9,H9,K9,L9,M9,N9,O9,Q9,R9)+(I9="Y")+(P9="Y")+(S9="Y"))/12) | AD9: =IF(OR(A9="",COUNT(G9:X9)=0),"",TODAY()-MAX(G9,H9,K9,L9,M9,N9,O9,Q9,R9,W9,X9)) | AE9: =IF(A9="","",IF(AND(Z9<>"YES",AD9<>"",AD9>THRESHOLDS!$B$12),"STUCK — act today","")) | AF9: =IF(A9="","",IF(J9="Active (verified)","",IF(J9="","Ask GST status (readiness R2)","Escalate to founder: orders need verified GSTIN in current code — no tax advice"))) | AG9: =IF(AND(G9<>"",L9<>""),L9-G9,"") | AH9: =IF(AND(L9<>"",N9<>""),N9-L9,"") | AI9: =IF(AND(N9<>"",AA9<>""),AA9-N9,"") | AJ9: =IF(AND(L9<>"",N9<>"",Q9<>""),"Qualifies (if FP-QUAL adopted)","")
Z10: =IF(A10="","",IF(AND(N10<>"",O10<>"",Q10<>"",R10<>"",S10="Y"),"YES","no")) | AA10: =IF(Z10="YES",MAX(N10,O10,Q10,R10),"") | AB10: =IF(A10="","",IF(X10<>"","13 Repeat activity",IF(W10<>"","12 First enquiry/order/booking",IF(Z10="YES","11 ACTIVATED",IF(Q10<>"","10 First listing live",IF(O10<>"","9 Profile completed",IF(N10<>"","8 Approved",IF(M10<>"","7 KYC submitted",IF(L10<>"","6 Registration completed",IF(K10<>"","5b Registration started",IF(H10<>"","5a Information sent",IF(G10<>"","5 Interested","—")))))))))))) | AC10: =IF(A10="","",(COUNT(G10,H10,K10,L10,M10,N10,O10,Q10,R10)+(I10="Y")+(P10="Y")+(S10="Y"))/12) | AD10: =IF(OR(A10="",COUNT(G10:X10)=0),"",TODAY()-MAX(G10,H10,K10,L10,M10,N10,O10,Q10,R10,W10,X10)) | AE10: =IF(A10="","",IF(AND(Z10<>"YES",AD10<>"",AD10>THRESHOLDS!$B$12),"STUCK — act today","")) | AF10: =IF(A10="","",IF(J10="Active (verified)","",IF(J10="","Ask GST status (readiness R2)","Escalate to founder: orders need verified GSTIN in current code — no tax advice"))) | AG10: =IF(AND(G10<>"",L10<>""),L10-G10,"") | AH10: =IF(AND(L10<>"",N10<>""),N10-L10,"") | AI10: =IF(AND(N10<>"",AA10<>""),AA10-N10,"") | AJ10: =IF(AND(L10<>"",N10<>"",Q10<>""),"Qualifies (if FP-QUAL adopted)","")
Z11: =IF(A11="","",IF(AND(N11<>"",O11<>"",Q11<>"",R11<>"",S11="Y"),"YES","no")) | AA11: =IF(Z11="YES",MAX(N11,O11,Q11,R11),"") | AB11: =IF(A11="","",IF(X11<>"","13 Repeat activity",IF(W11<>"","12 First enquiry/order/booking",IF(Z11="YES","11 ACTIVATED",IF(Q11<>"","10 First listing live",IF(O11<>"","9 Profile completed",IF(N11<>"","8 Approved",IF(M11<>"","7 KYC submitted",IF(L11<>"","6 Registration completed",IF(K11<>"","5b Registration started",IF(H11<>"","5a Information sent",IF(G11<>"","5 Interested","—")))))))))))) | AC11: =IF(A11="","",(COUNT(G11,H11,K11,L11,M11,N11,O11,Q11,R11)+(I11="Y")+(P11="Y")+(S11="Y"))/12) | AD11: =IF(OR(A11="",COUNT(G11:X11)=0),"",TODAY()-MAX(G11,H11,K11,L11,M11,N11,O11,Q11,R11,W11,X11)) | AE11: =IF(A11="","",IF(AND(Z11<>"YES",AD11<>"",AD11>THRESHOLDS!$B$12),"STUCK — act today","")) | AF11: =IF(A11="","",IF(J11="Active (verified)","",IF(J11="","Ask GST status (readiness R2)","Escalate to founder: orders need verified GSTIN in current code — no tax advice"))) | AG11: =IF(AND(G11<>"",L11<>""),L11-G11,"") | AH11: =IF(AND(L11<>"",N11<>""),N11-L11,"") | AI11: =IF(AND(N11<>"",AA11<>""),AA11-N11,"") | AJ11: =IF(AND(L11<>"",N11<>"",Q11<>""),"Qualifies (if FP-QUAL adopted)","")
Z12: =IF(A12="","",IF(AND(N12<>"",O12<>"",Q12<>"",R12<>"",S12="Y"),"YES","no")) | AA12: =IF(Z12="YES",MAX(N12,O12,Q12,R12),"") | AB12: =IF(A12="","",IF(X12<>"","13 Repeat activity",IF(W12<>"","12 First enquiry/order/booking",IF(Z12="YES","11 ACTIVATED",IF(Q12<>"","10 First listing live",IF(O12<>"","9 Profile completed",IF(N12<>"","8 Approved",IF(M12<>"","7 KYC submitted",IF(L12<>"","6 Registration completed",IF(K12<>"","5b Registration started",IF(H12<>"","5a Information sent",IF(G12<>"","5 Interested","—")))))))))))) | AC12: =IF(A12="","",(COUNT(G12,H12,K12,L12,M12,N12,O12,Q12,R12)+(I12="Y")+(P12="Y")+(S12="Y"))/12) | AD12: =IF(OR(A12="",COUNT(G12:X12)=0),"",TODAY()-MAX(G12,H12,K12,L12,M12,N12,O12,Q12,R12,W12,X12)) | AE12: =IF(A12="","",IF(AND(Z12<>"YES",AD12<>"",AD12>THRESHOLDS!$B$12),"STUCK — act today","")) | AF12: =IF(A12="","",IF(J12="Active (verified)","",IF(J12="","Ask GST status (readiness R2)","Escalate to founder: orders need verified GSTIN in current code — no tax advice"))) | AG12: =IF(AND(G12<>"",L12<>""),L12-G12,"") | AH12: =IF(AND(L12<>"",N12<>""),N12-L12,"") | AI12: =IF(AND(N12<>"",AA12<>""),AA12-N12,"") | AJ12: =IF(AND(L12<>"",N12<>"",Q12<>""),"Qualifies (if FP-QUAL adopted)","")
Z13: =IF(A13="","",IF(AND(N13<>"",O13<>"",Q13<>"",R13<>"",S13="Y"),"YES","no")) | AA13: =IF(Z13="YES",MAX(N13,O13,Q13,R13),"") | AB13: =IF(A13="","",IF(X13<>"","13 Repeat activity",IF(W13<>"","12 First enquiry/order/booking",IF(Z13="YES","11 ACTIVATED",IF(Q13<>"","10 First listing live",IF(O13<>"","9 Profile completed",IF(N13<>"","8 Approved",IF(M13<>"","7 KYC submitted",IF(L13<>"","6 Registration completed",IF(K13<>"","5b Registration started",IF(H13<>"","5a Information sent",IF(G13<>"","5 Interested","—")))))))))))) | AC13: =IF(A13="","",(COUNT(G13,H13,K13,L13,M13,N13,O13,Q13,R13)+(I13="Y")+(P13="Y")+(S13="Y"))/12) | AD13: =IF(OR(A13="",COUNT(G13:X13)=0),"",TODAY()-MAX(G13,H13,K13,L13,M13,N13,O13,Q13,R13,W13,X13)) | AE13: =IF(A13="","",IF(AND(Z13<>"YES",AD13<>"",AD13>THRESHOLDS!$B$12),"STUCK — act today","")) | AF13: =IF(A13="","",IF(J13="Active (verified)","",IF(J13="","Ask GST status (readiness R2)","Escalate to founder: orders need verified GSTIN in current code — no tax advice"))) | AG13: =IF(AND(G13<>"",L13<>""),L13-G13,"") | AH13: =IF(AND(L13<>"",N13<>""),N13-L13,"") | AI13: =IF(AND(N13<>"",AA13<>""),AA13-N13,"") | AJ13: =IF(AND(L13<>"",N13<>"",Q13<>""),"Qualifies (if FP-QUAL adopted)","")
... Z501: =IF(A501="","",IF(AND(N501<>"",O501<>"",Q501<>"",R501<>"",S501="Y"),"YES","no")) | AA501: =IF(Z501="YES",MAX(N501,O501,Q501,R501),"") | AB501: =IF(A501="","",IF(X501<>"","13 Repeat activity",IF(W501<>"","12 First enquiry/order/booking",IF(Z501="YES","11 ACTIVATED",IF(Q501<>"","10 First listing live",IF(O501<>"","9 Profile completed",IF(N501<>"","8 Approved",IF(M501<>"","7 KYC submitted",IF(L501<>"","6 Registration completed",IF(K501<>"","5b Registration started",IF(H501<>"","5a Information sent",IF(G501<>"","5 Interested","—")))))))))))) | AC501: =IF(A501="","",(COUNT(G501,H501,K501,L501,M501,N501,O501,Q501,R501)+(I501="Y")+(P501="Y")+(S501="Y"))/12) | AD501: =IF(OR(A501="",COUNT(G501:X501)=0),"",TODAY()-MAX(G501,H501,K501,L501,M501,N501,O501,Q501,R501,W501,X501)) | AE501: =IF(A501="","",IF(AND(Z501<>"YES",AD501<>"",AD501>THRESHOLDS!$B$12),"STUCK — act today","")) | AF501: =IF(A501="","",IF(J501="Active (verified)","",IF(J501="","Ask GST status (readiness R2)","Escalate to founder: orders need verified GSTIN in current code — no tax advice"))) | AG501: =IF(AND(G501<>"",L501<>""),L501-G501,"") | AH501: =IF(AND(L501<>"",N501<>""),N501-L501,"") | AI501: =IF(AND(N501<>"",AA501<>""),AA501-N501,"") | AJ501: =IF(AND(L501<>"",N501<>"",Q501<>""),"Qualifies (if FP-QUAL adopted)","")

Sheet KPI
A1: Conversion KPIs (cumulative over TRACKER; filter TRACKER by Interested date for a weekly cohort view)
A2: Thresholds are diagnostic TEST thresholds — see THRESHOLDS. "Insufficient data" when the earlier stage has fewer than the minimum cohort size.
A4: Stage | B4: Count
A5: Interested | B5: =COUNT(TRACKER!G2:G501)
A6: Registration completed | B6: =COUNT(TRACKER!L2:L501)
A7: Approved (KYC + store) | B7: =COUNT(TRACKER!N2:N501)
A8: Profile completed | B8: =COUNT(TRACKER!O2:O501)
A9: First listing live | B9: =COUNT(TRACKER!Q2:Q501)
A10: ACTIVATED | B10: =COUNTIF(TRACKER!Z2:Z501,"YES")
A11: First enquiry/order/booking | B11: =COUNT(TRACKER!W2:W501)
A12: Repeat activity | B12: =COUNT(TRACKER!X2:X501)
A14: Conversion | B14: Rate | C14: Investigate below (test) | D14: Healthy at/above (test) | E14: Status
A15: Interested → Registration completed | B15: =IF(B5=0,"",B6/B5) | C15: =THRESHOLDS!$B$3 | D15: =THRESHOLDS!$C$3 | E15: =IF(B5<THRESHOLDS!$B$11,"Insufficient data",IF(B15<C15,"INVESTIGATE",IF(B15>=D15,"Healthy signal","Watch")))
A16: Registration → Approved | B16: =IF(B6=0,"",B7/B6) | C16: =THRESHOLDS!$B$4 | D16: =THRESHOLDS!$C$4 | E16: =IF(B6<THRESHOLDS!$B$11,"Insufficient data",IF(B16<C16,"INVESTIGATE",IF(B16>=D16,"Healthy signal","Watch")))
A17: Approved → Profile completed | B17: =IF(B7=0,"",B8/B7) | C17: =THRESHOLDS!$B$5 | D17: =THRESHOLDS!$C$5 | E17: =IF(B7<THRESHOLDS!$B$11,"Insufficient data",IF(B17<C17,"INVESTIGATE",IF(B17>=D17,"Healthy signal","Watch")))
A18: Profile → First listing | B18: =IF(B8=0,"",B9/B8) | C18: =THRESHOLDS!$B$6 | D18: =THRESHOLDS!$C$6 | E18: =IF(B8<THRESHOLDS!$B$11,"Insufficient data",IF(B18<C18,"INVESTIGATE",IF(B18>=D18,"Healthy signal","Watch")))
A19: First listing → Activated | B19: =IF(B9=0,"",B10/B9) | C19: =THRESHOLDS!$B$7 | D19: =THRESHOLDS!$C$7 | E19: =IF(B9<THRESHOLDS!$B$11,"Insufficient data",IF(B19<C19,"INVESTIGATE",IF(B19>=D19,"Healthy signal","Watch")))
A20: Activated → First transaction | B20: =IF(B10=0,"",B11/B10) | E20: =IF(B10<THRESHOLDS!$B$11,"Insufficient data","Measure — no threshold yet")
A21: First transaction → Repeat | B21: =IF(B11=0,"",B12/B11) | E21: =IF(B11<THRESHOLDS!$B$11,"Insufficient data","Measure — no threshold yet")
A22: Interested → Activated (overall) | B22: =IF(B5=0,"",B10/B5) | C22: =THRESHOLDS!$B$10 | D22: =THRESHOLDS!$C$10 | E22: =IF(B5<THRESHOLDS!$B$11,"Insufficient data",IF(B22<C22,"INVESTIGATE",IF(B22>=D22,"Healthy signal","Watch")))
A24: Median days registration → approved | B24: =IF(COUNT(TRACKER!AH2:AH501)=0,"",MEDIAN(TRACKER!AH2:AH501)) | E24: =IF(B24="","",IF(B24>THRESHOLDS!$B$13,"INVESTIGATE","OK"))
A25: Median days interested → registered | B25: =IF(COUNT(TRACKER!AG2:AG501)=0,"",MEDIAN(TRACKER!AG2:AG501))
A26: Median days approved → activated | B26: =IF(COUNT(TRACKER!AI2:AI501)=0,"",MEDIAN(TRACKER!AI2:AI501))
A27: Professionals currently STUCK | B27: =COUNTIF(TRACKER!AE2:AE501,"STUCK*")
A28: GST status not verified (activated or later) | B28: =COUNTIFS(TRACKER!Z2:Z501,"YES",TRACKER!J2:J501,"<>Active (verified)")
A29: Consent to be named (share of activated) | B29: =IF(B10=0,"",COUNTIFS(TRACKER!Z2:Z501,"YES",TRACKER!T2:T501,"Y")/B10)
A30: Founding qualifiers under proposed FP-QUAL (cap 500) | B30: =COUNTIF(TRACKER!AJ2:AJ501,"Qualifies*")
A33: By category
A34: Category | B34: Interested | C34: Registered | D34: Approved | E34: Activated | F34: Transacting | G34: Interested → Activated | H34: Share of all activated
A35: Fashion & Lifestyle | B35: =COUNTIFS(TRACKER!C2:C501,A35,TRACKER!G2:G501,"<>") | C35: =COUNTIFS(TRACKER!C2:C501,A35,TRACKER!L2:L501,"<>") | D35: =COUNTIFS(TRACKER!C2:C501,A35,TRACKER!N2:N501,"<>") | E35: =COUNTIFS(TRACKER!C2:C501,A35,TRACKER!Z2:Z501,"YES") | F35: =COUNTIFS(TRACKER!C2:C501,A35,TRACKER!W2:W501,"<>") | G35: =IF(B35=0,"",E35/B35) | H35: =IF($B$10=0,"",E35/$B$10)
A36: Space & Design | B36: =COUNTIFS(TRACKER!C2:C501,A36,TRACKER!G2:G501,"<>") | C36: =COUNTIFS(TRACKER!C2:C501,A36,TRACKER!L2:L501,"<>") | D36: =COUNTIFS(TRACKER!C2:C501,A36,TRACKER!N2:N501,"<>") | E36: =COUNTIFS(TRACKER!C2:C501,A36,TRACKER!Z2:Z501,"YES") | F36: =COUNTIFS(TRACKER!C2:C501,A36,TRACKER!W2:W501,"<>") | G36: =IF(B36=0,"",E36/B36) | H36: =IF($B$10=0,"",E36/$B$10)
A37: Digital & Visual Arts | B37: =COUNTIFS(TRACKER!C2:C501,A37,TRACKER!G2:G501,"<>") | C37: =COUNTIFS(TRACKER!C2:C501,A37,TRACKER!L2:L501,"<>") | D37: =COUNTIFS(TRACKER!C2:C501,A37,TRACKER!N2:N501,"<>") | E37: =COUNTIFS(TRACKER!C2:C501,A37,TRACKER!Z2:Z501,"YES") | F37: =COUNTIFS(TRACKER!C2:C501,A37,TRACKER!W2:W501,"<>") | G37: =IF(B37=0,"",E37/B37) | H37: =IF($B$10=0,"",E37/$B$10)
A38: Beauty & Makeup | B38: =COUNTIFS(TRACKER!C2:C501,A38,TRACKER!G2:G501,"<>") | C38: =COUNTIFS(TRACKER!C2:C501,A38,TRACKER!L2:L501,"<>") | D38: =COUNTIFS(TRACKER!C2:C501,A38,TRACKER!N2:N501,"<>") | E38: =COUNTIFS(TRACKER!C2:C501,A38,TRACKER!Z2:Z501,"YES") | F38: =COUNTIFS(TRACKER!C2:C501,A38,TRACKER!W2:W501,"<>") | G38: =IF(B38=0,"",E38/B38) | H38: =IF($B$10=0,"",E38/$B$10)
A39: Lens & Motion | B39: =COUNTIFS(TRACKER!C2:C501,A39,TRACKER!G2:G501,"<>") | C39: =COUNTIFS(TRACKER!C2:C501,A39,TRACKER!L2:L501,"<>") | D39: =COUNTIFS(TRACKER!C2:C501,A39,TRACKER!N2:N501,"<>") | E39: =COUNTIFS(TRACKER!C2:C501,A39,TRACKER!Z2:Z501,"YES") | F39: =COUNTIFS(TRACKER!C2:C501,A39,TRACKER!W2:W501,"<>") | G39: =IF(B39=0,"",E39/B39) | H39: =IF($B$10=0,"",E39/$B$10)
A40: Content & Media | B40: =COUNTIFS(TRACKER!C2:C501,A40,TRACKER!G2:G501,"<>") | C40: =COUNTIFS(TRACKER!C2:C501,A40,TRACKER!L2:L501,"<>") | D40: =COUNTIFS(TRACKER!C2:C501,A40,TRACKER!N2:N501,"<>") | E40: =COUNTIFS(TRACKER!C2:C501,A40,TRACKER!Z2:Z501,"YES") | F40: =COUNTIFS(TRACKER!C2:C501,A40,TRACKER!W2:W501,"<>") | G40: =IF(B40=0,"",E40/B40) | H40: =IF($B$10=0,"",E40/$B$10)
A42: Guardrail: no category above 30% of activated (recommendation).

Sheet CHECKLIST_ITEMS
A1: Code | B1: Block | C1: Item | D1: Evidence | E1: Owner | F1: Requirement status
A2: ON-01 | B2: Onboarding | C2: Interest recorded with date and source message ID | D2: Tracker entry | E2: Onboarding lead | F2: Required
A3: ON-02 | B3: Onboarding | C3: Information note sent (interim note until seller terms approved) | D3: Sent copy | E3: Onboarding lead | F3: Required
A4: ON-03 | B4: Onboarding | C4: Readiness check R1–R7 completed | D4: Notes in tracker | E4: Onboarding lead | F4: Required
A5: ON-04 | B5: Onboarding | C5: Registration link sent (web path recommended until SUB-06 aligned) | D5: Message | E5: Onboarding lead | F5: CONFIRM path
A6: RG-05 | B6: Registration | C6: Registration completed, ₹1 + GST paid online | D6: Admin record / payment confirmation | E6: Onboarding lead | F6: Decided (SUB-01); EV-01 a
A7: KY-06 | B7: KYC | C7: Legal and business names match | D7: Admin | E7: Onboarding lead | F7: CONFIRM (Q-KYC)
A8: KY-07 | B8: KYC | C8: PAN provided/verified | D8: Admin | E8: Onboarding lead | F8: CONFIRM (CA-KYC)
A9: KY-08 | B9: KYC | C9: GSTIN status recorded; verified/active needed for orders in current code | D9: Admin / tracker column J | E9: Onboarding lead | F9: Code (EV-01 c); policy OPEN (CA-KYC)
A10: KY-09 | B10: KYC | C10: Bank account for payouts (name match) | D10: Admin | E10: Onboarding lead | F10: CONFIRM
A11: KY-10 | B11: KYC | C11: Address / city | D11: Admin | E11: Onboarding lead | F11: CONFIRM
A12: KY-11 | B12: KYC | C12: Category selected correctly | D12: Admin | E12: Onboarding lead | F12: Required (category drives features)
... A34: AC-33 | B34: Activation | C34: 7-day post-activation check-in and survey | D34: Notes | E34: Onboarding lead | F34: Recommendation

Sheet DETAILED_CHECKLIST
A1: Onboarding checklist — one professional (print or copy this sheet)
A3: Prospect / Seller ID
A4: Name
A5: Category / City
A6: Onboarding owner
A8: Code | B8: Item | C8: Done (Y/N) | D8: Date | E8: Note
A9: ON-01 | B9: Interest recorded with date and source message ID
A10: ON-02 | B10: Information note sent (interim note until seller terms approved)
A11: ON-03 | B11: Readiness check R1–R7 completed
A12: ON-04 | B12: Registration link sent (web path recommended until SUB-06 aligned)
A13: RG-05 | B13: Registration completed, ₹1 + GST paid online
A14: KY-06 | B14: Legal and business names match
A15: KY-07 | B15: PAN provided/verified
A16: KY-08 | B16: GSTIN status recorded; verified/active needed for orders in current code
A17: KY-09 | B17: Bank account for payouts (name match)
A18: KY-10 | B18: Address / city
A19: KY-11 | B19: Category selected correctly
A20: AP-12 | B20: Store approved (required for product creation)
... A41: AC-33 | B41: 7-day post-activation check-in and survey
A43: Completion | B43: =COUNTIF(C9:C41,"Y")/33

Sheet ESCALATION_LOG
A1: Escalation ID | B1: Prospect / Seller ID | C1: Stage | D1: Issue | E1: Trigger type | F1: Level | G1: Owner | H1: Opened | I1: Professional last updated | J1: Closed | K1: Status | L1: Outcome | M1: Days open | O1: Triggers: payment failure · KYC rejection · store approval > 3 business days · any GST question · off-platform contact request (SP-4a) · data/IP question · complaint · "I was told it was free"
M2: =IF(H2="","",IF(J2<>"",J2-H2,TODAY()-H2))
M3: =IF(H3="","",IF(J3<>"",J3-H3,TODAY()-H3))
M4: =IF(H4="","",IF(J4<>"",J4-H4,TODAY()-H4))
M5: =IF(H5="","",IF(J5<>"",J5-H5,TODAY()-H5))
M6: =IF(H6="","",IF(J6<>"",J6-H6,TODAY()-H6))
M7: =IF(H7="","",IF(J7<>"",J7-H7,TODAY()-H7))
M8: =IF(H8="","",IF(J8<>"",J8-H8,TODAY()-H8))
M9: =IF(H9="","",IF(J9<>"",J9-H9,TODAY()-H9))
M10: =IF(H10="","",IF(J10<>"",J10-H10,TODAY()-H10))
M11: =IF(H11="","",IF(J11<>"",J11-H11,TODAY()-H11))
M12: =IF(H12="","",IF(J12<>"",J12-H12,TODAY()-H12))
M13: =IF(H13="","",IF(J13<>"",J13-H13,TODAY()-H13))
... M301: =IF(H301="","",IF(J301<>"",J301-H301,TODAY()-H301))

Sheet LISTS
A1: Category | B1: Y/N | C1: GSTIN status | D1: Escalation level | E1: Escalation status
A2: Fashion & Lifestyle | B2: Y | C2: Active (verified) | D2: L1 Onboarding lead | E2: Open
A3: Space & Design | B3: N | C3: Not registered | D3: L2 Founder | E3: Waiting on professional
A4: Digital & Visual Arts | C4: Applied / pending | D4: L3 Engineering | E4: Resolved
A5: Beauty & Makeup | C5: Unknown | D5: Legal team (Q-REVIEWER) | E5: Closed — not resolvable
A6: Lens & Motion
A7: Content & Media
